// class version 50.0 (50)
// access flags 0x21
public class brw implements bwe  {

  // compiled from: RenderItem.java
  // access flags 0x0
  INNERCLASS brw$9 null null
  // access flags 0x0
  INNERCLASS brw$8 null null
  // access flags 0x0
  INNERCLASS brw$7 null null
  // access flags 0x0
  INNERCLASS brw$6 null null
  // access flags 0x0
  INNERCLASS brw$5 null null
  // access flags 0x0
  INNERCLASS brw$4 null null
  // access flags 0x0
  INNERCLASS brw$3 null null
  // access flags 0x0
  INNERCLASS brw$2 null null
  // access flags 0x0
  INNERCLASS brw$1 null null
  // access flags 0x4019
  public final static enum INNERCLASS bop$b bop b
  // access flags 0x4019
  public final static enum INNERCLASS bnf$r bnf r
  // access flags 0x4019
  public final static enum INNERCLASS bnf$l bnf l
  // access flags 0x4019
  public final static enum INNERCLASS bnf$i bnf i
  // access flags 0x4019
  public final static enum INNERCLASS apk$a apk a
  // access flags 0x4019
  public final static enum INNERCLASS akt$a akt a
  // access flags 0x4019
  public final static enum INNERCLASS akw$b akw b
  // access flags 0x4019
  public final static enum INNERCLASS anj$a anj a
  // access flags 0x4409
  public static abstract enum INNERCLASS amt$a amt a
  // access flags 0x4019
  public final static enum INNERCLASS anp$a anp a
  // access flags 0x4019
  public final static enum INNERCLASS ans$a ans a
  // access flags 0x4019
  public final static enum INNERCLASS alm$a alm a
  // access flags 0x4019
  public final static enum INNERCLASS aof$a aof a
  // access flags 0x4019
  public final static enum INNERCLASS aog$a aog a
  // access flags 0x4019
  public final static enum INNERCLASS anv$a anv a
  // access flags 0x4019
  public final static enum INNERCLASS aox$a aox a
  // access flags 0x4019
  public final static enum INNERCLASS aoy$a aoy a
  // access flags 0x4019
  public final static enum INNERCLASS apa$a apa a
  // access flags 0x4019
  public final static enum INNERCLASS anb$a anb a
  // access flags 0x4019
  public final static enum INNERCLASS apc$a apc a
  // access flags 0x4019
  public final static enum INNERCLASS adh$a adh a
  // access flags 0x4019
  public final static enum INNERCLASS amh$a amh a
  // access flags 0x4019
  public final static enum INNERCLASS aqp$a aqp a

  // access flags 0x1A
  private final static Lkl; b

  // access flags 0x2
  private Z c

  // access flags 0x1
  public F a

  // access flags 0x12
  private final Lbni; d

  // access flags 0x12
  private final Lbvf; e

  // access flags 0x12
  private final Lbcp; f

  // access flags 0x2
  private Lkl; modelLocation

  // access flags 0x2
  private Z renderItemGui

  // access flags 0x1
  public Lbxp; modelManager

  // access flags 0x2
  private Z renderModelHasEmissive

  // access flags 0x2
  private Z renderModelEmissive

  // access flags 0x1
  public <init>(Lbvf;Lbxp;Lbcp;)V
   L0
    LINENUMBER 89 L0
    ALOAD 0
    INVOKESPECIAL java/lang/Object.<init> ()V
   L1
    LINENUMBER 72 L1
    ALOAD 0
    ICONST_1
    PUTFIELD brw.c : Z
   L2
    LINENUMBER 81 L2
    ALOAD 0
    ACONST_NULL
    PUTFIELD brw.modelLocation : Lkl;
   L3
    LINENUMBER 82 L3
    ALOAD 0
    ICONST_0
    PUTFIELD brw.renderItemGui : Z
   L4
    LINENUMBER 83 L4
    ALOAD 0
    ACONST_NULL
    PUTFIELD brw.modelManager : Lbxp;
   L5
    LINENUMBER 84 L5
    ALOAD 0
    ICONST_0
    PUTFIELD brw.renderModelHasEmissive : Z
   L6
    LINENUMBER 85 L6
    ALOAD 0
    ICONST_0
    PUTFIELD brw.renderModelEmissive : Z
   L7
    LINENUMBER 90 L7
    ALOAD 0
    ALOAD 1
    PUTFIELD brw.e : Lbvf;
   L8
    LINENUMBER 92 L8
    ALOAD 0
    ALOAD 2
    PUTFIELD brw.modelManager : Lbxp;
   L9
    LINENUMBER 94 L9
    GETSTATIC net/optifine/reflect/Reflector.ItemModelMesherForge_Constructor : Lnet/optifine/reflect/ReflectorConstructor;
    INVOKEVIRTUAL net/optifine/reflect/ReflectorConstructor.exists ()Z
    IFEQ L10
   L11
    LINENUMBER 95 L11
    ALOAD 0
    GETSTATIC net/optifine/reflect/Reflector.ItemModelMesherForge_Constructor : Lnet/optifine/reflect/ReflectorConstructor;
    ICONST_1
    ANEWARRAY java/lang/Object
    DUP
    ICONST_0
    ALOAD 2
    AASTORE
    INVOKESTATIC net/optifine/reflect/Reflector.newInstance (Lnet/optifine/reflect/ReflectorConstructor;[Ljava/lang/Object;)Ljava/lang/Object;
    CHECKCAST bni
    PUTFIELD brw.d : Lbni;
    GOTO L12
   L10
    LINENUMBER 99 L10
   FRAME FULL [brw bvf bxp bcp] []
    ALOAD 0
    NEW bni
    DUP
    ALOAD 2
    INVOKESPECIAL bni.<init> (Lbxp;)V
    PUTFIELD brw.d : Lbni;
   L12
    LINENUMBER 103 L12
   FRAME FULL [brw bvf bxp bcp] []
    ALOAD 0
    INVOKESPECIAL brw.b ()V
   L13
    LINENUMBER 104 L13
    ALOAD 0
    ALOAD 3
    PUTFIELD brw.f : Lbcp;
   L14
    LINENUMBER 105 L14
    RETURN
   L15
    LOCALVARIABLE this Lbrw; L0 L15 0
    LOCALVARIABLE p_i46552_1_ Lbvf; L0 L15 1
    LOCALVARIABLE p_i46552_2_ Lbxp; L0 L15 2
    LOCALVARIABLE p_i46552_3_ Lbcp; L0 L15 3
    MAXSTACK = 6
    MAXLOCALS = 4

  // access flags 0x1
  public a(Z)V
   L0
    LINENUMBER 112 L0
    ALOAD 0
    ILOAD 1
    PUTFIELD brw.c : Z
   L1
    LINENUMBER 113 L1
    RETURN
   L2
    LOCALVARIABLE this Lbrw; L0 L2 0
    LOCALVARIABLE isNot Z L0 L2 1
    MAXSTACK = 2
    MAXLOCALS = 2

  // access flags 0x1
  public a()Lbni;
   L0
    LINENUMBER 117 L0
    ALOAD 0
    GETFIELD brw.d : Lbni;
    ARETURN
   L1
    LOCALVARIABLE this Lbrw; L0 L1 0
    MAXSTACK = 1
    MAXLOCALS = 1

  // access flags 0x4
  protected a(Lado;ILjava/lang/String;)V
   L0
    LINENUMBER 122 L0
    ALOAD 0
    GETFIELD brw.d : Lbni;
    ALOAD 1
    ILOAD 2
    NEW bxq
    DUP
    ALOAD 3
    LDC "inventory"
    INVOKESPECIAL bxq.<init> (Ljava/lang/String;Ljava/lang/String;)V
    INVOKEVIRTUAL bni.a (Lado;ILbxq;)V
   L1
    LINENUMBER 123 L1
    RETURN
   L2
    LOCALVARIABLE this Lbrw; L0 L2 0
    LOCALVARIABLE itm Lado; L0 L2 1
    LOCALVARIABLE subType I L0 L2 2
    LOCALVARIABLE identifier Ljava/lang/String; L0 L2 3
    MAXSTACK = 7
    MAXLOCALS = 4

  // access flags 0x4
  protected a(Lajt;ILjava/lang/String;)V
   L0
    LINENUMBER 127 L0
    ALOAD 0
    ALOAD 1
    INVOKESTATIC ado.a (Lajt;)Lado;
    ILOAD 2
    ALOAD 3
    INVOKEVIRTUAL brw.a (Lado;ILjava/lang/String;)V
   L1
    LINENUMBER 128 L1
    RETURN
   L2
    LOCALVARIABLE this Lbrw; L0 L2 0
    LOCALVARIABLE blk Lajt; L0 L2 1
    LOCALVARIABLE subType I L0 L2 2
    LOCALVARIABLE identifier Ljava/lang/String; L0 L2 3
    MAXSTACK = 4
    MAXLOCALS = 4

  // access flags 0x2
  private a(Lajt;Ljava/lang/String;)V
   L0
    LINENUMBER 132 L0
    ALOAD 0
    ALOAD 1
    ICONST_0
    ALOAD 2
    INVOKEVIRTUAL brw.a (Lajt;ILjava/lang/String;)V
   L1
    LINENUMBER 133 L1
    RETURN
   L2
    LOCALVARIABLE this Lbrw; L0 L2 0
    LOCALVARIABLE blk Lajt; L0 L2 1
    LOCALVARIABLE identifier Ljava/lang/String; L0 L2 2
    MAXSTACK = 4
    MAXLOCALS = 3

  // access flags 0x2
  private a(Lado;Ljava/lang/String;)V
   L0
    LINENUMBER 137 L0
    ALOAD 0
    ALOAD 1
    ICONST_0
    ALOAD 2
    INVOKEVIRTUAL brw.a (Lado;ILjava/lang/String;)V
   L1
    LINENUMBER 138 L1
    RETURN
   L2
    LOCALVARIABLE this Lbrw; L0 L2 0
    LOCALVARIABLE itm Lado; L0 L2 1
    LOCALVARIABLE identifier Ljava/lang/String; L0 L2 2
    MAXSTACK = 4
    MAXLOCALS = 3

  // access flags 0x2
  private a(Lbxl;Ladq;)V
   L0
    LINENUMBER 142 L0
    ALOAD 0
    ALOAD 1
    ICONST_M1
    ALOAD 2
    INVOKESPECIAL brw.a (Lbxl;ILadq;)V
   L1
    LINENUMBER 143 L1
    RETURN
   L2
    LOCALVARIABLE this Lbrw; L0 L2 0
    LOCALVARIABLE model Lbxl; L0 L2 1
    LOCALVARIABLE stack Ladq; L0 L2 2
    MAXSTACK = 4
    MAXLOCALS = 3

  // access flags 0x1
  public a(Lbxl;I)V
   L0
    LINENUMBER 148 L0
    ALOAD 0
    ALOAD 1
    ILOAD 2
    ACONST_NULL
    CHECKCAST adq
    INVOKESPECIAL brw.a (Lbxl;ILadq;)V
   L1
    LINENUMBER 149 L1
    RETURN
   L2
    LOCALVARIABLE this Lbrw; L0 L2 0
    LOCALVARIABLE model Lbxl; L0 L2 1
    LOCALVARIABLE color I L0 L2 2
    MAXSTACK = 4
    MAXLOCALS = 3

  // access flags 0x2
  private a(Lbxl;ILadq;)V
   L0
    LINENUMBER 160 L0
    INVOKESTATIC bnr.a ()Lbnr;
    ASTORE 4
   L1
    LINENUMBER 161 L1
    ALOAD 4
    INVOKEVIRTUAL bnr.c ()Lbmx;
    ASTORE 5
   L2
    LINENUMBER 163 L2
    INVOKESTATIC bcd.z ()Lbcd;
    INVOKEVIRTUAL bcd.R ()Lbvd;
    INVOKEVIRTUAL bvd.isTextureBound ()Z
    ISTORE 6
   L3
    LINENUMBER 165 L3
    INVOKESTATIC Config.isMultiTexture ()Z
    IFEQ L4
    ILOAD 6
    IFEQ L4
    ICONST_1
    GOTO L5
   L4
   FRAME FULL [brw bxl I adq bnr bmx I] []
    ICONST_0
   L5
   FRAME FULL [brw bxl I adq bnr bmx I] [I]
    ISTORE 7
   L6
    LINENUMBER 166 L6
    ILOAD 7
    IFEQ L7
   L8
    LINENUMBER 167 L8
    ALOAD 5
    GETSTATIC ahm.a : Lahm;
    INVOKEVIRTUAL bmx.setBlockLayer (Lahm;)V
   L7
    LINENUMBER 169 L7
   FRAME FULL [brw bxl I adq bnr bmx I I] []
    ALOAD 5
    BIPUSH 7
    GETSTATIC bvm.b : Lbvo;
    INVOKEVIRTUAL bmx.a (ILbvo;)V
   L9
    LINENUMBER 172 L9
    GETSTATIC cs.n : [Lcs;
    ASTORE 8
   L10
    ALOAD 8
    ARRAYLENGTH
    ISTORE 9
   L11
    ICONST_0
    ISTORE 10
   L12
   FRAME FULL [brw bxl I adq bnr bmx I I [Lcs; I I] []
    ILOAD 10
    ILOAD 9
    IF_ICMPGE L13
    ALOAD 8
    ILOAD 10
    AALOAD
    ASTORE 11
   L14
    LINENUMBER 174 L14
    ALOAD 0
    ALOAD 5
    ALOAD 1
    ACONST_NULL
    CHECKCAST ard
    ALOAD 11
    LCONST_0
    INVOKEINTERFACE bxl.a (Lard;Lcs;J)Ljava/util/List;
    ILOAD 2
    ALOAD 3
    INVOKESPECIAL brw.a (Lbmx;Ljava/util/List;ILadq;)V
   L15
    LINENUMBER 172 L15
    IINC 10 1
    GOTO L12
   L13
    LINENUMBER 177 L13
   FRAME FULL [brw bxl I adq bnr bmx I I [Lcs; I I] []
    ALOAD 0
    ALOAD 5
    ALOAD 1
    ACONST_NULL
    CHECKCAST ard
    ACONST_NULL
    CHECKCAST cs
    LCONST_0
    INVOKEINTERFACE bxl.a (Lard;Lcs;J)Ljava/util/List;
    ILOAD 2
    ALOAD 3
    INVOKESPECIAL brw.a (Lbmx;Ljava/util/List;ILadq;)V
   L16
    LINENUMBER 178 L16
    ALOAD 4
    INVOKEVIRTUAL bnr.b ()V
   L17
    LINENUMBER 180 L17
    ILOAD 7
    IFEQ L18
   L19
    LINENUMBER 183 L19
    ALOAD 5
    ACONST_NULL
    INVOKEVIRTUAL bmx.setBlockLayer (Lahm;)V
   L20
    LINENUMBER 185 L20
    INVOKESTATIC bnf.bindCurrentTexture ()V
   L18
    LINENUMBER 187 L18
   FRAME FULL [brw bxl I adq bnr bmx I I [Lcs; I I] []
    RETURN
   L21
    LOCALVARIABLE enumfacing Lcs; L14 L15 11
    LOCALVARIABLE arr$ [Lcs; L10 L13 8
    LOCALVARIABLE len$ I L11 L13 9
    LOCALVARIABLE i$ I L12 L13 10
    LOCALVARIABLE this Lbrw; L0 L21 0
    LOCALVARIABLE model Lbxl; L0 L21 1
    LOCALVARIABLE color I L0 L21 2
    LOCALVARIABLE stack Ladq; L0 L21 3
    LOCALVARIABLE tessellator Lbnr; L1 L21 4
    LOCALVARIABLE vertexbuffer Lbmx; L2 L21 5
    LOCALVARIABLE renderTextureMap Z L3 L21 6
    LOCALVARIABLE multiTexture Z L6 L21 7
    MAXSTACK = 7
    MAXLOCALS = 12

  // access flags 0x1
  public a(Ladq;Lbxl;)V
   L0
    LINENUMBER 191 L0
    ALOAD 1
    IFNULL L1
   L2
    LINENUMBER 193 L2
    INVOKESTATIC bnf.G ()V
   L3
    LINENUMBER 194 L3
    LDC -0.5
    LDC -0.5
    LDC -0.5
    INVOKESTATIC bnf.c (FFF)V
   L4
    LINENUMBER 196 L4
    ALOAD 2
    INVOKEINTERFACE bxl.c ()Z
    IFEQ L5
   L6
    LINENUMBER 198 L6
    FCONST_1
    FCONST_1
    FCONST_1
    FCONST_1
    INVOKESTATIC bnf.c (FFFF)V
   L7
    LINENUMBER 199 L7
    INVOKESTATIC bnf.D ()V
    ALOAD 2
    INSTANCEOF codechicken/lib/render/IItemRenderer
    IFEQ L8
    ALOAD 2
    ALOAD 1
    INVOKEINTERFACE codechicken/lib/render/IItemRenderer.renderItem (Lnet/minecraft/item/ItemStack;)V
    GOTO L9
   L8
    LINENUMBER 200 L8
   FRAME FULL [brw adq bxl] []
    ALOAD 2
    INSTANCEOF codechicken/lib/render/IItemRenderer
    IFEQ L10
    ALOAD 2
    ALOAD 1
    INVOKEINTERFACE codechicken/lib/render/IItemRenderer.renderItem (Lnet/minecraft/item/ItemStack;)V
    GOTO L9
   L10
   FRAME FULL [brw adq bxl] []
    GETSTATIC bnb.a : Lbnb;
    ALOAD 1
    INVOKEVIRTUAL bnb.a (Ladq;)V
    GOTO L9
   L5
    LINENUMBER 205 L5
   FRAME FULL [brw adq bxl] []
    INVOKESTATIC Config.isCustomItems ()Z
    IFEQ L11
   L12
    LINENUMBER 207 L12
    ALOAD 1
    ALOAD 2
    ALOAD 0
    GETFIELD brw.modelLocation : Lkl;
    ICONST_0
    INVOKESTATIC net/optifine/CustomItems.getCustomItemModel (Ladq;Lbxl;Lkl;Z)Lbxl;
    ASTORE 2
   L13
    LINENUMBER 209 L13
    ALOAD 0
    ACONST_NULL
    PUTFIELD brw.modelLocation : Lkl;
   L11
    LINENUMBER 212 L11
   FRAME FULL [brw adq bxl] []
    ALOAD 0
    ICONST_0
    PUTFIELD brw.renderModelHasEmissive : Z
   L14
    LINENUMBER 214 L14
    ALOAD 0
    ALOAD 2
    ALOAD 1
    INVOKESPECIAL brw.a (Lbxl;Ladq;)V
   L15
    LINENUMBER 216 L15
    ALOAD 0
    GETFIELD brw.renderModelHasEmissive : Z
    IFEQ L16
   L17
    LINENUMBER 219 L17
    GETSTATIC bze.lastBrightnessX : F
    FSTORE 3
   L18
    LINENUMBER 220 L18
    GETSTATIC bze.lastBrightnessY : F
    FSTORE 4
   L19
    LINENUMBER 221 L19
    GETSTATIC bze.r : I
    LDC 240.0
    FLOAD 4
    INVOKESTATIC bze.a (IFF)V
   L20
    LINENUMBER 223 L20
    ALOAD 0
    ICONST_1
    PUTFIELD brw.renderModelEmissive : Z
   L21
    LINENUMBER 224 L21
    ALOAD 0
    ALOAD 2
    ALOAD 1
    INVOKESPECIAL brw.a (Lbxl;Ladq;)V
   L22
    LINENUMBER 225 L22
    ALOAD 0
    ICONST_0
    PUTFIELD brw.renderModelEmissive : Z
   L23
    LINENUMBER 227 L23
    GETSTATIC bze.r : I
    FLOAD 3
    FLOAD 4
    INVOKESTATIC bze.a (IFF)V
   L16
    LINENUMBER 231 L16
   FRAME FULL [brw adq bxl] []
    ALOAD 1
    INVOKEVIRTUAL adq.t ()Z
    IFEQ L9
   L24
    LINENUMBER 234 L24
    INVOKESTATIC Config.isCustomItems ()Z
    IFEQ L25
    ALOAD 0
    ALOAD 1
    ALOAD 2
    INVOKESTATIC net/optifine/CustomItems.renderCustomEffect (Lbrw;Ladq;Lbxl;)Z
    IFNE L9
   L25
    LINENUMBER 236 L25
   FRAME FULL [brw adq bxl] []
    ALOAD 0
    ALOAD 2
    INVOKESPECIAL brw.a (Lbxl;)V
   L9
    LINENUMBER 240 L9
   FRAME FULL [brw adq bxl] []
    INVOKESTATIC bnf.H ()V
   L1
    LINENUMBER 242 L1
   FRAME FULL [brw adq bxl] []
    RETURN
   L26
    LOCALVARIABLE lightMapX F L18 L16 3
    LOCALVARIABLE lightMapY F L19 L16 4
    LOCALVARIABLE this Lbrw; L0 L26 0
    LOCALVARIABLE stack Ladq; L0 L26 1
    LOCALVARIABLE model Lbxl; L0 L26 2
    MAXSTACK = 4
    MAXLOCALS = 5

  // access flags 0x2
  private a(Lbxl;)V
   L0
    LINENUMBER 247 L0
    INVOKESTATIC Config.isCustomItems ()Z
    IFEQ L1
   L2
    LINENUMBER 249 L2
    INVOKESTATIC net/optifine/CustomItems.isUseGlint ()Z
    IFNE L1
   L3
    LINENUMBER 250 L3
    RETURN
   L1
    LINENUMBER 253 L1
   FRAME FULL [brw bxl] []
    INVOKESTATIC Config.isShaders ()Z
    IFEQ L4
   L5
    LINENUMBER 255 L5
    GETSTATIC net/optifine/shaders/Shaders.isShadowPass : Z
    IFEQ L4
   L6
    LINENUMBER 256 L6
    RETURN
   L4
    LINENUMBER 259 L4
   FRAME FULL [brw bxl] []
    ICONST_0
    INVOKESTATIC bnf.a (Z)V
   L7
    LINENUMBER 260 L7
    SIPUSH 514
    INVOKESTATIC bnf.c (I)V
   L8
    LINENUMBER 261 L8
    INVOKESTATIC bnf.g ()V
   L9
    LINENUMBER 262 L9
    GETSTATIC bnf$r.n : Lbnf$r;
    GETSTATIC bnf$l.e : Lbnf$l;
    INVOKESTATIC bnf.a (Lbnf$r;Lbnf$l;)V
   L10
    LINENUMBER 263 L10
    ALOAD 0
    GETFIELD brw.e : Lbvf;
    GETSTATIC brw.b : Lkl;
    INVOKEVIRTUAL bvf.a (Lkl;)V
   L11
    LINENUMBER 265 L11
    INVOKESTATIC Config.isShaders ()Z
    IFEQ L12
   L13
    LINENUMBER 267 L13
    ALOAD 0
    GETFIELD brw.renderItemGui : Z
    IFNE L12
   L14
    LINENUMBER 268 L14
    INVOKESTATIC net/optifine/shaders/ShadersRender.renderEnchantedGlintBegin ()V
   L12
    LINENUMBER 271 L12
   FRAME FULL [brw bxl] []
    SIPUSH 5890
    INVOKESTATIC bnf.n (I)V
   L15
    LINENUMBER 272 L15
    INVOKESTATIC bnf.G ()V
   L16
    LINENUMBER 273 L16
    LDC 8.0
    LDC 8.0
    LDC 8.0
    INVOKESTATIC bnf.b (FFF)V
   L17
    LINENUMBER 274 L17
    INVOKESTATIC bcd.I ()J
    LDC 3000
    LREM
    L2F
    LDC 3000.0
    FDIV
    LDC 8.0
    FDIV
    FSTORE 2
   L18
    LINENUMBER 275 L18
    FLOAD 2
    FCONST_0
    FCONST_0
    INVOKESTATIC bnf.c (FFF)V
   L19
    LINENUMBER 276 L19
    LDC -50.0
    FCONST_0
    FCONST_0
    FCONST_1
    INVOKESTATIC bnf.b (FFFF)V
   L20
    LINENUMBER 277 L20
    ALOAD 0
    ALOAD 1
    LDC -8372020
    INVOKEVIRTUAL brw.a (Lbxl;I)V
   L21
    LINENUMBER 278 L21
    INVOKESTATIC bnf.H ()V
   L22
    LINENUMBER 279 L22
    INVOKESTATIC bnf.G ()V
   L23
    LINENUMBER 280 L23
    LDC 8.0
    LDC 8.0
    LDC 8.0
    INVOKESTATIC bnf.b (FFF)V
   L24
    LINENUMBER 281 L24
    INVOKESTATIC bcd.I ()J
    LDC 4873
    LREM
    L2F
    LDC 4873.0
    FDIV
    LDC 8.0
    FDIV
    FSTORE 3
   L25
    LINENUMBER 282 L25
    FLOAD 3
    FNEG
    FCONST_0
    FCONST_0
    INVOKESTATIC bnf.c (FFF)V
   L26
    LINENUMBER 283 L26
    LDC 10.0
    FCONST_0
    FCONST_0
    FCONST_1
    INVOKESTATIC bnf.b (FFFF)V
   L27
    LINENUMBER 284 L27
    ALOAD 0
    ALOAD 1
    LDC -8372020
    INVOKEVIRTUAL brw.a (Lbxl;I)V
   L28
    LINENUMBER 285 L28
    INVOKESTATIC bnf.H ()V
   L29
    LINENUMBER 286 L29
    SIPUSH 5888
    INVOKESTATIC bnf.n (I)V
   L30
    LINENUMBER 287 L30
    GETSTATIC bnf$r.l : Lbnf$r;
    GETSTATIC bnf$l.j : Lbnf$l;
    INVOKESTATIC bnf.a (Lbnf$r;Lbnf$l;)V
   L31
    LINENUMBER 288 L31
    INVOKESTATIC bnf.f ()V
   L32
    LINENUMBER 289 L32
    SIPUSH 515
    INVOKESTATIC bnf.c (I)V
   L33
    LINENUMBER 290 L33
    ICONST_1
    INVOKESTATIC bnf.a (Z)V
   L34
    LINENUMBER 291 L34
    ALOAD 0
    GETFIELD brw.e : Lbvf;
    GETSTATIC bvd.g : Lkl;
    INVOKEVIRTUAL bvf.a (Lkl;)V
   L35
    LINENUMBER 293 L35
    INVOKESTATIC Config.isShaders ()Z
    IFEQ L36
   L37
    LINENUMBER 295 L37
    ALOAD 0
    GETFIELD brw.renderItemGui : Z
    IFNE L36
   L38
    LINENUMBER 296 L38
    INVOKESTATIC net/optifine/shaders/ShadersRender.renderEnchantedGlintEnd ()V
   L36
    LINENUMBER 298 L36
   FRAME FULL [brw bxl F F] []
    RETURN
   L39
    LOCALVARIABLE this Lbrw; L0 L39 0
    LOCALVARIABLE model Lbxl; L0 L39 1
    LOCALVARIABLE f F L18 L39 2
    LOCALVARIABLE f1 F L25 L39 3
    MAXSTACK = 4
    MAXLOCALS = 4

  // access flags 0x2
  private a(Lbmx;Lboc;)V
   L0
    LINENUMBER 302 L0
    ALOAD 2
    INVOKEVIRTUAL boc.e ()Lcs;
    INVOKEVIRTUAL cs.n ()Ldh;
    ASTORE 3
   L1
    LINENUMBER 303 L1
    ALOAD 1
    ALOAD 3
    INVOKEVIRTUAL dh.p ()I
    I2F
    ALOAD 3
    INVOKEVIRTUAL dh.q ()I
    I2F
    ALOAD 3
    INVOKEVIRTUAL dh.r ()I
    I2F
    INVOKEVIRTUAL bmx.b (FFF)V
   L2
    LINENUMBER 304 L2
    RETURN
   L3
    LOCALVARIABLE this Lbrw; L0 L3 0
    LOCALVARIABLE renderer Lbmx; L0 L3 1
    LOCALVARIABLE quad Lboc; L0 L3 2
    LOCALVARIABLE vec3i Ldh; L1 L3 3
    MAXSTACK = 4
    MAXLOCALS = 4

  // access flags 0x2
  private a(Lbmx;Lboc;I)V
   L0
    LINENUMBER 309 L0
    ALOAD 0
    GETFIELD brw.renderModelEmissive : Z
    IFEQ L1
   L2
    LINENUMBER 311 L2
    ALOAD 2
    INVOKEVIRTUAL boc.getQuadEmissive ()Lboc;
    IFNONNULL L3
   L4
    LINENUMBER 312 L4
    RETURN
   L3
    LINENUMBER 314 L3
   FRAME FULL [brw bmx boc I] []
    ALOAD 2
    INVOKEVIRTUAL boc.getQuadEmissive ()Lboc;
    ASTORE 2
    GOTO L5
   L1
    LINENUMBER 318 L1
   FRAME FULL [brw bmx boc I] []
    ALOAD 2
    INVOKEVIRTUAL boc.getQuadEmissive ()Lboc;
    IFNULL L5
   L6
    LINENUMBER 319 L6
    ALOAD 0
    ICONST_1
    PUTFIELD brw.renderModelHasEmissive : Z
   L5
    LINENUMBER 322 L5
   FRAME FULL [brw bmx boc I] []
    ALOAD 1
    INVOKEVIRTUAL bmx.isMultiTexture ()Z
    IFEQ L7
   L8
    LINENUMBER 324 L8
    ALOAD 1
    ALOAD 2
    INVOKEVIRTUAL boc.getVertexDataSingle ()[I
    INVOKEVIRTUAL bmx.a ([I)V
    GOTO L9
   L7
    LINENUMBER 329 L7
   FRAME FULL [brw bmx boc I] []
    ALOAD 1
    ALOAD 2
    INVOKEVIRTUAL boc.b ()[I
    INVOKEVIRTUAL bmx.a ([I)V
   L9
    LINENUMBER 333 L9
   FRAME FULL [brw bmx boc I] []
    ALOAD 1
    ALOAD 2
    INVOKEVIRTUAL boc.a ()Lbve;
    INVOKEVIRTUAL bmx.putSprite (Lbve;)V
   L10
    LINENUMBER 335 L10
    GETSTATIC net/optifine/reflect/Reflector.ForgeHooksClient_putQuadColor : Lnet/optifine/reflect/ReflectorMethod;
    INVOKEVIRTUAL net/optifine/reflect/ReflectorMethod.exists ()Z
    IFEQ L11
   L12
    LINENUMBER 336 L12
    GETSTATIC net/optifine/reflect/Reflector.ForgeHooksClient_putQuadColor : Lnet/optifine/reflect/ReflectorMethod;
    ICONST_3
    ANEWARRAY java/lang/Object
    DUP
    ICONST_0
    ALOAD 1
    AASTORE
    DUP
    ICONST_1
    ALOAD 2
    AASTORE
    DUP
    ICONST_2
    ILOAD 3
    INVOKESTATIC java/lang/Integer.valueOf (I)Ljava/lang/Integer;
    AASTORE
    INVOKESTATIC net/optifine/reflect/Reflector.call (Lnet/optifine/reflect/ReflectorMethod;[Ljava/lang/Object;)Ljava/lang/Object;
    POP
    GOTO L13
   L11
    LINENUMBER 339 L11
   FRAME FULL [brw bmx boc I] []
    ALOAD 1
    ILOAD 3
    INVOKEVIRTUAL bmx.a (I)V
   L13
    LINENUMBER 340 L13
   FRAME FULL [brw bmx boc I] []
    ALOAD 0
    ALOAD 1
    ALOAD 2
    INVOKESPECIAL brw.a (Lbmx;Lboc;)V
   L14
    LINENUMBER 341 L14
    RETURN
   L15
    LOCALVARIABLE this Lbrw; L0 L15 0
    LOCALVARIABLE renderer Lbmx; L0 L15 1
    LOCALVARIABLE quad Lboc; L0 L15 2
    LOCALVARIABLE color I L0 L15 3
    MAXSTACK = 5
    MAXLOCALS = 4

  // access flags 0x2
  // signature (Lbmx;Ljava/util/List<Lboc;>;ILadq;)V
  // declaration: void a(bmx, java.util.List<boc>, int, adq)
  private a(Lbmx;Ljava/util/List;ILadq;)V
   L0
    LINENUMBER 345 L0
    ILOAD 3
    ICONST_M1
    IF_ICMPNE L1
    ALOAD 4
    IFNULL L1
    ICONST_1
    GOTO L2
   L1
   FRAME FULL [brw bmx java/util/List I adq] []
    ICONST_0
   L2
   FRAME FULL [brw bmx java/util/List I adq] [I]
    ISTORE 5
   L3
    LINENUMBER 346 L3
    ICONST_0
    ISTORE 6
   L4
    LINENUMBER 348 L4
    ALOAD 2
    INVOKEINTERFACE java/util/List.size ()I
    ISTORE 7
   L5
   FRAME FULL [brw bmx java/util/List I adq I I I] []
    ILOAD 6
    ILOAD 7
    IF_ICMPGE L6
   L7
    LINENUMBER 350 L7
    ALOAD 2
    ILOAD 6
    INVOKEINTERFACE java/util/List.get (I)Ljava/lang/Object;
    CHECKCAST boc
    ASTORE 8
   L8
    LINENUMBER 351 L8
    ILOAD 3
    ISTORE 9
   L9
    LINENUMBER 353 L9
    ILOAD 5
    IFEQ L10
    ALOAD 8
    INVOKEVIRTUAL boc.c ()Z
    IFEQ L10
   L11
    LINENUMBER 355 L11
    ALOAD 0
    GETFIELD brw.f : Lbcp;
    ALOAD 4
    ALOAD 8
    INVOKEVIRTUAL boc.d ()I
    INVOKEVIRTUAL bcp.a (Ladq;I)I
    ISTORE 9
   L12
    LINENUMBER 357 L12
    INVOKESTATIC Config.isCustomColors ()Z
    IFEQ L13
   L14
    LINENUMBER 358 L14
    ALOAD 4
    ALOAD 8
    INVOKEVIRTUAL boc.d ()I
    ILOAD 9
    INVOKESTATIC net/optifine/CustomColors.getColorFromItemStack (Ladq;II)I
    ISTORE 9
   L13
    LINENUMBER 361 L13
   FRAME FULL [brw bmx java/util/List I adq I I I boc I] []
    GETSTATIC bnd.a : Z
    IFEQ L15
   L16
    LINENUMBER 363 L16
    ILOAD 9
    INVOKESTATIC bvh.c (I)I
    ISTORE 9
   L15
    LINENUMBER 366 L15
   FRAME FULL [brw bmx java/util/List I adq I I I boc I] []
    ILOAD 9
    LDC -16777216
    IOR
    ISTORE 9
   L10
    LINENUMBER 370 L10
   FRAME FULL [brw bmx java/util/List I adq I I I boc I] []
    ALOAD 0
    ALOAD 1
    ALOAD 8
    ILOAD 9
    INVOKESPECIAL brw.a (Lbmx;Lboc;I)V
   L17
    LINENUMBER 348 L17
    IINC 6 1
    GOTO L5
   L6
    LINENUMBER 372 L6
   FRAME FULL [brw bmx java/util/List I adq I I I] []
    RETURN
   L18
    LOCALVARIABLE bakedquad Lboc; L8 L17 8
    LOCALVARIABLE k I L9 L17 9
    LOCALVARIABLE j I L5 L6 7
    LOCALVARIABLE this Lbrw; L0 L18 0
    LOCALVARIABLE renderer Lbmx; L0 L18 1
    LOCALVARIABLE quads Ljava/util/List; L0 L18 2
    // signature Ljava/util/List<Lboc;>;
    // declaration: java.util.List<boc>
    LOCALVARIABLE color I L0 L18 3
    LOCALVARIABLE stack Ladq; L0 L18 4
    LOCALVARIABLE flag Z L3 L18 5
    LOCALVARIABLE i I L4 L18 6
    MAXSTACK = 4
    MAXLOCALS = 10

  // access flags 0x1
  public a(Ladq;)Z
   L0
    LINENUMBER 376 L0
    ALOAD 0
    GETFIELD brw.d : Lbni;
    ALOAD 1
    INVOKEVIRTUAL bni.a (Ladq;)Lbxl;
    ASTORE 2
   L1
    LINENUMBER 377 L1
    ALOAD 2
    IFNONNULL L2
    ICONST_0
    GOTO L3
   L2
   FRAME FULL [brw adq bxl] []
    ALOAD 2
    INVOKEINTERFACE bxl.b ()Z
   L3
   FRAME FULL [brw adq bxl] [I]
    IRETURN
   L4
    LOCALVARIABLE this Lbrw; L0 L4 0
    LOCALVARIABLE stack Ladq; L0 L4 1
    LOCALVARIABLE ibakedmodel Lbxl; L1 L4 2
    MAXSTACK = 2
    MAXLOCALS = 3

  // access flags 0x1
  public a(Ladq;Lbop$b;)V
   L0
    LINENUMBER 382 L0
    ALOAD 1
    IFNULL L1
   L2
    LINENUMBER 384 L2
    ALOAD 0
    ALOAD 1
    ACONST_NULL
    CHECKCAST aht
    ACONST_NULL
    CHECKCAST sa
    INVOKEVIRTUAL brw.a (Ladq;Laht;Lsa;)Lbxl;
    ASTORE 3
   L3
    LINENUMBER 385 L3
    ALOAD 0
    ALOAD 1
    ALOAD 3
    ALOAD 2
    ICONST_0
    INVOKEVIRTUAL brw.a (Ladq;Lbxl;Lbop$b;Z)V
   L1
    LINENUMBER 387 L1
   FRAME FULL [brw adq bop$b] []
    RETURN
   L4
    LOCALVARIABLE ibakedmodel Lbxl; L3 L1 3
    LOCALVARIABLE this Lbrw; L0 L4 0
    LOCALVARIABLE stack Ladq; L0 L4 1
    LOCALVARIABLE cameraTransformType Lbop$b; L0 L4 2
    MAXSTACK = 5
    MAXLOCALS = 4

  // access flags 0x1
  public a(Ladq;Laht;Lsa;)Lbxl;
   L0
    LINENUMBER 391 L0
    ALOAD 0
    GETFIELD brw.d : Lbni;
    ALOAD 1
    INVOKEVIRTUAL bni.a (Ladq;)Lbxl;
    ASTORE 4
   L1
    LINENUMBER 392 L1
    ALOAD 1
    INVOKEVIRTUAL adq.b ()Lado;
    ASTORE 5
   L2
    LINENUMBER 394 L2
    INVOKESTATIC Config.isCustomItems ()Z
    IFEQ L3
   L4
    LINENUMBER 397 L4
    ALOAD 5
    IFNULL L5
    ALOAD 5
    INVOKEVIRTUAL ado.i ()Z
    IFEQ L5
   L6
    LINENUMBER 398 L6
    ALOAD 0
    ALOAD 4
    INVOKEINTERFACE bxl.f ()Lbon;
    ALOAD 1
    ALOAD 2
    ALOAD 3
    INVOKEVIRTUAL bon.a (Ladq;Laht;Lsa;)Lkl;
    PUTFIELD brw.modelLocation : Lkl;
   L5
    LINENUMBER 400 L5
   FRAME FULL [brw adq aht sa bxl ado] []
    ALOAD 1
    ALOAD 4
    ALOAD 0
    GETFIELD brw.modelLocation : Lkl;
    ICONST_1
    INVOKESTATIC net/optifine/CustomItems.getCustomItemModel (Ladq;Lbxl;Lkl;Z)Lbxl;
    ASTORE 6
   L7
    LINENUMBER 401 L7
    ALOAD 6
    ALOAD 4
    IF_ACMPEQ L3
   L8
    LINENUMBER 402 L8
    ALOAD 6
    ARETURN
   L3
    LINENUMBER 405 L3
   FRAME FULL [brw adq aht sa bxl ado] []
    GETSTATIC net/optifine/reflect/Reflector.ModelLoader_getInventoryVariant : Lnet/optifine/reflect/ReflectorMethod;
    INVOKEVIRTUAL net/optifine/reflect/ReflectorMethod.exists ()Z
    IFEQ L9
   L10
    LINENUMBER 406 L10
    ALOAD 4
    INVOKEINTERFACE bxl.f ()Lbon;
    ALOAD 4
    ALOAD 1
    ALOAD 2
    ALOAD 3
    INVOKEVIRTUAL bon.handleItemState (Lbxl;Ladq;Laht;Lsa;)Lbxl;
    ARETURN
   L9
    LINENUMBER 408 L9
   FRAME FULL [brw adq aht sa bxl ado] []
    ALOAD 5
    IFNULL L11
    ALOAD 5
    INVOKEVIRTUAL ado.i ()Z
    IFEQ L11
   L12
    LINENUMBER 410 L12
    ALOAD 4
    INVOKEINTERFACE bxl.f ()Lbon;
    ALOAD 1
    ALOAD 2
    ALOAD 3
    INVOKEVIRTUAL bon.a (Ladq;Laht;Lsa;)Lkl;
    ASTORE 6
   L13
    LINENUMBER 411 L13
    ALOAD 6
    IFNONNULL L14
    ALOAD 4
    GOTO L15
   L14
   FRAME FULL [brw adq aht sa bxl ado kl] []
    ALOAD 0
    GETFIELD brw.d : Lbni;
    INVOKEVIRTUAL bni.a ()Lbxp;
    NEW bxq
    DUP
    ALOAD 6
    LDC "inventory"
    INVOKESPECIAL bxq.<init> (Lkl;Ljava/lang/String;)V
    INVOKEVIRTUAL bxp.a (Lbxq;)Lbxl;
   L15
   FRAME FULL [brw adq aht sa bxl ado kl] [bxl]
    ARETURN
   L11
    LINENUMBER 415 L11
   FRAME FULL [brw adq aht sa bxl ado] []
    ALOAD 4
    ARETURN
   L16
    LOCALVARIABLE modelFull Lbxl; L7 L3 6
    LOCALVARIABLE resourcelocation Lkl; L13 L11 6
    LOCALVARIABLE this Lbrw; L0 L16 0
    LOCALVARIABLE p_184393_1_ Ladq; L0 L16 1
    LOCALVARIABLE p_184393_2_ Laht; L0 L16 2
    LOCALVARIABLE p_184393_3_ Lsa; L0 L16 3
    LOCALVARIABLE ibakedmodel Lbxl; L1 L16 4
    LOCALVARIABLE item Lado; L2 L16 5
    MAXSTACK = 5
    MAXLOCALS = 7

  // access flags 0x1
  public a(Ladq;Lsa;Lbop$b;Z)V
   L0
    LINENUMBER 421 L0
    ALOAD 1
    IFNULL L1
    ALOAD 2
    IFNULL L1
    ALOAD 1
    INVOKEVIRTUAL adq.b ()Lado;
    IFNULL L1
   L2
    LINENUMBER 423 L2
    ALOAD 0
    ALOAD 1
    ALOAD 2
    GETFIELD sa.l : Laht;
    ALOAD 2
    INVOKEVIRTUAL brw.a (Ladq;Laht;Lsa;)Lbxl;
    ASTORE 5
   L3
    LINENUMBER 424 L3
    ALOAD 0
    ALOAD 1
    ALOAD 5
    ALOAD 3
    ILOAD 4
    INVOKEVIRTUAL brw.a (Ladq;Lbxl;Lbop$b;Z)V
   L1
    LINENUMBER 426 L1
   FRAME FULL [brw adq sa bop$b I] []
    RETURN
   L4
    LOCALVARIABLE ibakedmodel Lbxl; L3 L1 5
    LOCALVARIABLE this Lbrw; L0 L4 0
    LOCALVARIABLE p_184392_1_ Ladq; L0 L4 1
    LOCALVARIABLE p_184392_2_ Lsa; L0 L4 2
    LOCALVARIABLE p_184392_3_ Lbop$b; L0 L4 3
    LOCALVARIABLE p_184392_4_ Z L0 L4 4
    MAXSTACK = 5
    MAXLOCALS = 6

  // access flags 0x4
  protected a(Ladq;Lbxl;Lbop$b;Z)V
   L0
    LINENUMBER 430 L0
    ALOAD 1
    INVOKEVIRTUAL adq.b ()Lado;
    IFNULL L1
   L2
    LINENUMBER 432 L2
    ALOAD 0
    GETFIELD brw.e : Lbvf;
    GETSTATIC bvd.g : Lkl;
    INVOKEVIRTUAL bvf.a (Lkl;)V
   L3
    LINENUMBER 433 L3
    ALOAD 0
    GETFIELD brw.e : Lbvf;
    GETSTATIC bvd.g : Lkl;
    INVOKEVIRTUAL bvf.b (Lkl;)Lbvg;
    ICONST_0
    ICONST_0
    INVOKEINTERFACE bvg.b (ZZ)V
   L4
    LINENUMBER 434 L4
    FCONST_1
    FCONST_1
    FCONST_1
    FCONST_1
    INVOKESTATIC bnf.c (FFFF)V
   L5
    LINENUMBER 435 L5
    INVOKESTATIC bnf.D ()V
   L6
    LINENUMBER 436 L6
    SIPUSH 516
    LDC 0.1
    INVOKESTATIC bnf.a (IF)V
   L7
    LINENUMBER 437 L7
    INVOKESTATIC bnf.m ()V
   L8
    LINENUMBER 438 L8
    GETSTATIC bnf$r.l : Lbnf$r;
    GETSTATIC bnf$l.j : Lbnf$l;
    GETSTATIC bnf$r.e : Lbnf$r;
    GETSTATIC bnf$l.n : Lbnf$l;
    INVOKESTATIC bnf.a (Lbnf$r;Lbnf$l;Lbnf$r;Lbnf$l;)V
   L9
    LINENUMBER 439 L9
    INVOKESTATIC bnf.G ()V
   L10
    LINENUMBER 441 L10
    GETSTATIC net/optifine/reflect/Reflector.ForgeHooksClient_handleCameraTransforms : Lnet/optifine/reflect/ReflectorMethod;
    INVOKEVIRTUAL net/optifine/reflect/ReflectorMethod.exists ()Z
    IFEQ L11
   L12
    LINENUMBER 444 L12
    GETSTATIC net/optifine/reflect/Reflector.ForgeHooksClient_handleCameraTransforms : Lnet/optifine/reflect/ReflectorMethod;
    ICONST_3
    ANEWARRAY java/lang/Object
    DUP
    ICONST_0
    ALOAD 2
    AASTORE
    DUP
    ICONST_1
    ALOAD 3
    AASTORE
    DUP
    ICONST_2
    ILOAD 4
    INVOKESTATIC java/lang/Boolean.valueOf (Z)Ljava/lang/Boolean;
    AASTORE
    INVOKESTATIC net/optifine/reflect/Reflector.call (Lnet/optifine/reflect/ReflectorMethod;[Ljava/lang/Object;)Ljava/lang/Object;
    CHECKCAST bxl
    ASTORE 2
    GOTO L13
   L11
    LINENUMBER 449 L11
   FRAME FULL [brw adq bxl bop$b I] []
    ALOAD 2
    INVOKEINTERFACE bxl.e ()Lbop;
    ASTORE 5
   L14
    LINENUMBER 450 L14
    ALOAD 5
    ALOAD 3
    INVOKEVIRTUAL bop.b (Lbop$b;)Lboo;
    ILOAD 4
    INVOKESTATIC bop.a (Lboo;Z)V
   L15
    LINENUMBER 452 L15
    ALOAD 0
    ALOAD 5
    ALOAD 3
    INVOKEVIRTUAL bop.b (Lbop$b;)Lboo;
    INVOKESPECIAL brw.a (Lboo;)Z
    IFEQ L13
   L16
    LINENUMBER 454 L16
    GETSTATIC bnf$i.a : Lbnf$i;
    INVOKESTATIC bnf.a (Lbnf$i;)V
   L13
    LINENUMBER 459 L13
   FRAME FULL [brw adq bxl bop$b I] []
    ILOAD 4
    INVOKESTATIC net/optifine/CustomItems.setRenderOffHand (Z)V
   L17
    LINENUMBER 461 L17
    ALOAD 0
    ALOAD 1
    ALOAD 2
    INVOKEVIRTUAL brw.a (Ladq;Lbxl;)V
   L18
    LINENUMBER 463 L18
    ICONST_0
    INVOKESTATIC net/optifine/CustomItems.setRenderOffHand (Z)V
   L19
    LINENUMBER 465 L19
    GETSTATIC bnf$i.b : Lbnf$i;
    INVOKESTATIC bnf.a (Lbnf$i;)V
   L20
    LINENUMBER 466 L20
    INVOKESTATIC bnf.H ()V
   L21
    LINENUMBER 467 L21
    INVOKESTATIC bnf.E ()V
   L22
    LINENUMBER 468 L22
    INVOKESTATIC bnf.l ()V
   L23
    LINENUMBER 469 L23
    ALOAD 0
    GETFIELD brw.e : Lbvf;
    GETSTATIC bvd.g : Lkl;
    INVOKEVIRTUAL bvf.a (Lkl;)V
   L24
    LINENUMBER 470 L24
    ALOAD 0
    GETFIELD brw.e : Lbvf;
    GETSTATIC bvd.g : Lkl;
    INVOKEVIRTUAL bvf.b (Lkl;)Lbvg;
    INVOKEINTERFACE bvg.a ()V
   L1
    LINENUMBER 472 L1
   FRAME FULL [brw adq bxl bop$b I] []
    RETURN
   L25
    LOCALVARIABLE itemcameratransforms Lbop; L14 L13 5
    LOCALVARIABLE this Lbrw; L0 L25 0
    LOCALVARIABLE p_184394_1_ Ladq; L0 L25 1
    LOCALVARIABLE p_184394_2_ Lbxl; L0 L25 2
    LOCALVARIABLE p_184394_3_ Lbop$b; L0 L25 3
    LOCALVARIABLE p_184394_4_ Z L0 L25 4
    MAXSTACK = 5
    MAXLOCALS = 6

  // access flags 0x2
  private a(Lboo;)Z
   L0
    LINENUMBER 479 L0
    ALOAD 1
    GETFIELD boo.d : Lorg/lwjgl/util/vector/Vector3f;
    GETFIELD org/lwjgl/util/vector/Vector3f.x : F
    FCONST_0
    FCMPG
    IFGE L1
    ICONST_1
    GOTO L2
   L1
   FRAME FULL [brw boo] []
    ICONST_0
   L2
   FRAME FULL [brw boo] [I]
    ALOAD 1
    GETFIELD boo.d : Lorg/lwjgl/util/vector/Vector3f;
    GETFIELD org/lwjgl/util/vector/Vector3f.y : F
    FCONST_0
    FCMPG
    IFGE L3
    ICONST_1
    GOTO L4
   L3
   FRAME FULL [brw boo] [I]
    ICONST_0
   L4
   FRAME FULL [brw boo] [I I]
    IXOR
    ALOAD 1
    GETFIELD boo.d : Lorg/lwjgl/util/vector/Vector3f;
    GETFIELD org/lwjgl/util/vector/Vector3f.z : F
    FCONST_0
    FCMPG
    IFGE L5
    ICONST_1
    GOTO L6
   L5
   FRAME FULL [brw boo] [I]
    ICONST_0
   L6
   FRAME FULL [brw boo] [I I]
    IXOR
    IRETURN
   L7
    LOCALVARIABLE this Lbrw; L0 L7 0
    LOCALVARIABLE itemTranformVec Lboo; L0 L7 1
    MAXSTACK = 3
    MAXLOCALS = 2

  // access flags 0x1
  public a(Ladq;II)V
   L0
    LINENUMBER 484 L0
    ALOAD 0
    ALOAD 1
    ILOAD 2
    ILOAD 3
    ALOAD 0
    ALOAD 1
    ACONST_NULL
    CHECKCAST aht
    ACONST_NULL
    CHECKCAST sa
    INVOKEVIRTUAL brw.a (Ladq;Laht;Lsa;)Lbxl;
    INVOKEVIRTUAL brw.a (Ladq;IILbxl;)V
   L1
    LINENUMBER 485 L1
    RETURN
   L2
    LOCALVARIABLE this Lbrw; L0 L2 0
    LOCALVARIABLE stack Ladq; L0 L2 1
    LOCALVARIABLE x I L0 L2 2
    LOCALVARIABLE y I L0 L2 3
    MAXSTACK = 8
    MAXLOCALS = 4

  // access flags 0x4
  protected a(Ladq;IILbxl;)V
   L0
    LINENUMBER 490 L0
    ALOAD 0
    ICONST_1
    PUTFIELD brw.renderItemGui : Z
   L1
    LINENUMBER 492 L1
    INVOKESTATIC bnf.G ()V
   L2
    LINENUMBER 493 L2
    ALOAD 0
    GETFIELD brw.e : Lbvf;
    GETSTATIC bvd.g : Lkl;
    INVOKEVIRTUAL bvf.a (Lkl;)V
   L3
    LINENUMBER 494 L3
    ALOAD 0
    GETFIELD brw.e : Lbvf;
    GETSTATIC bvd.g : Lkl;
    INVOKEVIRTUAL bvf.b (Lkl;)Lbvg;
    ICONST_0
    ICONST_0
    INVOKEINTERFACE bvg.b (ZZ)V
   L4
    LINENUMBER 495 L4
    INVOKESTATIC bnf.D ()V
   L5
    LINENUMBER 496 L5
    INVOKESTATIC bnf.e ()V
   L6
    LINENUMBER 497 L6
    SIPUSH 516
    LDC 0.1
    INVOKESTATIC bnf.a (IF)V
   L7
    LINENUMBER 498 L7
    INVOKESTATIC bnf.m ()V
   L8
    LINENUMBER 499 L8
    GETSTATIC bnf$r.l : Lbnf$r;
    GETSTATIC bnf$l.j : Lbnf$l;
    INVOKESTATIC bnf.a (Lbnf$r;Lbnf$l;)V
   L9
    LINENUMBER 500 L9
    FCONST_1
    FCONST_1
    FCONST_1
    FCONST_1
    INVOKESTATIC bnf.c (FFFF)V
   L10
    LINENUMBER 501 L10
    ALOAD 0
    ILOAD 2
    ILOAD 3
    ALOAD 4
    INVOKEINTERFACE bxl.b ()Z
    INVOKESPECIAL brw.a (IIZ)V
   L11
    LINENUMBER 503 L11
    GETSTATIC net/optifine/reflect/Reflector.ForgeHooksClient_handleCameraTransforms : Lnet/optifine/reflect/ReflectorMethod;
    INVOKEVIRTUAL net/optifine/reflect/ReflectorMethod.exists ()Z
    IFEQ L12
   L13
    LINENUMBER 506 L13
    GETSTATIC net/optifine/reflect/Reflector.ForgeHooksClient_handleCameraTransforms : Lnet/optifine/reflect/ReflectorMethod;
    ICONST_3
    ANEWARRAY java/lang/Object
    DUP
    ICONST_0
    ALOAD 4
    AASTORE
    DUP
    ICONST_1
    GETSTATIC bop$b.g : Lbop$b;
    AASTORE
    DUP
    ICONST_2
    ICONST_0
    INVOKESTATIC java/lang/Boolean.valueOf (Z)Ljava/lang/Boolean;
    AASTORE
    INVOKESTATIC net/optifine/reflect/Reflector.call (Lnet/optifine/reflect/ReflectorMethod;[Ljava/lang/Object;)Ljava/lang/Object;
    CHECKCAST bxl
    ASTORE 4
    GOTO L14
   L12
    LINENUMBER 511 L12
   FRAME FULL [brw adq I I bxl] []
    ALOAD 4
    INVOKEINTERFACE bxl.e ()Lbop;
    GETSTATIC bop$b.g : Lbop$b;
    INVOKEVIRTUAL bop.a (Lbop$b;)V
   L14
    LINENUMBER 515 L14
   FRAME FULL [brw adq I I bxl] []
    ALOAD 0
    ALOAD 1
    ALOAD 4
    INVOKEVIRTUAL brw.a (Ladq;Lbxl;)V
   L15
    LINENUMBER 516 L15
    INVOKESTATIC bnf.d ()V
   L16
    LINENUMBER 517 L16
    INVOKESTATIC bnf.E ()V
   L17
    LINENUMBER 518 L17
    INVOKESTATIC bnf.g ()V
   L18
    LINENUMBER 519 L18
    INVOKESTATIC bnf.H ()V
   L19
    LINENUMBER 520 L19
    ALOAD 0
    GETFIELD brw.e : Lbvf;
    GETSTATIC bvd.g : Lkl;
    INVOKEVIRTUAL bvf.a (Lkl;)V
   L20
    LINENUMBER 521 L20
    ALOAD 0
    GETFIELD brw.e : Lbvf;
    GETSTATIC bvd.g : Lkl;
    INVOKEVIRTUAL bvf.b (Lkl;)Lbvg;
    INVOKEINTERFACE bvg.a ()V
   L21
    LINENUMBER 523 L21
    ALOAD 0
    ICONST_0
    PUTFIELD brw.renderItemGui : Z
   L22
    LINENUMBER 525 L22
    RETURN
   L23
    LOCALVARIABLE this Lbrw; L0 L23 0
    LOCALVARIABLE p_184390_1_ Ladq; L0 L23 1
    LOCALVARIABLE p_184390_2_ I L0 L23 2
    LOCALVARIABLE p_184390_3_ I L0 L23 3
    LOCALVARIABLE p_184390_4_ Lbxl; L0 L23 4
    MAXSTACK = 5
    MAXLOCALS = 5

  // access flags 0x2
  private a(IIZ)V
   L0
    LINENUMBER 529 L0
    ILOAD 1
    I2F
    ILOAD 2
    I2F
    LDC 100.0
    ALOAD 0
    GETFIELD brw.a : F
    FADD
    INVOKESTATIC bnf.c (FFF)V
   L1
    LINENUMBER 530 L1
    LDC 8.0
    LDC 8.0
    FCONST_0
    INVOKESTATIC bnf.c (FFF)V
   L2
    LINENUMBER 531 L2
    FCONST_1
    LDC -1.0
    FCONST_1
    INVOKESTATIC bnf.b (FFF)V
   L3
    LINENUMBER 532 L3
    LDC 16.0
    LDC 16.0
    LDC 16.0
    INVOKESTATIC bnf.b (FFF)V
   L4
    LINENUMBER 534 L4
    ILOAD 3
    IFEQ L5
   L6
    LINENUMBER 536 L6
    INVOKESTATIC bnf.f ()V
    GOTO L7
   L5
    LINENUMBER 540 L5
   FRAME FULL [brw I I I] []
    INVOKESTATIC bnf.g ()V
   L7
    LINENUMBER 542 L7
   FRAME FULL [brw I I I] []
    RETURN
   L8
    LOCALVARIABLE this Lbrw; L0 L8 0
    LOCALVARIABLE xPosition I L0 L8 1
    LOCALVARIABLE yPosition I L0 L8 2
    LOCALVARIABLE isGui3d Z L0 L8 3
    MAXSTACK = 4
    MAXLOCALS = 4

  // access flags 0x1
  public b(Ladq;II)V
   L0
    LINENUMBER 546 L0
    ALOAD 0
    INVOKESTATIC bcd.z ()Lbcd;
    GETFIELD bcd.h : Lbmr;
    ALOAD 1
    ILOAD 2
    ILOAD 3
    INVOKEVIRTUAL brw.a (Lsa;Ladq;II)V
   L1
    LINENUMBER 547 L1
    RETURN
   L2
    LOCALVARIABLE this Lbrw; L0 L2 0
    LOCALVARIABLE stack Ladq; L0 L2 1
    LOCALVARIABLE xPosition I L0 L2 2
    LOCALVARIABLE yPosition I L0 L2 3
    MAXSTACK = 5
    MAXLOCALS = 4

  // access flags 0x1
  public a(Lsa;Ladq;II)V
    TRYCATCHBLOCK L0 L1 L2 java/lang/Throwable
   L3
    LINENUMBER 551 L3
    ALOAD 2
    IFNULL L4
    ALOAD 2
    INVOKEVIRTUAL adq.b ()Lado;
    IFNULL L4
   L5
    LINENUMBER 553 L5
    ALOAD 0
    DUP
    GETFIELD brw.a : F
    LDC 50.0
    FADD
    PUTFIELD brw.a : F
   L0
    LINENUMBER 557 L0
    ALOAD 0
    ALOAD 2
    ILOAD 3
    ILOAD 4
    ALOAD 0
    ALOAD 2
    ACONST_NULL
    CHECKCAST aht
    ALOAD 1
    INVOKEVIRTUAL brw.a (Ladq;Laht;Lsa;)Lbxl;
    INVOKEVIRTUAL brw.a (Ladq;IILbxl;)V
   L1
    LINENUMBER 592 L1
    GOTO L6
   L2
    LINENUMBER 559 L2
   FRAME FULL [brw sa adq I I] [java/lang/Throwable]
    ASTORE 5
   L7
    LINENUMBER 561 L7
    ALOAD 5
    LDC "Rendering item"
    INVOKESTATIC b.a (Ljava/lang/Throwable;Ljava/lang/String;)Lb;
    ASTORE 6
   L8
    LINENUMBER 562 L8
    ALOAD 6
    LDC "Item being rendered"
    INVOKEVIRTUAL b.a (Ljava/lang/String;)Lc;
    ASTORE 7
   L9
    LINENUMBER 563 L9
    ALOAD 7
    LDC "Item Type"
    NEW brw$1
    DUP
    ALOAD 0
    ALOAD 2
    INVOKESPECIAL brw$1.<init> (Lbrw;Ladq;)V
    INVOKEVIRTUAL c.a (Ljava/lang/String;Ld;)V
   L10
    LINENUMBER 570 L10
    ALOAD 7
    LDC "Item Aux"
    NEW brw$2
    DUP
    ALOAD 0
    ALOAD 2
    INVOKESPECIAL brw$2.<init> (Lbrw;Ladq;)V
    INVOKEVIRTUAL c.a (Ljava/lang/String;Ld;)V
   L11
    LINENUMBER 577 L11
    ALOAD 7
    LDC "Item NBT"
    NEW brw$3
    DUP
    ALOAD 0
    ALOAD 2
    INVOKESPECIAL brw$3.<init> (Lbrw;Ladq;)V
    INVOKEVIRTUAL c.a (Ljava/lang/String;Ld;)V
   L12
    LINENUMBER 584 L12
    ALOAD 7
    LDC "Item Foil"
    NEW brw$4
    DUP
    ALOAD 0
    ALOAD 2
    INVOKESPECIAL brw$4.<init> (Lbrw;Ladq;)V
    INVOKEVIRTUAL c.a (Ljava/lang/String;Ld;)V
   L13
    LINENUMBER 591 L13
    NEW f
    DUP
    ALOAD 6
    INVOKESPECIAL f.<init> (Lb;)V
    ATHROW
   L6
    LINENUMBER 594 L6
   FRAME FULL [brw sa adq I I] []
    ALOAD 0
    DUP
    GETFIELD brw.a : F
    LDC 50.0
    FSUB
    PUTFIELD brw.a : F
   L4
    LINENUMBER 596 L4
   FRAME FULL [brw sa adq I I] []
    RETURN
   L14
    LOCALVARIABLE crashreport Lb; L8 L6 6
    LOCALVARIABLE crashreportcategory Lc; L9 L6 7
    LOCALVARIABLE throwable Ljava/lang/Throwable; L7 L6 5
    LOCALVARIABLE this Lbrw; L3 L14 0
    LOCALVARIABLE p_184391_1_ Lsa; L3 L14 1
    LOCALVARIABLE p_184391_2_ Ladq; L3 L14 2
    LOCALVARIABLE p_184391_3_ I L3 L14 3
    LOCALVARIABLE p_184391_4_ I L3 L14 4
    MAXSTACK = 8
    MAXLOCALS = 8

  // access flags 0x1
  public a(Lbcr;Ladq;II)V
   L0
    LINENUMBER 600 L0
    ALOAD 0
    ALOAD 1
    ALOAD 2
    ILOAD 3
    ILOAD 4
    ACONST_NULL
    CHECKCAST java/lang/String
    INVOKEVIRTUAL brw.a (Lbcr;Ladq;IILjava/lang/String;)V
   L1
    LINENUMBER 601 L1
    RETURN
   L2
    LOCALVARIABLE this Lbrw; L0 L2 0
    LOCALVARIABLE fr Lbcr; L0 L2 1
    LOCALVARIABLE stack Ladq; L0 L2 2
    LOCALVARIABLE xPosition I L0 L2 3
    LOCALVARIABLE yPosition I L0 L2 4
    MAXSTACK = 6
    MAXLOCALS = 5

  // access flags 0x1
  public a(Lbcr;Ladq;IILjava/lang/String;)V
   L0
    LINENUMBER 608 L0
    ALOAD 2
    IFNULL L1
   L2
    LINENUMBER 610 L2
    ALOAD 2
    GETFIELD adq.b : I
    ICONST_1
    IF_ICMPNE L3
    ALOAD 5
    IFNULL L4
   L3
    LINENUMBER 612 L3
   FRAME FULL [brw bcr adq I I java/lang/String] []
    ALOAD 5
    IFNONNULL L5
    ALOAD 2
    GETFIELD adq.b : I
    INVOKESTATIC java/lang/String.valueOf (I)Ljava/lang/String;
    GOTO L6
   L5
   FRAME FULL [brw bcr adq I I java/lang/String] []
    ALOAD 5
   L6
   FRAME FULL [brw bcr adq I I java/lang/String] [java/lang/String]
    ASTORE 6
   L7
    LINENUMBER 614 L7
    ALOAD 5
    IFNONNULL L8
    ALOAD 2
    GETFIELD adq.b : I
    ICONST_1
    IF_ICMPGE L8
   L9
    LINENUMBER 616 L9
    NEW java/lang/StringBuilder
    DUP
    INVOKESPECIAL java/lang/StringBuilder.<init> ()V
    GETSTATIC a.m : La;
    INVOKEVIRTUAL java/lang/StringBuilder.append (Ljava/lang/Object;)Ljava/lang/StringBuilder;
    ALOAD 2
    GETFIELD adq.b : I
    INVOKESTATIC java/lang/String.valueOf (I)Ljava/lang/String;
    INVOKEVIRTUAL java/lang/StringBuilder.append (Ljava/lang/String;)Ljava/lang/StringBuilder;
    INVOKEVIRTUAL java/lang/StringBuilder.toString ()Ljava/lang/String;
    ASTORE 6
   L8
    LINENUMBER 619 L8
   FRAME FULL [brw bcr adq I I java/lang/String java/lang/String] []
    INVOKESTATIC bnf.g ()V
   L10
    LINENUMBER 620 L10
    INVOKESTATIC bnf.j ()V
   L11
    LINENUMBER 621 L11
    INVOKESTATIC bnf.l ()V
   L12
    LINENUMBER 622 L12
    ALOAD 1
    ALOAD 6
    ILOAD 3
    BIPUSH 19
    IADD
    ICONST_2
    ISUB
    ALOAD 1
    ALOAD 6
    INVOKEVIRTUAL bcr.a (Ljava/lang/String;)I
    ISUB
    I2F
    ILOAD 4
    BIPUSH 6
    IADD
    ICONST_3
    IADD
    I2F
    LDC 16777215
    INVOKEVIRTUAL bcr.a (Ljava/lang/String;FFI)I
    POP
   L13
    LINENUMBER 623 L13
    INVOKESTATIC bnf.f ()V
   L14
    LINENUMBER 624 L14
    INVOKESTATIC bnf.k ()V
   L15
    LINENUMBER 626 L15
    INVOKESTATIC bnf.m ()V
   L4
    LINENUMBER 631 L4
   FRAME FULL [brw bcr adq I I java/lang/String] []
    ALOAD 2
    INVOKESTATIC net/optifine/reflect/ReflectorForge.isItemDamaged (Ladq;)Z
    IFEQ L16
   L17
    LINENUMBER 633 L17
    LDC 13.0
    ALOAD 2
    INVOKEVIRTUAL adq.h ()I
    I2D
    LDC 13.0
    DMUL
    ALOAD 2
    INVOKEVIRTUAL adq.j ()I
    I2D
    DDIV
    DSUB
    INVOKESTATIC java/lang/Math.round (D)J
    L2I
    ISTORE 6
   L18
    LINENUMBER 634 L18
    LDC 255.0
    ALOAD 2
    INVOKEVIRTUAL adq.h ()I
    I2D
    LDC 255.0
    DMUL
    ALOAD 2
    INVOKEVIRTUAL adq.j ()I
    I2D
    DDIV
    DSUB
    INVOKESTATIC java/lang/Math.round (D)J
    L2I
    ISTORE 7
   L19
    LINENUMBER 636 L19
    GETSTATIC net/optifine/reflect/Reflector.ForgeItem_getDurabilityForDisplay : Lnet/optifine/reflect/ReflectorMethod;
    INVOKEVIRTUAL net/optifine/reflect/ReflectorMethod.exists ()Z
    IFEQ L20
   L21
    LINENUMBER 638 L21
    ALOAD 2
    INVOKEVIRTUAL adq.b ()Lado;
    GETSTATIC net/optifine/reflect/Reflector.ForgeItem_getDurabilityForDisplay : Lnet/optifine/reflect/ReflectorMethod;
    ICONST_1
    ANEWARRAY java/lang/Object
    DUP
    ICONST_0
    ALOAD 2
    AASTORE
    INVOKESTATIC net/optifine/reflect/Reflector.callDouble (Ljava/lang/Object;Lnet/optifine/reflect/ReflectorMethod;[Ljava/lang/Object;)D
    DSTORE 8
   L22
    LINENUMBER 639 L22
    LDC 13.0
    DLOAD 8
    LDC 13.0
    DMUL
    DSUB
    INVOKESTATIC java/lang/Math.round (D)J
    L2I
    ISTORE 6
   L23
    LINENUMBER 640 L23
    LDC 255.0
    DLOAD 8
    LDC 255.0
    DMUL
    DSUB
    INVOKESTATIC java/lang/Math.round (D)J
    L2I
    ISTORE 7
   L20
    LINENUMBER 643 L20
   FRAME FULL [brw bcr adq I I java/lang/String I I] []
    INVOKESTATIC bnf.g ()V
   L24
    LINENUMBER 644 L24
    INVOKESTATIC bnf.j ()V
   L25
    LINENUMBER 645 L25
    INVOKESTATIC bnf.z ()V
   L26
    LINENUMBER 646 L26
    INVOKESTATIC bnf.d ()V
   L27
    LINENUMBER 647 L27
    INVOKESTATIC bnf.l ()V
   L28
    LINENUMBER 648 L28
    INVOKESTATIC bnr.a ()Lbnr;
    ASTORE 8
   L29
    LINENUMBER 649 L29
    ALOAD 8
    INVOKEVIRTUAL bnr.c ()Lbmx;
    ASTORE 9
   L30
    LINENUMBER 650 L30
    ALOAD 0
    ALOAD 9
    ILOAD 3
    ICONST_2
    IADD
    ILOAD 4
    BIPUSH 13
    IADD
    BIPUSH 13
    ICONST_2
    ICONST_0
    ICONST_0
    ICONST_0
    SIPUSH 255
    INVOKESPECIAL brw.a (Lbmx;IIIIIIII)V
   L31
    LINENUMBER 651 L31
    ALOAD 0
    ALOAD 9
    ILOAD 3
    ICONST_2
    IADD
    ILOAD 4
    BIPUSH 13
    IADD
    BIPUSH 12
    ICONST_1
    SIPUSH 255
    ILOAD 7
    ISUB
    ICONST_4
    IDIV
    BIPUSH 64
    ICONST_0
    SIPUSH 255
    INVOKESPECIAL brw.a (Lbmx;IIIIIIII)V
   L32
    LINENUMBER 653 L32
    SIPUSH 255
    ILOAD 7
    ISUB
    ISTORE 10
   L33
    LINENUMBER 654 L33
    ILOAD 7
    ISTORE 11
   L34
    LINENUMBER 655 L34
    ICONST_0
    ISTORE 12
   L35
    LINENUMBER 656 L35
    INVOKESTATIC Config.isCustomColors ()Z
    IFEQ L36
   L37
    LINENUMBER 658 L37
    ILOAD 7
    INVOKESTATIC net/optifine/CustomColors.getDurabilityColor (I)I
    ISTORE 13
   L38
    LINENUMBER 659 L38
    ILOAD 13
    IFLT L36
   L39
    LINENUMBER 661 L39
    ILOAD 13
    BIPUSH 16
    ISHR
    SIPUSH 255
    IAND
    ISTORE 10
   L40
    LINENUMBER 662 L40
    ILOAD 13
    BIPUSH 8
    ISHR
    SIPUSH 255
    IAND
    ISTORE 11
   L41
    LINENUMBER 663 L41
    ILOAD 13
    ICONST_0
    ISHR
    SIPUSH 255
    IAND
    ISTORE 12
   L36
    LINENUMBER 667 L36
   FRAME FULL [brw bcr adq I I java/lang/String I I bnr bmx I I I] []
    ALOAD 0
    ALOAD 9
    ILOAD 3
    ICONST_2
    IADD
    ILOAD 4
    BIPUSH 13
    IADD
    ILOAD 6
    ICONST_1
    ILOAD 10
    ILOAD 11
    ILOAD 12
    SIPUSH 255
    INVOKESPECIAL brw.a (Lbmx;IIIIIIII)V
   L42
    LINENUMBER 668 L42
    INVOKESTATIC bnf.m ()V
   L43
    LINENUMBER 669 L43
    INVOKESTATIC bnf.e ()V
   L44
    LINENUMBER 670 L44
    INVOKESTATIC bnf.y ()V
   L45
    LINENUMBER 671 L45
    INVOKESTATIC bnf.f ()V
   L46
    LINENUMBER 672 L46
    INVOKESTATIC bnf.k ()V
   L16
    LINENUMBER 675 L16
   FRAME FULL [brw bcr adq I I java/lang/String] []
    INVOKESTATIC bcd.z ()Lbcd;
    GETFIELD bcd.h : Lbmr;
    ASTORE 6
   L47
    LINENUMBER 676 L47
    ALOAD 6
    IFNONNULL L48
    FCONST_0
    GOTO L49
   L48
   FRAME FULL [brw bcr adq I I java/lang/String bmr] []
    ALOAD 6
    INVOKEVIRTUAL bmr.db ()Ladp;
    ALOAD 2
    INVOKEVIRTUAL adq.b ()Lado;
    INVOKESTATIC bcd.z ()Lbcd;
    INVOKEVIRTUAL bcd.ak ()F
    INVOKEVIRTUAL adp.a (Lado;F)F
   L49
   FRAME FULL [brw bcr adq I I java/lang/String bmr] [F]
    FSTORE 7
   L50
    LINENUMBER 678 L50
    FLOAD 7
    FCONST_0
    FCMPL
    IFLE L1
   L51
    LINENUMBER 680 L51
    INVOKESTATIC bnf.g ()V
   L52
    LINENUMBER 681 L52
    INVOKESTATIC bnf.j ()V
   L53
    LINENUMBER 682 L53
    INVOKESTATIC bnf.z ()V
   L54
    LINENUMBER 683 L54
    INVOKESTATIC bnr.a ()Lbnr;
    ASTORE 8
   L55
    LINENUMBER 684 L55
    ALOAD 8
    INVOKEVIRTUAL bnr.c ()Lbmx;
    ASTORE 9
   L56
    LINENUMBER 685 L56
    ALOAD 0
    ALOAD 9
    ILOAD 3
    ILOAD 4
    LDC 16.0
    FCONST_1
    FLOAD 7
    FSUB
    FMUL
    INVOKESTATIC on.d (F)I
    IADD
    BIPUSH 16
    LDC 16.0
    FLOAD 7
    FMUL
    INVOKESTATIC on.f (F)I
    SIPUSH 255
    SIPUSH 255
    SIPUSH 255
    BIPUSH 127
    INVOKESPECIAL brw.a (Lbmx;IIIIIIII)V
   L57
    LINENUMBER 686 L57
    INVOKESTATIC bnf.y ()V
   L58
    LINENUMBER 687 L58
    INVOKESTATIC bnf.f ()V
   L59
    LINENUMBER 688 L59
    INVOKESTATIC bnf.k ()V
   L1
    LINENUMBER 691 L1
   FRAME FULL [brw bcr adq I I java/lang/String] []
    RETURN
   L60
    LOCALVARIABLE s Ljava/lang/String; L7 L4 6
    LOCALVARIABLE health D L22 L20 8
    LOCALVARIABLE col I L38 L36 13
    LOCALVARIABLE j I L18 L16 6
    LOCALVARIABLE i I L19 L16 7
    LOCALVARIABLE tessellator Lbnr; L29 L16 8
    LOCALVARIABLE vertexbuffer Lbmx; L30 L16 9
    LOCALVARIABLE red I L33 L16 10
    LOCALVARIABLE green I L34 L16 11
    LOCALVARIABLE blue I L35 L16 12
    LOCALVARIABLE tessellator1 Lbnr; L55 L1 8
    LOCALVARIABLE vertexbuffer1 Lbmx; L56 L1 9
    LOCALVARIABLE entityplayersp Lbmr; L47 L1 6
    LOCALVARIABLE f F L50 L1 7
    LOCALVARIABLE this Lbrw; L0 L60 0
    LOCALVARIABLE fr Lbcr; L0 L60 1
    LOCALVARIABLE stack Ladq; L0 L60 2
    LOCALVARIABLE xPosition I L0 L60 3
    LOCALVARIABLE yPosition I L0 L60 4
    LOCALVARIABLE text Ljava/lang/String; L0 L60 5
    MAXSTACK = 10
    MAXLOCALS = 14

  // access flags 0x2
  private a(Lbmx;IIIIIIII)V
   L0
    LINENUMBER 698 L0
    ALOAD 1
    BIPUSH 7
    GETSTATIC bvm.f : Lbvo;
    INVOKEVIRTUAL bmx.a (ILbvo;)V
   L1
    LINENUMBER 699 L1
    ALOAD 1
    ILOAD 2
    ICONST_0
    IADD
    I2D
    ILOAD 3
    ICONST_0
    IADD
    I2D
    DCONST_0
    INVOKEVIRTUAL bmx.b (DDD)Lbmx;
    ILOAD 6
    ILOAD 7
    ILOAD 8
    ILOAD 9
    INVOKEVIRTUAL bmx.b (IIII)Lbmx;
    INVOKEVIRTUAL bmx.d ()V
   L2
    LINENUMBER 700 L2
    ALOAD 1
    ILOAD 2
    ICONST_0
    IADD
    I2D
    ILOAD 3
    ILOAD 5
    IADD
    I2D
    DCONST_0
    INVOKEVIRTUAL bmx.b (DDD)Lbmx;
    ILOAD 6
    ILOAD 7
    ILOAD 8
    ILOAD 9
    INVOKEVIRTUAL bmx.b (IIII)Lbmx;
    INVOKEVIRTUAL bmx.d ()V
   L3
    LINENUMBER 701 L3
    ALOAD 1
    ILOAD 2
    ILOAD 4
    IADD
    I2D
    ILOAD 3
    ILOAD 5
    IADD
    I2D
    DCONST_0
    INVOKEVIRTUAL bmx.b (DDD)Lbmx;
    ILOAD 6
    ILOAD 7
    ILOAD 8
    ILOAD 9
    INVOKEVIRTUAL bmx.b (IIII)Lbmx;
    INVOKEVIRTUAL bmx.d ()V
   L4
    LINENUMBER 702 L4
    ALOAD 1
    ILOAD 2
    ILOAD 4
    IADD
    I2D
    ILOAD 3
    ICONST_0
    IADD
    I2D
    DCONST_0
    INVOKEVIRTUAL bmx.b (DDD)Lbmx;
    ILOAD 6
    ILOAD 7
    ILOAD 8
    ILOAD 9
    INVOKEVIRTUAL bmx.b (IIII)Lbmx;
    INVOKEVIRTUAL bmx.d ()V
   L5
    LINENUMBER 703 L5
    INVOKESTATIC bnr.a ()Lbnr;
    INVOKEVIRTUAL bnr.b ()V
   L6
    LINENUMBER 704 L6
    RETURN
   L7
    LOCALVARIABLE this Lbrw; L0 L7 0
    LOCALVARIABLE renderer Lbmx; L0 L7 1
    LOCALVARIABLE x I L0 L7 2
    LOCALVARIABLE y I L0 L7 3
    LOCALVARIABLE width I L0 L7 4
    LOCALVARIABLE height I L0 L7 5
    LOCALVARIABLE red I L0 L7 6
    LOCALVARIABLE green I L0 L7 7
    LOCALVARIABLE blue I L0 L7 8
    LOCALVARIABLE alpha I L0 L7 9
    MAXSTACK = 7
    MAXLOCALS = 10

  // access flags 0x2
  private b()V
   L0
    LINENUMBER 708 L0
    ALOAD 0
    GETSTATIC aju.cf : Lajt;
    LDC "anvil_intact"
    INVOKESPECIAL brw.a (Lajt;Ljava/lang/String;)V
   L1
    LINENUMBER 709 L1
    ALOAD 0
    GETSTATIC aju.cf : Lajt;
    ICONST_1
    LDC "anvil_slightly_damaged"
    INVOKEVIRTUAL brw.a (Lajt;ILjava/lang/String;)V
   L2
    LINENUMBER 710 L2
    ALOAD 0
    GETSTATIC aju.cf : Lajt;
    ICONST_2
    LDC "anvil_very_damaged"
    INVOKEVIRTUAL brw.a (Lajt;ILjava/lang/String;)V
   L3
    LINENUMBER 711 L3
    ALOAD 0
    GETSTATIC aju.cy : Lajt;
    GETSTATIC act.p : Lact;
    INVOKEVIRTUAL act.a ()I
    LDC "black_carpet"
    INVOKEVIRTUAL brw.a (Lajt;ILjava/lang/String;)V
   L4
    LINENUMBER 712 L4
    ALOAD 0
    GETSTATIC aju.cy : Lajt;
    GETSTATIC act.l : Lact;
    INVOKEVIRTUAL act.a ()I
    LDC "blue_carpet"
    INVOKEVIRTUAL brw.a (Lajt;ILjava/lang/String;)V
   L5
    LINENUMBER 713 L5
    ALOAD 0
    GETSTATIC aju.cy : Lajt;
    GETSTATIC act.m : Lact;
    INVOKEVIRTUAL act.a ()I
    LDC "brown_carpet"
    INVOKEVIRTUAL brw.a (Lajt;ILjava/lang/String;)V
   L6
    LINENUMBER 714 L6
    ALOAD 0
    GETSTATIC aju.cy : Lajt;
    GETSTATIC act.j : Lact;
    INVOKEVIRTUAL act.a ()I
    LDC "cyan_carpet"
    INVOKEVIRTUAL brw.a (Lajt;ILjava/lang/String;)V
   L7
    LINENUMBER 715 L7
    ALOAD 0
    GETSTATIC aju.cy : Lajt;
    GETSTATIC act.h : Lact;
    INVOKEVIRTUAL act.a ()I
    LDC "gray_carpet"
    INVOKEVIRTUAL brw.a (Lajt;ILjava/lang/String;)V
   L8
    LINENUMBER 716 L8
    ALOAD 0
    GETSTATIC aju.cy : Lajt;
    GETSTATIC act.n : Lact;
    INVOKEVIRTUAL act.a ()I
    LDC "green_carpet"
    INVOKEVIRTUAL brw.a (Lajt;ILjava/lang/String;)V
   L9
    LINENUMBER 717 L9
    ALOAD 0
    GETSTATIC aju.cy : Lajt;
    GETSTATIC act.d : Lact;
    INVOKEVIRTUAL act.a ()I
    LDC "light_blue_carpet"
    INVOKEVIRTUAL brw.a (Lajt;ILjava/lang/String;)V
   L10
    LINENUMBER 718 L10
    ALOAD 0
    GETSTATIC aju.cy : Lajt;
    GETSTATIC act.f : Lact;
    INVOKEVIRTUAL act.a ()I
    LDC "lime_carpet"
    INVOKEVIRTUAL brw.a (Lajt;ILjava/lang/String;)V
   L11
    LINENUMBER 719 L11
    ALOAD 0
    GETSTATIC aju.cy : Lajt;
    GETSTATIC act.c : Lact;
    INVOKEVIRTUAL act.a ()I
    LDC "magenta_carpet"
    INVOKEVIRTUAL brw.a (Lajt;ILjava/lang/String;)V
   L12
    LINENUMBER 720 L12
    ALOAD 0
    GETSTATIC aju.cy : Lajt;
    GETSTATIC act.b : Lact;
    INVOKEVIRTUAL act.a ()I
    LDC "orange_carpet"
    INVOKEVIRTUAL brw.a (Lajt;ILjava/lang/String;)V
   L13
    LINENUMBER 721 L13
    ALOAD 0
    GETSTATIC aju.cy : Lajt;
    GETSTATIC act.g : Lact;
    INVOKEVIRTUAL act.a ()I
    LDC "pink_carpet"
    INVOKEVIRTUAL brw.a (Lajt;ILjava/lang/String;)V
   L14
    LINENUMBER 722 L14
    ALOAD 0
    GETSTATIC aju.cy : Lajt;
    GETSTATIC act.k : Lact;
    INVOKEVIRTUAL act.a ()I
    LDC "purple_carpet"
    INVOKEVIRTUAL brw.a (Lajt;ILjava/lang/String;)V
   L15
    LINENUMBER 723 L15
    ALOAD 0
    GETSTATIC aju.cy : Lajt;
    GETSTATIC act.o : Lact;
    INVOKEVIRTUAL act.a ()I
    LDC "red_carpet"
    INVOKEVIRTUAL brw.a (Lajt;ILjava/lang/String;)V
   L16
    LINENUMBER 724 L16
    ALOAD 0
    GETSTATIC aju.cy : Lajt;
    GETSTATIC act.i : Lact;
    INVOKEVIRTUAL act.a ()I
    LDC "silver_carpet"
    INVOKEVIRTUAL brw.a (Lajt;ILjava/lang/String;)V
   L17
    LINENUMBER 725 L17
    ALOAD 0
    GETSTATIC aju.cy : Lajt;
    GETSTATIC act.a : Lact;
    INVOKEVIRTUAL act.a ()I
    LDC "white_carpet"
    INVOKEVIRTUAL brw.a (Lajt;ILjava/lang/String;)V
   L18
    LINENUMBER 726 L18
    ALOAD 0
    GETSTATIC aju.cy : Lajt;
    GETSTATIC act.e : Lact;
    INVOKEVIRTUAL act.a ()I
    LDC "yellow_carpet"
    INVOKEVIRTUAL brw.a (Lajt;ILjava/lang/String;)V
   L19
    LINENUMBER 727 L19
    ALOAD 0
    GETSTATIC aju.bZ : Lajt;
    GETSTATIC apk$a.b : Lapk$a;
    INVOKEVIRTUAL apk$a.a ()I
    LDC "mossy_cobblestone_wall"
    INVOKEVIRTUAL brw.a (Lajt;ILjava/lang/String;)V
   L20
    LINENUMBER 728 L20
    ALOAD 0
    GETSTATIC aju.bZ : Lajt;
    GETSTATIC apk$a.a : Lapk$a;
    INVOKEVIRTUAL apk$a.a ()I
    LDC "cobblestone_wall"
    INVOKEVIRTUAL brw.a (Lajt;ILjava/lang/String;)V
   L21
    LINENUMBER 729 L21
    ALOAD 0
    GETSTATIC aju.d : Lajt;
    GETSTATIC akt$a.b : Lakt$a;
    INVOKEVIRTUAL akt$a.a ()I
    LDC "coarse_dirt"
    INVOKEVIRTUAL brw.a (Lajt;ILjava/lang/String;)V
   L22
    LINENUMBER 730 L22
    ALOAD 0
    GETSTATIC aju.d : Lajt;
    GETSTATIC akt$a.a : Lakt$a;
    INVOKEVIRTUAL akt$a.a ()I
    LDC "dirt"
    INVOKEVIRTUAL brw.a (Lajt;ILjava/lang/String;)V
   L23
    LINENUMBER 731 L23
    ALOAD 0
    GETSTATIC aju.d : Lajt;
    GETSTATIC akt$a.c : Lakt$a;
    INVOKEVIRTUAL akt$a.a ()I
    LDC "podzol"
    INVOKEVIRTUAL brw.a (Lajt;ILjava/lang/String;)V
   L24
    LINENUMBER 732 L24
    ALOAD 0
    GETSTATIC aju.cF : Lakw;
    GETSTATIC akw$b.d : Lakw$b;
    INVOKEVIRTUAL akw$b.a ()I
    LDC "double_fern"
    INVOKEVIRTUAL brw.a (Lajt;ILjava/lang/String;)V
   L25
    LINENUMBER 733 L25
    ALOAD 0
    GETSTATIC aju.cF : Lakw;
    GETSTATIC akw$b.c : Lakw$b;
    INVOKEVIRTUAL akw$b.a ()I
    LDC "double_grass"
    INVOKEVIRTUAL brw.a (Lajt;ILjava/lang/String;)V
   L26
    LINENUMBER 734 L26
    ALOAD 0
    GETSTATIC aju.cF : Lakw;
    GETSTATIC akw$b.f : Lakw$b;
    INVOKEVIRTUAL akw$b.a ()I
    LDC "paeonia"
    INVOKEVIRTUAL brw.a (Lajt;ILjava/lang/String;)V
   L27
    LINENUMBER 735 L27
    ALOAD 0
    GETSTATIC aju.cF : Lakw;
    GETSTATIC akw$b.e : Lakw$b;
    INVOKEVIRTUAL akw$b.a ()I
    LDC "double_rose"
    INVOKEVIRTUAL brw.a (Lajt;ILjava/lang/String;)V
   L28
    LINENUMBER 736 L28
    ALOAD 0
    GETSTATIC aju.cF : Lakw;
    GETSTATIC akw$b.a : Lakw$b;
    INVOKEVIRTUAL akw$b.a ()I
    LDC "sunflower"
    INVOKEVIRTUAL brw.a (Lajt;ILjava/lang/String;)V
   L29
    LINENUMBER 737 L29
    ALOAD 0
    GETSTATIC aju.cF : Lakw;
    GETSTATIC akw$b.b : Lakw$b;
    INVOKEVIRTUAL akw$b.a ()I
    LDC "syringa"
    INVOKEVIRTUAL brw.a (Lajt;ILjava/lang/String;)V
   L30
    LINENUMBER 738 L30
    ALOAD 0
    GETSTATIC aju.t : Laml;
    GETSTATIC anj$a.c : Lanj$a;
    INVOKEVIRTUAL anj$a.a ()I
    LDC "birch_leaves"
    INVOKEVIRTUAL brw.a (Lajt;ILjava/lang/String;)V
   L31
    LINENUMBER 739 L31
    ALOAD 0
    GETSTATIC aju.t : Laml;
    GETSTATIC anj$a.d : Lanj$a;
    INVOKEVIRTUAL anj$a.a ()I
    LDC "jungle_leaves"
    INVOKEVIRTUAL brw.a (Lajt;ILjava/lang/String;)V
   L32
    LINENUMBER 740 L32
    ALOAD 0
    GETSTATIC aju.t : Laml;
    GETSTATIC anj$a.a : Lanj$a;
    INVOKEVIRTUAL anj$a.a ()I
    LDC "oak_leaves"
    INVOKEVIRTUAL brw.a (Lajt;ILjava/lang/String;)V
   L33
    LINENUMBER 741 L33
    ALOAD 0
    GETSTATIC aju.t : Laml;
    GETSTATIC anj$a.b : Lanj$a;
    INVOKEVIRTUAL anj$a.a ()I
    LDC "spruce_leaves"
    INVOKEVIRTUAL brw.a (Lajt;ILjava/lang/String;)V
   L34
    LINENUMBER 742 L34
    ALOAD 0
    GETSTATIC aju.u : Laml;
    GETSTATIC anj$a.e : Lanj$a;
    INVOKEVIRTUAL anj$a.a ()I
    ICONST_4
    ISUB
    LDC "acacia_leaves"
    INVOKEVIRTUAL brw.a (Lajt;ILjava/lang/String;)V
   L35
    LINENUMBER 743 L35
    ALOAD 0
    GETSTATIC aju.u : Laml;
    GETSTATIC anj$a.f : Lanj$a;
    INVOKEVIRTUAL anj$a.a ()I
    ICONST_4
    ISUB
    LDC "dark_oak_leaves"
    INVOKEVIRTUAL brw.a (Lajt;ILjava/lang/String;)V
   L36
    LINENUMBER 744 L36
    ALOAD 0
    GETSTATIC aju.r : Lajt;
    GETSTATIC anj$a.c : Lanj$a;
    INVOKEVIRTUAL anj$a.a ()I
    LDC "birch_log"
    INVOKEVIRTUAL brw.a (Lajt;ILjava/lang/String;)V
   L37
    LINENUMBER 745 L37
    ALOAD 0
    GETSTATIC aju.r : Lajt;
    GETSTATIC anj$a.d : Lanj$a;
    INVOKEVIRTUAL anj$a.a ()I
    LDC "jungle_log"
    INVOKEVIRTUAL brw.a (Lajt;ILjava/lang/String;)V
   L38
    LINENUMBER 746 L38
    ALOAD 0
    GETSTATIC aju.r : Lajt;
    GETSTATIC anj$a.a : Lanj$a;
    INVOKEVIRTUAL anj$a.a ()I
    LDC "oak_log"
    INVOKEVIRTUAL brw.a (Lajt;ILjava/lang/String;)V
   L39
    LINENUMBER 747 L39
    ALOAD 0
    GETSTATIC aju.r : Lajt;
    GETSTATIC anj$a.b : Lanj$a;
    INVOKEVIRTUAL anj$a.a ()I
    LDC "spruce_log"
    INVOKEVIRTUAL brw.a (Lajt;ILjava/lang/String;)V
   L40
    LINENUMBER 748 L40
    ALOAD 0
    GETSTATIC aju.s : Lajt;
    GETSTATIC anj$a.e : Lanj$a;
    INVOKEVIRTUAL anj$a.a ()I
    ICONST_4
    ISUB
    LDC "acacia_log"
    INVOKEVIRTUAL brw.a (Lajt;ILjava/lang/String;)V
   L41
    LINENUMBER 749 L41
    ALOAD 0
    GETSTATIC aju.s : Lajt;
    GETSTATIC anj$a.f : Lanj$a;
    INVOKEVIRTUAL anj$a.a ()I
    ICONST_4
    ISUB
    LDC "dark_oak_log"
    INVOKEVIRTUAL brw.a (Lajt;ILjava/lang/String;)V
   L42
    LINENUMBER 750 L42
    ALOAD 0
    GETSTATIC aju.be : Lajt;
    GETSTATIC amt$a.f : Lamt$a;
    INVOKEVIRTUAL amt$a.a ()I
    LDC "chiseled_brick_monster_egg"
    INVOKEVIRTUAL brw.a (Lajt;ILjava/lang/String;)V
   L43
    LINENUMBER 751 L43
    ALOAD 0
    GETSTATIC aju.be : Lajt;
    GETSTATIC amt$a.b : Lamt$a;
    INVOKEVIRTUAL amt$a.a ()I
    LDC "cobblestone_monster_egg"
    INVOKEVIRTUAL brw.a (Lajt;ILjava/lang/String;)V
   L44
    LINENUMBER 752 L44
    ALOAD 0
    GETSTATIC aju.be : Lajt;
    GETSTATIC amt$a.e : Lamt$a;
    INVOKEVIRTUAL amt$a.a ()I
    LDC "cracked_brick_monster_egg"
    INVOKEVIRTUAL brw.a (Lajt;ILjava/lang/String;)V
   L45
    LINENUMBER 753 L45
    ALOAD 0
    GETSTATIC aju.be : Lajt;
    GETSTATIC amt$a.d : Lamt$a;
    INVOKEVIRTUAL amt$a.a ()I
    LDC "mossy_brick_monster_egg"
    INVOKEVIRTUAL brw.a (Lajt;ILjava/lang/String;)V
   L46
    LINENUMBER 754 L46
    ALOAD 0
    GETSTATIC aju.be : Lajt;
    GETSTATIC amt$a.a : Lamt$a;
    INVOKEVIRTUAL amt$a.a ()I
    LDC "stone_monster_egg"
    INVOKEVIRTUAL brw.a (Lajt;ILjava/lang/String;)V
   L47
    LINENUMBER 755 L47
    ALOAD 0
    GETSTATIC aju.be : Lajt;
    GETSTATIC amt$a.c : Lamt$a;
    INVOKEVIRTUAL amt$a.a ()I
    LDC "stone_brick_monster_egg"
    INVOKEVIRTUAL brw.a (Lajt;ILjava/lang/String;)V
   L48
    LINENUMBER 756 L48
    ALOAD 0
    GETSTATIC aju.f : Lajt;
    GETSTATIC anj$a.e : Lanj$a;
    INVOKEVIRTUAL anj$a.a ()I
    LDC "acacia_planks"
    INVOKEVIRTUAL brw.a (Lajt;ILjava/lang/String;)V
   L49
    LINENUMBER 757 L49
    ALOAD 0
    GETSTATIC aju.f : Lajt;
    GETSTATIC anj$a.c : Lanj$a;
    INVOKEVIRTUAL anj$a.a ()I
    LDC "birch_planks"
    INVOKEVIRTUAL brw.a (Lajt;ILjava/lang/String;)V
   L50
    LINENUMBER 758 L50
    ALOAD 0
    GETSTATIC aju.f : Lajt;
    GETSTATIC anj$a.f : Lanj$a;
    INVOKEVIRTUAL anj$a.a ()I
    LDC "dark_oak_planks"
    INVOKEVIRTUAL brw.a (Lajt;ILjava/lang/String;)V
   L51
    LINENUMBER 759 L51
    ALOAD 0
    GETSTATIC aju.f : Lajt;
    GETSTATIC anj$a.d : Lanj$a;
    INVOKEVIRTUAL anj$a.a ()I
    LDC "jungle_planks"
    INVOKEVIRTUAL brw.a (Lajt;ILjava/lang/String;)V
   L52
    LINENUMBER 760 L52
    ALOAD 0
    GETSTATIC aju.f : Lajt;
    GETSTATIC anj$a.a : Lanj$a;
    INVOKEVIRTUAL anj$a.a ()I
    LDC "oak_planks"
    INVOKEVIRTUAL brw.a (Lajt;ILjava/lang/String;)V
   L53
    LINENUMBER 761 L53
    ALOAD 0
    GETSTATIC aju.f : Lajt;
    GETSTATIC anj$a.b : Lanj$a;
    INVOKEVIRTUAL anj$a.a ()I
    LDC "spruce_planks"
    INVOKEVIRTUAL brw.a (Lajt;ILjava/lang/String;)V
   L54
    LINENUMBER 762 L54
    ALOAD 0
    GETSTATIC aju.cI : Lajt;
    GETSTATIC anp$a.b : Lanp$a;
    INVOKEVIRTUAL anp$a.a ()I
    LDC "prismarine_bricks"
    INVOKEVIRTUAL brw.a (Lajt;ILjava/lang/String;)V
   L55
    LINENUMBER 763 L55
    ALOAD 0
    GETSTATIC aju.cI : Lajt;
    GETSTATIC anp$a.c : Lanp$a;
    INVOKEVIRTUAL anp$a.a ()I
    LDC "dark_prismarine"
    INVOKEVIRTUAL brw.a (Lajt;ILjava/lang/String;)V
   L56
    LINENUMBER 764 L56
    ALOAD 0
    GETSTATIC aju.cI : Lajt;
    GETSTATIC anp$a.a : Lanp$a;
    INVOKEVIRTUAL anp$a.a ()I
    LDC "prismarine"
    INVOKEVIRTUAL brw.a (Lajt;ILjava/lang/String;)V
   L57
    LINENUMBER 765 L57
    ALOAD 0
    GETSTATIC aju.cq : Lajt;
    GETSTATIC ans$a.b : Lans$a;
    INVOKEVIRTUAL ans$a.a ()I
    LDC "chiseled_quartz_block"
    INVOKEVIRTUAL brw.a (Lajt;ILjava/lang/String;)V
   L58
    LINENUMBER 766 L58
    ALOAD 0
    GETSTATIC aju.cq : Lajt;
    GETSTATIC ans$a.a : Lans$a;
    INVOKEVIRTUAL ans$a.a ()I
    LDC "quartz_block"
    INVOKEVIRTUAL brw.a (Lajt;ILjava/lang/String;)V
   L59
    LINENUMBER 767 L59
    ALOAD 0
    GETSTATIC aju.cq : Lajt;
    GETSTATIC ans$a.c : Lans$a;
    INVOKEVIRTUAL ans$a.a ()I
    LDC "quartz_column"
    INVOKEVIRTUAL brw.a (Lajt;ILjava/lang/String;)V
   L60
    LINENUMBER 768 L60
    ALOAD 0
    GETSTATIC aju.O : Lalm;
    GETSTATIC alm$a.d : Lalm$a;
    INVOKEVIRTUAL alm$a.b ()I
    LDC "allium"
    INVOKEVIRTUAL brw.a (Lajt;ILjava/lang/String;)V
   L61
    LINENUMBER 769 L61
    ALOAD 0
    GETSTATIC aju.O : Lalm;
    GETSTATIC alm$a.c : Lalm$a;
    INVOKEVIRTUAL alm$a.b ()I
    LDC "blue_orchid"
    INVOKEVIRTUAL brw.a (Lajt;ILjava/lang/String;)V
   L62
    LINENUMBER 770 L62
    ALOAD 0
    GETSTATIC aju.O : Lalm;
    GETSTATIC alm$a.e : Lalm$a;
    INVOKEVIRTUAL alm$a.b ()I
    LDC "houstonia"
    INVOKEVIRTUAL brw.a (Lajt;ILjava/lang/String;)V
   L63
    LINENUMBER 771 L63
    ALOAD 0
    GETSTATIC aju.O : Lalm;
    GETSTATIC alm$a.g : Lalm$a;
    INVOKEVIRTUAL alm$a.b ()I
    LDC "orange_tulip"
    INVOKEVIRTUAL brw.a (Lajt;ILjava/lang/String;)V
   L64
    LINENUMBER 772 L64
    ALOAD 0
    GETSTATIC aju.O : Lalm;
    GETSTATIC alm$a.j : Lalm$a;
    INVOKEVIRTUAL alm$a.b ()I
    LDC "oxeye_daisy"
    INVOKEVIRTUAL brw.a (Lajt;ILjava/lang/String;)V
   L65
    LINENUMBER 773 L65
    ALOAD 0
    GETSTATIC aju.O : Lalm;
    GETSTATIC alm$a.i : Lalm$a;
    INVOKEVIRTUAL alm$a.b ()I
    LDC "pink_tulip"
    INVOKEVIRTUAL brw.a (Lajt;ILjava/lang/String;)V
   L66
    LINENUMBER 774 L66
    ALOAD 0
    GETSTATIC aju.O : Lalm;
    GETSTATIC alm$a.b : Lalm$a;
    INVOKEVIRTUAL alm$a.b ()I
    LDC "poppy"
    INVOKEVIRTUAL brw.a (Lajt;ILjava/lang/String;)V
   L67
    LINENUMBER 775 L67
    ALOAD 0
    GETSTATIC aju.O : Lalm;
    GETSTATIC alm$a.f : Lalm$a;
    INVOKEVIRTUAL alm$a.b ()I
    LDC "red_tulip"
    INVOKEVIRTUAL brw.a (Lajt;ILjava/lang/String;)V
   L68
    LINENUMBER 776 L68
    ALOAD 0
    GETSTATIC aju.O : Lalm;
    GETSTATIC alm$a.h : Lalm$a;
    INVOKEVIRTUAL alm$a.b ()I
    LDC "white_tulip"
    INVOKEVIRTUAL brw.a (Lajt;ILjava/lang/String;)V
   L69
    LINENUMBER 777 L69
    ALOAD 0
    GETSTATIC aju.m : Laof;
    GETSTATIC aof$a.b : Laof$a;
    INVOKEVIRTUAL aof$a.a ()I
    LDC "red_sand"
    INVOKEVIRTUAL brw.a (Lajt;ILjava/lang/String;)V
   L70
    LINENUMBER 778 L70
    ALOAD 0
    GETSTATIC aju.m : Laof;
    GETSTATIC aof$a.a : Laof$a;
    INVOKEVIRTUAL aof$a.a ()I
    LDC "sand"
    INVOKEVIRTUAL brw.a (Lajt;ILjava/lang/String;)V
   L71
    LINENUMBER 779 L71
    ALOAD 0
    GETSTATIC aju.A : Lajt;
    GETSTATIC aog$a.b : Laog$a;
    INVOKEVIRTUAL aog$a.a ()I
    LDC "chiseled_sandstone"
    INVOKEVIRTUAL brw.a (Lajt;ILjava/lang/String;)V
   L72
    LINENUMBER 780 L72
    ALOAD 0
    GETSTATIC aju.A : Lajt;
    GETSTATIC aog$a.a : Laog$a;
    INVOKEVIRTUAL aog$a.a ()I
    LDC "sandstone"
    INVOKEVIRTUAL brw.a (Lajt;ILjava/lang/String;)V
   L73
    LINENUMBER 781 L73
    ALOAD 0
    GETSTATIC aju.A : Lajt;
    GETSTATIC aog$a.c : Laog$a;
    INVOKEVIRTUAL aog$a.a ()I
    LDC "smooth_sandstone"
    INVOKEVIRTUAL brw.a (Lajt;ILjava/lang/String;)V
   L74
    LINENUMBER 782 L74
    ALOAD 0
    GETSTATIC aju.cM : Lajt;
    GETSTATIC anv$a.b : Lanv$a;
    INVOKEVIRTUAL anv$a.a ()I
    LDC "chiseled_red_sandstone"
    INVOKEVIRTUAL brw.a (Lajt;ILjava/lang/String;)V
   L75
    LINENUMBER 783 L75
    ALOAD 0
    GETSTATIC aju.cM : Lajt;
    GETSTATIC anv$a.a : Lanv$a;
    INVOKEVIRTUAL anv$a.a ()I
    LDC "red_sandstone"
    INVOKEVIRTUAL brw.a (Lajt;ILjava/lang/String;)V
   L76
    LINENUMBER 784 L76
    ALOAD 0
    GETSTATIC aju.cM : Lajt;
    GETSTATIC anv$a.c : Lanv$a;
    INVOKEVIRTUAL anv$a.a ()I
    LDC "smooth_red_sandstone"
    INVOKEVIRTUAL brw.a (Lajt;ILjava/lang/String;)V
   L77
    LINENUMBER 785 L77
    ALOAD 0
    GETSTATIC aju.g : Lajt;
    GETSTATIC anj$a.e : Lanj$a;
    INVOKEVIRTUAL anj$a.a ()I
    LDC "acacia_sapling"
    INVOKEVIRTUAL brw.a (Lajt;ILjava/lang/String;)V
   L78
    LINENUMBER 786 L78
    ALOAD 0
    GETSTATIC aju.g : Lajt;
    GETSTATIC anj$a.c : Lanj$a;
    INVOKEVIRTUAL anj$a.a ()I
    LDC "birch_sapling"
    INVOKEVIRTUAL brw.a (Lajt;ILjava/lang/String;)V
   L79
    LINENUMBER 787 L79
    ALOAD 0
    GETSTATIC aju.g : Lajt;
    GETSTATIC anj$a.f : Lanj$a;
    INVOKEVIRTUAL anj$a.a ()I
    LDC "dark_oak_sapling"
    INVOKEVIRTUAL brw.a (Lajt;ILjava/lang/String;)V
   L80
    LINENUMBER 788 L80
    ALOAD 0
    GETSTATIC aju.g : Lajt;
    GETSTATIC anj$a.d : Lanj$a;
    INVOKEVIRTUAL anj$a.a ()I
    LDC "jungle_sapling"
    INVOKEVIRTUAL brw.a (Lajt;ILjava/lang/String;)V
   L81
    LINENUMBER 789 L81
    ALOAD 0
    GETSTATIC aju.g : Lajt;
    GETSTATIC anj$a.a : Lanj$a;
    INVOKEVIRTUAL anj$a.a ()I
    LDC "oak_sapling"
    INVOKEVIRTUAL brw.a (Lajt;ILjava/lang/String;)V
   L82
    LINENUMBER 790 L82
    ALOAD 0
    GETSTATIC aju.g : Lajt;
    GETSTATIC anj$a.b : Lanj$a;
    INVOKEVIRTUAL anj$a.a ()I
    LDC "spruce_sapling"
    INVOKEVIRTUAL brw.a (Lajt;ILjava/lang/String;)V
   L83
    LINENUMBER 791 L83
    ALOAD 0
    GETSTATIC aju.v : Lajt;
    ICONST_0
    LDC "sponge"
    INVOKEVIRTUAL brw.a (Lajt;ILjava/lang/String;)V
   L84
    LINENUMBER 792 L84
    ALOAD 0
    GETSTATIC aju.v : Lajt;
    ICONST_1
    LDC "sponge_wet"
    INVOKEVIRTUAL brw.a (Lajt;ILjava/lang/String;)V
   L85
    LINENUMBER 793 L85
    ALOAD 0
    GETSTATIC aju.cG : Laor;
    GETSTATIC act.p : Lact;
    INVOKEVIRTUAL act.a ()I
    LDC "black_stained_glass"
    INVOKEVIRTUAL brw.a (Lajt;ILjava/lang/String;)V
   L86
    LINENUMBER 794 L86
    ALOAD 0
    GETSTATIC aju.cG : Laor;
    GETSTATIC act.l : Lact;
    INVOKEVIRTUAL act.a ()I
    LDC "blue_stained_glass"
    INVOKEVIRTUAL brw.a (Lajt;ILjava/lang/String;)V
   L87
    LINENUMBER 795 L87
    ALOAD 0
    GETSTATIC aju.cG : Laor;
    GETSTATIC act.m : Lact;
    INVOKEVIRTUAL act.a ()I
    LDC "brown_stained_glass"
    INVOKEVIRTUAL brw.a (Lajt;ILjava/lang/String;)V
   L88
    LINENUMBER 796 L88
    ALOAD 0
    GETSTATIC aju.cG : Laor;
    GETSTATIC act.j : Lact;
    INVOKEVIRTUAL act.a ()I
    LDC "cyan_stained_glass"
    INVOKEVIRTUAL brw.a (Lajt;ILjava/lang/String;)V
   L89
    LINENUMBER 797 L89
    ALOAD 0
    GETSTATIC aju.cG : Laor;
    GETSTATIC act.h : Lact;
    INVOKEVIRTUAL act.a ()I
    LDC "gray_stained_glass"
    INVOKEVIRTUAL brw.a (Lajt;ILjava/lang/String;)V
   L90
    LINENUMBER 798 L90
    ALOAD 0
    GETSTATIC aju.cG : Laor;
    GETSTATIC act.n : Lact;
    INVOKEVIRTUAL act.a ()I
    LDC "green_stained_glass"
    INVOKEVIRTUAL brw.a (Lajt;ILjava/lang/String;)V
   L91
    LINENUMBER 799 L91
    ALOAD 0
    GETSTATIC aju.cG : Laor;
    GETSTATIC act.d : Lact;
    INVOKEVIRTUAL act.a ()I
    LDC "light_blue_stained_glass"
    INVOKEVIRTUAL brw.a (Lajt;ILjava/lang/String;)V
   L92
    LINENUMBER 800 L92
    ALOAD 0
    GETSTATIC aju.cG : Laor;
    GETSTATIC act.f : Lact;
    INVOKEVIRTUAL act.a ()I
    LDC "lime_stained_glass"
    INVOKEVIRTUAL brw.a (Lajt;ILjava/lang/String;)V
   L93
    LINENUMBER 801 L93
    ALOAD 0
    GETSTATIC aju.cG : Laor;
    GETSTATIC act.c : Lact;
    INVOKEVIRTUAL act.a ()I
    LDC "magenta_stained_glass"
    INVOKEVIRTUAL brw.a (Lajt;ILjava/lang/String;)V
   L94
    LINENUMBER 802 L94
    ALOAD 0
    GETSTATIC aju.cG : Laor;
    GETSTATIC act.b : Lact;
    INVOKEVIRTUAL act.a ()I
    LDC "orange_stained_glass"
    INVOKEVIRTUAL brw.a (Lajt;ILjava/lang/String;)V
   L95
    LINENUMBER 803 L95
    ALOAD 0
    GETSTATIC aju.cG : Laor;
    GETSTATIC act.g : Lact;
    INVOKEVIRTUAL act.a ()I
    LDC "pink_stained_glass"
    INVOKEVIRTUAL brw.a (Lajt;ILjava/lang/String;)V
   L96
    LINENUMBER 804 L96
    ALOAD 0
    GETSTATIC aju.cG : Laor;
    GETSTATIC act.k : Lact;
    INVOKEVIRTUAL act.a ()I
    LDC "purple_stained_glass"
    INVOKEVIRTUAL brw.a (Lajt;ILjava/lang/String;)V
   L97
    LINENUMBER 805 L97
    ALOAD 0
    GETSTATIC aju.cG : Laor;
    GETSTATIC act.o : Lact;
    INVOKEVIRTUAL act.a ()I
    LDC "red_stained_glass"
    INVOKEVIRTUAL brw.a (Lajt;ILjava/lang/String;)V
   L98
    LINENUMBER 806 L98
    ALOAD 0
    GETSTATIC aju.cG : Laor;
    GETSTATIC act.i : Lact;
    INVOKEVIRTUAL act.a ()I
    LDC "silver_stained_glass"
    INVOKEVIRTUAL brw.a (Lajt;ILjava/lang/String;)V
   L99
    LINENUMBER 807 L99
    ALOAD 0
    GETSTATIC aju.cG : Laor;
    GETSTATIC act.a : Lact;
    INVOKEVIRTUAL act.a ()I
    LDC "white_stained_glass"
    INVOKEVIRTUAL brw.a (Lajt;ILjava/lang/String;)V
   L100
    LINENUMBER 808 L100
    ALOAD 0
    GETSTATIC aju.cG : Laor;
    GETSTATIC act.e : Lact;
    INVOKEVIRTUAL act.a ()I
    LDC "yellow_stained_glass"
    INVOKEVIRTUAL brw.a (Lajt;ILjava/lang/String;)V
   L101
    LINENUMBER 809 L101
    ALOAD 0
    GETSTATIC aju.cH : Laos;
    GETSTATIC act.p : Lact;
    INVOKEVIRTUAL act.a ()I
    LDC "black_stained_glass_pane"
    INVOKEVIRTUAL brw.a (Lajt;ILjava/lang/String;)V
   L102
    LINENUMBER 810 L102
    ALOAD 0
    GETSTATIC aju.cH : Laos;
    GETSTATIC act.l : Lact;
    INVOKEVIRTUAL act.a ()I
    LDC "blue_stained_glass_pane"
    INVOKEVIRTUAL brw.a (Lajt;ILjava/lang/String;)V
   L103
    LINENUMBER 811 L103
    ALOAD 0
    GETSTATIC aju.cH : Laos;
    GETSTATIC act.m : Lact;
    INVOKEVIRTUAL act.a ()I
    LDC "brown_stained_glass_pane"
    INVOKEVIRTUAL brw.a (Lajt;ILjava/lang/String;)V
   L104
    LINENUMBER 812 L104
    ALOAD 0
    GETSTATIC aju.cH : Laos;
    GETSTATIC act.j : Lact;
    INVOKEVIRTUAL act.a ()I
    LDC "cyan_stained_glass_pane"
    INVOKEVIRTUAL brw.a (Lajt;ILjava/lang/String;)V
   L105
    LINENUMBER 813 L105
    ALOAD 0
    GETSTATIC aju.cH : Laos;
    GETSTATIC act.h : Lact;
    INVOKEVIRTUAL act.a ()I
    LDC "gray_stained_glass_pane"
    INVOKEVIRTUAL brw.a (Lajt;ILjava/lang/String;)V
   L106
    LINENUMBER 814 L106
    ALOAD 0
    GETSTATIC aju.cH : Laos;
    GETSTATIC act.n : Lact;
    INVOKEVIRTUAL act.a ()I
    LDC "green_stained_glass_pane"
    INVOKEVIRTUAL brw.a (Lajt;ILjava/lang/String;)V
   L107
    LINENUMBER 815 L107
    ALOAD 0
    GETSTATIC aju.cH : Laos;
    GETSTATIC act.d : Lact;
    INVOKEVIRTUAL act.a ()I
    LDC "light_blue_stained_glass_pane"
    INVOKEVIRTUAL brw.a (Lajt;ILjava/lang/String;)V
   L108
    LINENUMBER 816 L108
    ALOAD 0
    GETSTATIC aju.cH : Laos;
    GETSTATIC act.f : Lact;
    INVOKEVIRTUAL act.a ()I
    LDC "lime_stained_glass_pane"
    INVOKEVIRTUAL brw.a (Lajt;ILjava/lang/String;)V
   L109
    LINENUMBER 817 L109
    ALOAD 0
    GETSTATIC aju.cH : Laos;
    GETSTATIC act.c : Lact;
    INVOKEVIRTUAL act.a ()I
    LDC "magenta_stained_glass_pane"
    INVOKEVIRTUAL brw.a (Lajt;ILjava/lang/String;)V
   L110
    LINENUMBER 818 L110
    ALOAD 0
    GETSTATIC aju.cH : Laos;
    GETSTATIC act.b : Lact;
    INVOKEVIRTUAL act.a ()I
    LDC "orange_stained_glass_pane"
    INVOKEVIRTUAL brw.a (Lajt;ILjava/lang/String;)V
   L111
    LINENUMBER 819 L111
    ALOAD 0
    GETSTATIC aju.cH : Laos;
    GETSTATIC act.g : Lact;
    INVOKEVIRTUAL act.a ()I
    LDC "pink_stained_glass_pane"
    INVOKEVIRTUAL brw.a (Lajt;ILjava/lang/String;)V
   L112
    LINENUMBER 820 L112
    ALOAD 0
    GETSTATIC aju.cH : Laos;
    GETSTATIC act.k : Lact;
    INVOKEVIRTUAL act.a ()I
    LDC "purple_stained_glass_pane"
    INVOKEVIRTUAL brw.a (Lajt;ILjava/lang/String;)V
   L113
    LINENUMBER 821 L113
    ALOAD 0
    GETSTATIC aju.cH : Laos;
    GETSTATIC act.o : Lact;
    INVOKEVIRTUAL act.a ()I
    LDC "red_stained_glass_pane"
    INVOKEVIRTUAL brw.a (Lajt;ILjava/lang/String;)V
   L114
    LINENUMBER 822 L114
    ALOAD 0
    GETSTATIC aju.cH : Laos;
    GETSTATIC act.i : Lact;
    INVOKEVIRTUAL act.a ()I
    LDC "silver_stained_glass_pane"
    INVOKEVIRTUAL brw.a (Lajt;ILjava/lang/String;)V
   L115
    LINENUMBER 823 L115
    ALOAD 0
    GETSTATIC aju.cH : Laos;
    GETSTATIC act.a : Lact;
    INVOKEVIRTUAL act.a ()I
    LDC "white_stained_glass_pane"
    INVOKEVIRTUAL brw.a (Lajt;ILjava/lang/String;)V
   L116
    LINENUMBER 824 L116
    ALOAD 0
    GETSTATIC aju.cH : Laos;
    GETSTATIC act.e : Lact;
    INVOKEVIRTUAL act.a ()I
    LDC "yellow_stained_glass_pane"
    INVOKEVIRTUAL brw.a (Lajt;ILjava/lang/String;)V
   L117
    LINENUMBER 825 L117
    ALOAD 0
    GETSTATIC aju.cu : Lajt;
    GETSTATIC act.p : Lact;
    INVOKEVIRTUAL act.a ()I
    LDC "black_stained_hardened_clay"
    INVOKEVIRTUAL brw.a (Lajt;ILjava/lang/String;)V
   L118
    LINENUMBER 826 L118
    ALOAD 0
    GETSTATIC aju.cu : Lajt;
    GETSTATIC act.l : Lact;
    INVOKEVIRTUAL act.a ()I
    LDC "blue_stained_hardened_clay"
    INVOKEVIRTUAL brw.a (Lajt;ILjava/lang/String;)V
   L119
    LINENUMBER 827 L119
    ALOAD 0
    GETSTATIC aju.cu : Lajt;
    GETSTATIC act.m : Lact;
    INVOKEVIRTUAL act.a ()I
    LDC "brown_stained_hardened_clay"
    INVOKEVIRTUAL brw.a (Lajt;ILjava/lang/String;)V
   L120
    LINENUMBER 828 L120
    ALOAD 0
    GETSTATIC aju.cu : Lajt;
    GETSTATIC act.j : Lact;
    INVOKEVIRTUAL act.a ()I
    LDC "cyan_stained_hardened_clay"
    INVOKEVIRTUAL brw.a (Lajt;ILjava/lang/String;)V
   L121
    LINENUMBER 829 L121
    ALOAD 0
    GETSTATIC aju.cu : Lajt;
    GETSTATIC act.h : Lact;
    INVOKEVIRTUAL act.a ()I
    LDC "gray_stained_hardened_clay"
    INVOKEVIRTUAL brw.a (Lajt;ILjava/lang/String;)V
   L122
    LINENUMBER 830 L122
    ALOAD 0
    GETSTATIC aju.cu : Lajt;
    GETSTATIC act.n : Lact;
    INVOKEVIRTUAL act.a ()I
    LDC "green_stained_hardened_clay"
    INVOKEVIRTUAL brw.a (Lajt;ILjava/lang/String;)V
   L123
    LINENUMBER 831 L123
    ALOAD 0
    GETSTATIC aju.cu : Lajt;
    GETSTATIC act.d : Lact;
    INVOKEVIRTUAL act.a ()I
    LDC "light_blue_stained_hardened_clay"
    INVOKEVIRTUAL brw.a (Lajt;ILjava/lang/String;)V
   L124
    LINENUMBER 832 L124
    ALOAD 0
    GETSTATIC aju.cu : Lajt;
    GETSTATIC act.f : Lact;
    INVOKEVIRTUAL act.a ()I
    LDC "lime_stained_hardened_clay"
    INVOKEVIRTUAL brw.a (Lajt;ILjava/lang/String;)V
   L125
    LINENUMBER 833 L125
    ALOAD 0
    GETSTATIC aju.cu : Lajt;
    GETSTATIC act.c : Lact;
    INVOKEVIRTUAL act.a ()I
    LDC "magenta_stained_hardened_clay"
    INVOKEVIRTUAL brw.a (Lajt;ILjava/lang/String;)V
   L126
    LINENUMBER 834 L126
    ALOAD 0
    GETSTATIC aju.cu : Lajt;
    GETSTATIC act.b : Lact;
    INVOKEVIRTUAL act.a ()I
    LDC "orange_stained_hardened_clay"
    INVOKEVIRTUAL brw.a (Lajt;ILjava/lang/String;)V
   L127
    LINENUMBER 835 L127
    ALOAD 0
    GETSTATIC aju.cu : Lajt;
    GETSTATIC act.g : Lact;
    INVOKEVIRTUAL act.a ()I
    LDC "pink_stained_hardened_clay"
    INVOKEVIRTUAL brw.a (Lajt;ILjava/lang/String;)V
   L128
    LINENUMBER 836 L128
    ALOAD 0
    GETSTATIC aju.cu : Lajt;
    GETSTATIC act.k : Lact;
    INVOKEVIRTUAL act.a ()I
    LDC "purple_stained_hardened_clay"
    INVOKEVIRTUAL brw.a (Lajt;ILjava/lang/String;)V
   L129
    LINENUMBER 837 L129
    ALOAD 0
    GETSTATIC aju.cu : Lajt;
    GETSTATIC act.o : Lact;
    INVOKEVIRTUAL act.a ()I
    LDC "red_stained_hardened_clay"
    INVOKEVIRTUAL brw.a (Lajt;ILjava/lang/String;)V
   L130
    LINENUMBER 838 L130
    ALOAD 0
    GETSTATIC aju.cu : Lajt;
    GETSTATIC act.i : Lact;
    INVOKEVIRTUAL act.a ()I
    LDC "silver_stained_hardened_clay"
    INVOKEVIRTUAL brw.a (Lajt;ILjava/lang/String;)V
   L131
    LINENUMBER 839 L131
    ALOAD 0
    GETSTATIC aju.cu : Lajt;
    GETSTATIC act.a : Lact;
    INVOKEVIRTUAL act.a ()I
    LDC "white_stained_hardened_clay"
    INVOKEVIRTUAL brw.a (Lajt;ILjava/lang/String;)V
   L132
    LINENUMBER 840 L132
    ALOAD 0
    GETSTATIC aju.cu : Lajt;
    GETSTATIC act.e : Lact;
    INVOKEVIRTUAL act.a ()I
    LDC "yellow_stained_hardened_clay"
    INVOKEVIRTUAL brw.a (Lajt;ILjava/lang/String;)V
   L133
    LINENUMBER 841 L133
    ALOAD 0
    GETSTATIC aju.b : Lajt;
    GETSTATIC aox$a.f : Laox$a;
    INVOKEVIRTUAL aox$a.a ()I
    LDC "andesite"
    INVOKEVIRTUAL brw.a (Lajt;ILjava/lang/String;)V
   L134
    LINENUMBER 842 L134
    ALOAD 0
    GETSTATIC aju.b : Lajt;
    GETSTATIC aox$a.g : Laox$a;
    INVOKEVIRTUAL aox$a.a ()I
    LDC "andesite_smooth"
    INVOKEVIRTUAL brw.a (Lajt;ILjava/lang/String;)V
   L135
    LINENUMBER 843 L135
    ALOAD 0
    GETSTATIC aju.b : Lajt;
    GETSTATIC aox$a.d : Laox$a;
    INVOKEVIRTUAL aox$a.a ()I
    LDC "diorite"
    INVOKEVIRTUAL brw.a (Lajt;ILjava/lang/String;)V
   L136
    LINENUMBER 844 L136
    ALOAD 0
    GETSTATIC aju.b : Lajt;
    GETSTATIC aox$a.e : Laox$a;
    INVOKEVIRTUAL aox$a.a ()I
    LDC "diorite_smooth"
    INVOKEVIRTUAL brw.a (Lajt;ILjava/lang/String;)V
   L137
    LINENUMBER 845 L137
    ALOAD 0
    GETSTATIC aju.b : Lajt;
    GETSTATIC aox$a.b : Laox$a;
    INVOKEVIRTUAL aox$a.a ()I
    LDC "granite"
    INVOKEVIRTUAL brw.a (Lajt;ILjava/lang/String;)V
   L138
    LINENUMBER 846 L138
    ALOAD 0
    GETSTATIC aju.b : Lajt;
    GETSTATIC aox$a.c : Laox$a;
    INVOKEVIRTUAL aox$a.a ()I
    LDC "granite_smooth"
    INVOKEVIRTUAL brw.a (Lajt;ILjava/lang/String;)V
   L139
    LINENUMBER 847 L139
    ALOAD 0
    GETSTATIC aju.b : Lajt;
    GETSTATIC aox$a.a : Laox$a;
    INVOKEVIRTUAL aox$a.a ()I
    LDC "stone"
    INVOKEVIRTUAL brw.a (Lajt;ILjava/lang/String;)V
   L140
    LINENUMBER 848 L140
    ALOAD 0
    GETSTATIC aju.bf : Lajt;
    GETSTATIC aoy$a.c : Laoy$a;
    INVOKEVIRTUAL aoy$a.a ()I
    LDC "cracked_stonebrick"
    INVOKEVIRTUAL brw.a (Lajt;ILjava/lang/String;)V
   L141
    LINENUMBER 849 L141
    ALOAD 0
    GETSTATIC aju.bf : Lajt;
    GETSTATIC aoy$a.a : Laoy$a;
    INVOKEVIRTUAL aoy$a.a ()I
    LDC "stonebrick"
    INVOKEVIRTUAL brw.a (Lajt;ILjava/lang/String;)V
   L142
    LINENUMBER 850 L142
    ALOAD 0
    GETSTATIC aju.bf : Lajt;
    GETSTATIC aoy$a.d : Laoy$a;
    INVOKEVIRTUAL aoy$a.a ()I
    LDC "chiseled_stonebrick"
    INVOKEVIRTUAL brw.a (Lajt;ILjava/lang/String;)V
   L143
    LINENUMBER 851 L143
    ALOAD 0
    GETSTATIC aju.bf : Lajt;
    GETSTATIC aoy$a.b : Laoy$a;
    INVOKEVIRTUAL aoy$a.a ()I
    LDC "mossy_stonebrick"
    INVOKEVIRTUAL brw.a (Lajt;ILjava/lang/String;)V
   L144
    LINENUMBER 852 L144
    ALOAD 0
    GETSTATIC aju.U : Lalz;
    GETSTATIC apa$a.e : Lapa$a;
    INVOKEVIRTUAL apa$a.a ()I
    LDC "brick_slab"
    INVOKEVIRTUAL brw.a (Lajt;ILjava/lang/String;)V
   L145
    LINENUMBER 853 L145
    ALOAD 0
    GETSTATIC aju.U : Lalz;
    GETSTATIC apa$a.d : Lapa$a;
    INVOKEVIRTUAL apa$a.a ()I
    LDC "cobblestone_slab"
    INVOKEVIRTUAL brw.a (Lajt;ILjava/lang/String;)V
   L146
    LINENUMBER 854 L146
    ALOAD 0
    GETSTATIC aju.U : Lalz;
    GETSTATIC apa$a.c : Lapa$a;
    INVOKEVIRTUAL apa$a.a ()I
    LDC "old_wood_slab"
    INVOKEVIRTUAL brw.a (Lajt;ILjava/lang/String;)V
   L147
    LINENUMBER 855 L147
    ALOAD 0
    GETSTATIC aju.U : Lalz;
    GETSTATIC apa$a.g : Lapa$a;
    INVOKEVIRTUAL apa$a.a ()I
    LDC "nether_brick_slab"
    INVOKEVIRTUAL brw.a (Lajt;ILjava/lang/String;)V
   L148
    LINENUMBER 856 L148
    ALOAD 0
    GETSTATIC aju.U : Lalz;
    GETSTATIC apa$a.h : Lapa$a;
    INVOKEVIRTUAL apa$a.a ()I
    LDC "quartz_slab"
    INVOKEVIRTUAL brw.a (Lajt;ILjava/lang/String;)V
   L149
    LINENUMBER 857 L149
    ALOAD 0
    GETSTATIC aju.U : Lalz;
    GETSTATIC apa$a.b : Lapa$a;
    INVOKEVIRTUAL apa$a.a ()I
    LDC "sandstone_slab"
    INVOKEVIRTUAL brw.a (Lajt;ILjava/lang/String;)V
   L150
    LINENUMBER 858 L150
    ALOAD 0
    GETSTATIC aju.U : Lalz;
    GETSTATIC apa$a.f : Lapa$a;
    INVOKEVIRTUAL apa$a.a ()I
    LDC "stone_brick_slab"
    INVOKEVIRTUAL brw.a (Lajt;ILjava/lang/String;)V
   L151
    LINENUMBER 859 L151
    ALOAD 0
    GETSTATIC aju.U : Lalz;
    GETSTATIC apa$a.a : Lapa$a;
    INVOKEVIRTUAL apa$a.a ()I
    LDC "stone_slab"
    INVOKEVIRTUAL brw.a (Lajt;ILjava/lang/String;)V
   L152
    LINENUMBER 860 L152
    ALOAD 0
    GETSTATIC aju.cP : Lalz;
    GETSTATIC anb$a.a : Lanb$a;
    INVOKEVIRTUAL anb$a.a ()I
    LDC "red_sandstone_slab"
    INVOKEVIRTUAL brw.a (Lajt;ILjava/lang/String;)V
   L153
    LINENUMBER 861 L153
    ALOAD 0
    GETSTATIC aju.H : Lapc;
    GETSTATIC apc$a.a : Lapc$a;
    INVOKEVIRTUAL apc$a.a ()I
    LDC "dead_bush"
    INVOKEVIRTUAL brw.a (Lajt;ILjava/lang/String;)V
   L154
    LINENUMBER 862 L154
    ALOAD 0
    GETSTATIC aju.H : Lapc;
    GETSTATIC apc$a.c : Lapc$a;
    INVOKEVIRTUAL apc$a.a ()I
    LDC "fern"
    INVOKEVIRTUAL brw.a (Lajt;ILjava/lang/String;)V
   L155
    LINENUMBER 863 L155
    ALOAD 0
    GETSTATIC aju.H : Lapc;
    GETSTATIC apc$a.b : Lapc$a;
    INVOKEVIRTUAL apc$a.a ()I
    LDC "tall_grass"
    INVOKEVIRTUAL brw.a (Lajt;ILjava/lang/String;)V
   L156
    LINENUMBER 864 L156
    ALOAD 0
    GETSTATIC aju.bM : Lalz;
    GETSTATIC anj$a.e : Lanj$a;
    INVOKEVIRTUAL anj$a.a ()I
    LDC "acacia_slab"
    INVOKEVIRTUAL brw.a (Lajt;ILjava/lang/String;)V
   L157
    LINENUMBER 865 L157
    ALOAD 0
    GETSTATIC aju.bM : Lalz;
    GETSTATIC anj$a.c : Lanj$a;
    INVOKEVIRTUAL anj$a.a ()I
    LDC "birch_slab"
    INVOKEVIRTUAL brw.a (Lajt;ILjava/lang/String;)V
   L158
    LINENUMBER 866 L158
    ALOAD 0
    GETSTATIC aju.bM : Lalz;
    GETSTATIC anj$a.f : Lanj$a;
    INVOKEVIRTUAL anj$a.a ()I
    LDC "dark_oak_slab"
    INVOKEVIRTUAL brw.a (Lajt;ILjava/lang/String;)V
   L159
    LINENUMBER 867 L159
    ALOAD 0
    GETSTATIC aju.bM : Lalz;
    GETSTATIC anj$a.d : Lanj$a;
    INVOKEVIRTUAL anj$a.a ()I
    LDC "jungle_slab"
    INVOKEVIRTUAL brw.a (Lajt;ILjava/lang/String;)V
   L160
    LINENUMBER 868 L160
    ALOAD 0
    GETSTATIC aju.bM : Lalz;
    GETSTATIC anj$a.a : Lanj$a;
    INVOKEVIRTUAL anj$a.a ()I
    LDC "oak_slab"
    INVOKEVIRTUAL brw.a (Lajt;ILjava/lang/String;)V
   L161
    LINENUMBER 869 L161
    ALOAD 0
    GETSTATIC aju.bM : Lalz;
    GETSTATIC anj$a.b : Lanj$a;
    INVOKEVIRTUAL anj$a.a ()I
    LDC "spruce_slab"
    INVOKEVIRTUAL brw.a (Lajt;ILjava/lang/String;)V
   L162
    LINENUMBER 870 L162
    ALOAD 0
    GETSTATIC aju.L : Lajt;
    GETSTATIC act.p : Lact;
    INVOKEVIRTUAL act.a ()I
    LDC "black_wool"
    INVOKEVIRTUAL brw.a (Lajt;ILjava/lang/String;)V
   L163
    LINENUMBER 871 L163
    ALOAD 0
    GETSTATIC aju.L : Lajt;
    GETSTATIC act.l : Lact;
    INVOKEVIRTUAL act.a ()I
    LDC "blue_wool"
    INVOKEVIRTUAL brw.a (Lajt;ILjava/lang/String;)V
   L164
    LINENUMBER 872 L164
    ALOAD 0
    GETSTATIC aju.L : Lajt;
    GETSTATIC act.m : Lact;
    INVOKEVIRTUAL act.a ()I
    LDC "brown_wool"
    INVOKEVIRTUAL brw.a (Lajt;ILjava/lang/String;)V
   L165
    LINENUMBER 873 L165
    ALOAD 0
    GETSTATIC aju.L : Lajt;
    GETSTATIC act.j : Lact;
    INVOKEVIRTUAL act.a ()I
    LDC "cyan_wool"
    INVOKEVIRTUAL brw.a (Lajt;ILjava/lang/String;)V
   L166
    LINENUMBER 874 L166
    ALOAD 0
    GETSTATIC aju.L : Lajt;
    GETSTATIC act.h : Lact;
    INVOKEVIRTUAL act.a ()I
    LDC "gray_wool"
    INVOKEVIRTUAL brw.a (Lajt;ILjava/lang/String;)V
   L167
    LINENUMBER 875 L167
    ALOAD 0
    GETSTATIC aju.L : Lajt;
    GETSTATIC act.n : Lact;
    INVOKEVIRTUAL act.a ()I
    LDC "green_wool"
    INVOKEVIRTUAL brw.a (Lajt;ILjava/lang/String;)V
   L168
    LINENUMBER 876 L168
    ALOAD 0
    GETSTATIC aju.L : Lajt;
    GETSTATIC act.d : Lact;
    INVOKEVIRTUAL act.a ()I
    LDC "light_blue_wool"
    INVOKEVIRTUAL brw.a (Lajt;ILjava/lang/String;)V
   L169
    LINENUMBER 877 L169
    ALOAD 0
    GETSTATIC aju.L : Lajt;
    GETSTATIC act.f : Lact;
    INVOKEVIRTUAL act.a ()I
    LDC "lime_wool"
    INVOKEVIRTUAL brw.a (Lajt;ILjava/lang/String;)V
   L170
    LINENUMBER 878 L170
    ALOAD 0
    GETSTATIC aju.L : Lajt;
    GETSTATIC act.c : Lact;
    INVOKEVIRTUAL act.a ()I
    LDC "magenta_wool"
    INVOKEVIRTUAL brw.a (Lajt;ILjava/lang/String;)V
   L171
    LINENUMBER 879 L171
    ALOAD 0
    GETSTATIC aju.L : Lajt;
    GETSTATIC act.b : Lact;
    INVOKEVIRTUAL act.a ()I
    LDC "orange_wool"
    INVOKEVIRTUAL brw.a (Lajt;ILjava/lang/String;)V
   L172
    LINENUMBER 880 L172
    ALOAD 0
    GETSTATIC aju.L : Lajt;
    GETSTATIC act.g : Lact;
    INVOKEVIRTUAL act.a ()I
    LDC "pink_wool"
    INVOKEVIRTUAL brw.a (Lajt;ILjava/lang/String;)V
   L173
    LINENUMBER 881 L173
    ALOAD 0
    GETSTATIC aju.L : Lajt;
    GETSTATIC act.k : Lact;
    INVOKEVIRTUAL act.a ()I
    LDC "purple_wool"
    INVOKEVIRTUAL brw.a (Lajt;ILjava/lang/String;)V
   L174
    LINENUMBER 882 L174
    ALOAD 0
    GETSTATIC aju.L : Lajt;
    GETSTATIC act.o : Lact;
    INVOKEVIRTUAL act.a ()I
    LDC "red_wool"
    INVOKEVIRTUAL brw.a (Lajt;ILjava/lang/String;)V
   L175
    LINENUMBER 883 L175
    ALOAD 0
    GETSTATIC aju.L : Lajt;
    GETSTATIC act.i : Lact;
    INVOKEVIRTUAL act.a ()I
    LDC "silver_wool"
    INVOKEVIRTUAL brw.a (Lajt;ILjava/lang/String;)V
   L176
    LINENUMBER 884 L176
    ALOAD 0
    GETSTATIC aju.L : Lajt;
    GETSTATIC act.a : Lact;
    INVOKEVIRTUAL act.a ()I
    LDC "white_wool"
    INVOKEVIRTUAL brw.a (Lajt;ILjava/lang/String;)V
   L177
    LINENUMBER 885 L177
    ALOAD 0
    GETSTATIC aju.L : Lajt;
    GETSTATIC act.e : Lact;
    INVOKEVIRTUAL act.a ()I
    LDC "yellow_wool"
    INVOKEVIRTUAL brw.a (Lajt;ILjava/lang/String;)V
   L178
    LINENUMBER 886 L178
    ALOAD 0
    GETSTATIC aju.ak : Lajt;
    LDC "farmland"
    INVOKESPECIAL brw.a (Lajt;Ljava/lang/String;)V
   L179
    LINENUMBER 887 L179
    ALOAD 0
    GETSTATIC aju.cC : Lajt;
    LDC "acacia_stairs"
    INVOKESPECIAL brw.a (Lajt;Ljava/lang/String;)V
   L180
    LINENUMBER 888 L180
    ALOAD 0
    GETSTATIC aju.cs : Lajt;
    LDC "activator_rail"
    INVOKESPECIAL brw.a (Lajt;Ljava/lang/String;)V
   L181
    LINENUMBER 889 L181
    ALOAD 0
    GETSTATIC aju.bY : Lajq;
    LDC "beacon"
    INVOKESPECIAL brw.a (Lajt;Ljava/lang/String;)V
   L182
    LINENUMBER 890 L182
    ALOAD 0
    GETSTATIC aju.h : Lajt;
    LDC "bedrock"
    INVOKESPECIAL brw.a (Lajt;Ljava/lang/String;)V
   L183
    LINENUMBER 891 L183
    ALOAD 0
    GETSTATIC aju.bV : Lajt;
    LDC "birch_stairs"
    INVOKESPECIAL brw.a (Lajt;Ljava/lang/String;)V
   L184
    LINENUMBER 892 L184
    ALOAD 0
    GETSTATIC aju.X : Lajt;
    LDC "bookshelf"
    INVOKESPECIAL brw.a (Lajt;Ljava/lang/String;)V
   L185
    LINENUMBER 893 L185
    ALOAD 0
    GETSTATIC aju.V : Lajt;
    LDC "brick_block"
    INVOKESPECIAL brw.a (Lajt;Ljava/lang/String;)V
   L186
    LINENUMBER 894 L186
    ALOAD 0
    GETSTATIC aju.V : Lajt;
    LDC "brick_block"
    INVOKESPECIAL brw.a (Lajt;Ljava/lang/String;)V
   L187
    LINENUMBER 895 L187
    ALOAD 0
    GETSTATIC aju.bu : Lajt;
    LDC "brick_stairs"
    INVOKESPECIAL brw.a (Lajt;Ljava/lang/String;)V
   L188
    LINENUMBER 896 L188
    ALOAD 0
    GETSTATIC aju.P : Lajy;
    LDC "brown_mushroom"
    INVOKESPECIAL brw.a (Lajt;Ljava/lang/String;)V
   L189
    LINENUMBER 897 L189
    ALOAD 0
    GETSTATIC aju.aK : Laka;
    LDC "cactus"
    INVOKESPECIAL brw.a (Lajt;Ljava/lang/String;)V
   L190
    LINENUMBER 898 L190
    ALOAD 0
    GETSTATIC aju.aL : Lajt;
    LDC "clay"
    INVOKESPECIAL brw.a (Lajt;Ljava/lang/String;)V
   L191
    LINENUMBER 899 L191
    ALOAD 0
    GETSTATIC aju.cA : Lajt;
    LDC "coal_block"
    INVOKESPECIAL brw.a (Lajt;Ljava/lang/String;)V
   L192
    LINENUMBER 900 L192
    ALOAD 0
    GETSTATIC aju.q : Lajt;
    LDC "coal_ore"
    INVOKESPECIAL brw.a (Lajt;Ljava/lang/String;)V
   L193
    LINENUMBER 901 L193
    ALOAD 0
    GETSTATIC aju.e : Lajt;
    LDC "cobblestone"
    INVOKESPECIAL brw.a (Lajt;Ljava/lang/String;)V
   L194
    LINENUMBER 902 L194
    ALOAD 0
    GETSTATIC aju.ai : Lajt;
    LDC "crafting_table"
    INVOKESPECIAL brw.a (Lajt;Ljava/lang/String;)V
   L195
    LINENUMBER 903 L195
    ALOAD 0
    GETSTATIC aju.cD : Lajt;
    LDC "dark_oak_stairs"
    INVOKESPECIAL brw.a (Lajt;Ljava/lang/String;)V
   L196
    LINENUMBER 904 L196
    ALOAD 0
    GETSTATIC aju.cl : Lako;
    LDC "daylight_detector"
    INVOKESPECIAL brw.a (Lajt;Ljava/lang/String;)V
   L197
    LINENUMBER 905 L197
    ALOAD 0
    GETSTATIC aju.I : Lakp;
    LDC "dead_bush"
    INVOKESPECIAL brw.a (Lajt;Ljava/lang/String;)V
   L198
    LINENUMBER 906 L198
    ALOAD 0
    GETSTATIC aju.E : Lajt;
    LDC "detector_rail"
    INVOKESPECIAL brw.a (Lajt;Ljava/lang/String;)V
   L199
    LINENUMBER 907 L199
    ALOAD 0
    GETSTATIC aju.ah : Lajt;
    LDC "diamond_block"
    INVOKESPECIAL brw.a (Lajt;Ljava/lang/String;)V
   L200
    LINENUMBER 908 L200
    ALOAD 0
    GETSTATIC aju.ag : Lajt;
    LDC "diamond_ore"
    INVOKESPECIAL brw.a (Lajt;Ljava/lang/String;)V
   L201
    LINENUMBER 909 L201
    ALOAD 0
    GETSTATIC aju.z : Lajt;
    LDC "dispenser"
    INVOKESPECIAL brw.a (Lajt;Ljava/lang/String;)V
   L202
    LINENUMBER 910 L202
    ALOAD 0
    GETSTATIC aju.ct : Lajt;
    LDC "dropper"
    INVOKESPECIAL brw.a (Lajt;Ljava/lang/String;)V
   L203
    LINENUMBER 911 L203
    ALOAD 0
    GETSTATIC aju.bT : Lajt;
    LDC "emerald_block"
    INVOKESPECIAL brw.a (Lajt;Ljava/lang/String;)V
   L204
    LINENUMBER 912 L204
    ALOAD 0
    GETSTATIC aju.bP : Lajt;
    LDC "emerald_ore"
    INVOKESPECIAL brw.a (Lajt;Ljava/lang/String;)V
   L205
    LINENUMBER 913 L205
    ALOAD 0
    GETSTATIC aju.bC : Lajt;
    LDC "enchanting_table"
    INVOKESPECIAL brw.a (Lajt;Ljava/lang/String;)V
   L206
    LINENUMBER 914 L206
    ALOAD 0
    GETSTATIC aju.bG : Lajt;
    LDC "end_portal_frame"
    INVOKESPECIAL brw.a (Lajt;Ljava/lang/String;)V
   L207
    LINENUMBER 915 L207
    ALOAD 0
    GETSTATIC aju.bH : Lajt;
    LDC "end_stone"
    INVOKESPECIAL brw.a (Lajt;Ljava/lang/String;)V
   L208
    LINENUMBER 916 L208
    ALOAD 0
    GETSTATIC aju.aO : Lajt;
    LDC "oak_fence"
    INVOKESPECIAL brw.a (Lajt;Ljava/lang/String;)V
   L209
    LINENUMBER 917 L209
    ALOAD 0
    GETSTATIC aju.aP : Lajt;
    LDC "spruce_fence"
    INVOKESPECIAL brw.a (Lajt;Ljava/lang/String;)V
   L210
    LINENUMBER 918 L210
    ALOAD 0
    GETSTATIC aju.aQ : Lajt;
    LDC "birch_fence"
    INVOKESPECIAL brw.a (Lajt;Ljava/lang/String;)V
   L211
    LINENUMBER 919 L211
    ALOAD 0
    GETSTATIC aju.aR : Lajt;
    LDC "jungle_fence"
    INVOKESPECIAL brw.a (Lajt;Ljava/lang/String;)V
   L212
    LINENUMBER 920 L212
    ALOAD 0
    GETSTATIC aju.aS : Lajt;
    LDC "dark_oak_fence"
    INVOKESPECIAL brw.a (Lajt;Ljava/lang/String;)V
   L213
    LINENUMBER 921 L213
    ALOAD 0
    GETSTATIC aju.aT : Lajt;
    LDC "acacia_fence"
    INVOKESPECIAL brw.a (Lajt;Ljava/lang/String;)V
   L214
    LINENUMBER 922 L214
    ALOAD 0
    GETSTATIC aju.bo : Lajt;
    LDC "oak_fence_gate"
    INVOKESPECIAL brw.a (Lajt;Ljava/lang/String;)V
   L215
    LINENUMBER 923 L215
    ALOAD 0
    GETSTATIC aju.bp : Lajt;
    LDC "spruce_fence_gate"
    INVOKESPECIAL brw.a (Lajt;Ljava/lang/String;)V
   L216
    LINENUMBER 924 L216
    ALOAD 0
    GETSTATIC aju.bq : Lajt;
    LDC "birch_fence_gate"
    INVOKESPECIAL brw.a (Lajt;Ljava/lang/String;)V
   L217
    LINENUMBER 925 L217
    ALOAD 0
    GETSTATIC aju.br : Lajt;
    LDC "jungle_fence_gate"
    INVOKESPECIAL brw.a (Lajt;Ljava/lang/String;)V
   L218
    LINENUMBER 926 L218
    ALOAD 0
    GETSTATIC aju.bs : Lajt;
    LDC "dark_oak_fence_gate"
    INVOKESPECIAL brw.a (Lajt;Ljava/lang/String;)V
   L219
    LINENUMBER 927 L219
    ALOAD 0
    GETSTATIC aju.bt : Lajt;
    LDC "acacia_fence_gate"
    INVOKESPECIAL brw.a (Lajt;Ljava/lang/String;)V
   L220
    LINENUMBER 928 L220
    ALOAD 0
    GETSTATIC aju.al : Lajt;
    LDC "furnace"
    INVOKESPECIAL brw.a (Lajt;Ljava/lang/String;)V
   L221
    LINENUMBER 929 L221
    ALOAD 0
    GETSTATIC aju.w : Lajt;
    LDC "glass"
    INVOKESPECIAL brw.a (Lajt;Ljava/lang/String;)V
   L222
    LINENUMBER 930 L222
    ALOAD 0
    GETSTATIC aju.bj : Lajt;
    LDC "glass_pane"
    INVOKESPECIAL brw.a (Lajt;Ljava/lang/String;)V
   L223
    LINENUMBER 931 L223
    ALOAD 0
    GETSTATIC aju.aX : Lajt;
    LDC "glowstone"
    INVOKESPECIAL brw.a (Lajt;Ljava/lang/String;)V
   L224
    LINENUMBER 932 L224
    ALOAD 0
    GETSTATIC aju.D : Lajt;
    LDC "golden_rail"
    INVOKESPECIAL brw.a (Lajt;Ljava/lang/String;)V
   L225
    LINENUMBER 933 L225
    ALOAD 0
    GETSTATIC aju.R : Lajt;
    LDC "gold_block"
    INVOKESPECIAL brw.a (Lajt;Ljava/lang/String;)V
   L226
    LINENUMBER 934 L226
    ALOAD 0
    GETSTATIC aju.o : Lajt;
    LDC "gold_ore"
    INVOKESPECIAL brw.a (Lajt;Ljava/lang/String;)V
   L227
    LINENUMBER 935 L227
    ALOAD 0
    GETSTATIC aju.c : Lalv;
    LDC "grass"
    INVOKESPECIAL brw.a (Lajt;Ljava/lang/String;)V
   L228
    LINENUMBER 936 L228
    ALOAD 0
    GETSTATIC aju.da : Lajt;
    LDC "grass_path"
    INVOKESPECIAL brw.a (Lajt;Ljava/lang/String;)V
   L229
    LINENUMBER 937 L229
    ALOAD 0
    GETSTATIC aju.n : Lajt;
    LDC "gravel"
    INVOKESPECIAL brw.a (Lajt;Ljava/lang/String;)V
   L230
    LINENUMBER 938 L230
    ALOAD 0
    GETSTATIC aju.cz : Lajt;
    LDC "hardened_clay"
    INVOKESPECIAL brw.a (Lajt;Ljava/lang/String;)V
   L231
    LINENUMBER 939 L231
    ALOAD 0
    GETSTATIC aju.cx : Lajt;
    LDC "hay_block"
    INVOKESPECIAL brw.a (Lajt;Ljava/lang/String;)V
   L232
    LINENUMBER 940 L232
    ALOAD 0
    GETSTATIC aju.ci : Lajt;
    LDC "heavy_weighted_pressure_plate"
    INVOKESPECIAL brw.a (Lajt;Ljava/lang/String;)V
   L233
    LINENUMBER 941 L233
    ALOAD 0
    GETSTATIC aju.cp : Lamf;
    LDC "hopper"
    INVOKESPECIAL brw.a (Lajt;Ljava/lang/String;)V
   L234
    LINENUMBER 942 L234
    ALOAD 0
    GETSTATIC aju.aI : Lajt;
    LDC "ice"
    INVOKESPECIAL brw.a (Lajt;Ljava/lang/String;)V
   L235
    LINENUMBER 943 L235
    ALOAD 0
    GETSTATIC aju.bi : Lajt;
    LDC "iron_bars"
    INVOKESPECIAL brw.a (Lajt;Ljava/lang/String;)V
   L236
    LINENUMBER 944 L236
    ALOAD 0
    GETSTATIC aju.S : Lajt;
    LDC "iron_block"
    INVOKESPECIAL brw.a (Lajt;Ljava/lang/String;)V
   L237
    LINENUMBER 945 L237
    ALOAD 0
    GETSTATIC aju.p : Lajt;
    LDC "iron_ore"
    INVOKESPECIAL brw.a (Lajt;Ljava/lang/String;)V
   L238
    LINENUMBER 946 L238
    ALOAD 0
    GETSTATIC aju.cw : Lajt;
    LDC "iron_trapdoor"
    INVOKESPECIAL brw.a (Lajt;Ljava/lang/String;)V
   L239
    LINENUMBER 947 L239
    ALOAD 0
    GETSTATIC aju.aN : Lajt;
    LDC "jukebox"
    INVOKESPECIAL brw.a (Lajt;Ljava/lang/String;)V
   L240
    LINENUMBER 948 L240
    ALOAD 0
    GETSTATIC aju.bW : Lajt;
    LDC "jungle_stairs"
    INVOKESPECIAL brw.a (Lajt;Ljava/lang/String;)V
   L241
    LINENUMBER 949 L241
    ALOAD 0
    GETSTATIC aju.au : Lajt;
    LDC "ladder"
    INVOKESPECIAL brw.a (Lajt;Ljava/lang/String;)V
   L242
    LINENUMBER 950 L242
    ALOAD 0
    GETSTATIC aju.y : Lajt;
    LDC "lapis_block"
    INVOKESPECIAL brw.a (Lajt;Ljava/lang/String;)V
   L243
    LINENUMBER 951 L243
    ALOAD 0
    GETSTATIC aju.x : Lajt;
    LDC "lapis_ore"
    INVOKESPECIAL brw.a (Lajt;Ljava/lang/String;)V
   L244
    LINENUMBER 952 L244
    ALOAD 0
    GETSTATIC aju.ay : Lajt;
    LDC "lever"
    INVOKESPECIAL brw.a (Lajt;Ljava/lang/String;)V
   L245
    LINENUMBER 953 L245
    ALOAD 0
    GETSTATIC aju.ch : Lajt;
    LDC "light_weighted_pressure_plate"
    INVOKESPECIAL brw.a (Lajt;Ljava/lang/String;)V
   L246
    LINENUMBER 954 L246
    ALOAD 0
    GETSTATIC aju.aZ : Lajt;
    LDC "lit_pumpkin"
    INVOKESPECIAL brw.a (Lajt;Ljava/lang/String;)V
   L247
    LINENUMBER 955 L247
    ALOAD 0
    GETSTATIC aju.bk : Lajt;
    LDC "melon_block"
    INVOKESPECIAL brw.a (Lajt;Ljava/lang/String;)V
   L248
    LINENUMBER 956 L248
    ALOAD 0
    GETSTATIC aju.Y : Lajt;
    LDC "mossy_cobblestone"
    INVOKESPECIAL brw.a (Lajt;Ljava/lang/String;)V
   L249
    LINENUMBER 957 L249
    ALOAD 0
    GETSTATIC aju.bw : Lamv;
    LDC "mycelium"
    INVOKESPECIAL brw.a (Lajt;Ljava/lang/String;)V
   L250
    LINENUMBER 958 L250
    ALOAD 0
    GETSTATIC aju.aV : Lajt;
    LDC "netherrack"
    INVOKESPECIAL brw.a (Lajt;Ljava/lang/String;)V
   L251
    LINENUMBER 959 L251
    ALOAD 0
    GETSTATIC aju.by : Lajt;
    LDC "nether_brick"
    INVOKESPECIAL brw.a (Lajt;Ljava/lang/String;)V
   L252
    LINENUMBER 960 L252
    ALOAD 0
    GETSTATIC aju.bz : Lajt;
    LDC "nether_brick_fence"
    INVOKESPECIAL brw.a (Lajt;Ljava/lang/String;)V
   L253
    LINENUMBER 961 L253
    ALOAD 0
    GETSTATIC aju.bA : Lajt;
    LDC "nether_brick_stairs"
    INVOKESPECIAL brw.a (Lajt;Ljava/lang/String;)V
   L254
    LINENUMBER 962 L254
    ALOAD 0
    GETSTATIC aju.B : Lajt;
    LDC "noteblock"
    INVOKESPECIAL brw.a (Lajt;Ljava/lang/String;)V
   L255
    LINENUMBER 963 L255
    ALOAD 0
    GETSTATIC aju.ad : Lajt;
    LDC "oak_stairs"
    INVOKESPECIAL brw.a (Lajt;Ljava/lang/String;)V
   L256
    LINENUMBER 964 L256
    ALOAD 0
    GETSTATIC aju.Z : Lajt;
    LDC "obsidian"
    INVOKESPECIAL brw.a (Lajt;Ljava/lang/String;)V
   L257
    LINENUMBER 965 L257
    ALOAD 0
    GETSTATIC aju.cB : Lajt;
    LDC "packed_ice"
    INVOKESPECIAL brw.a (Lajt;Ljava/lang/String;)V
   L258
    LINENUMBER 966 L258
    ALOAD 0
    GETSTATIC aju.J : Laqu;
    LDC "piston"
    INVOKESPECIAL brw.a (Lajt;Ljava/lang/String;)V
   L259
    LINENUMBER 967 L259
    ALOAD 0
    GETSTATIC aju.aU : Lajt;
    LDC "pumpkin"
    INVOKESPECIAL brw.a (Lajt;Ljava/lang/String;)V
   L260
    LINENUMBER 968 L260
    ALOAD 0
    GETSTATIC aju.co : Lajt;
    LDC "quartz_ore"
    INVOKESPECIAL brw.a (Lajt;Ljava/lang/String;)V
   L261
    LINENUMBER 969 L261
    ALOAD 0
    GETSTATIC aju.cr : Lajt;
    LDC "quartz_stairs"
    INVOKESPECIAL brw.a (Lajt;Ljava/lang/String;)V
   L262
    LINENUMBER 970 L262
    ALOAD 0
    GETSTATIC aju.av : Lajt;
    LDC "rail"
    INVOKESPECIAL brw.a (Lajt;Ljava/lang/String;)V
   L263
    LINENUMBER 971 L263
    ALOAD 0
    GETSTATIC aju.cn : Lajt;
    LDC "redstone_block"
    INVOKESPECIAL brw.a (Lajt;Ljava/lang/String;)V
   L264
    LINENUMBER 972 L264
    ALOAD 0
    GETSTATIC aju.bJ : Lajt;
    LDC "redstone_lamp"
    INVOKESPECIAL brw.a (Lajt;Ljava/lang/String;)V
   L265
    LINENUMBER 973 L265
    ALOAD 0
    GETSTATIC aju.aC : Lajt;
    LDC "redstone_ore"
    INVOKESPECIAL brw.a (Lajt;Ljava/lang/String;)V
   L266
    LINENUMBER 974 L266
    ALOAD 0
    GETSTATIC aju.aF : Lajt;
    LDC "redstone_torch"
    INVOKESPECIAL brw.a (Lajt;Ljava/lang/String;)V
   L267
    LINENUMBER 975 L267
    ALOAD 0
    GETSTATIC aju.Q : Lajy;
    LDC "red_mushroom"
    INVOKESPECIAL brw.a (Lajt;Ljava/lang/String;)V
   L268
    LINENUMBER 976 L268
    ALOAD 0
    GETSTATIC aju.bO : Lajt;
    LDC "sandstone_stairs"
    INVOKESPECIAL brw.a (Lajt;Ljava/lang/String;)V
   L269
    LINENUMBER 977 L269
    ALOAD 0
    GETSTATIC aju.cN : Lajt;
    LDC "red_sandstone_stairs"
    INVOKESPECIAL brw.a (Lajt;Ljava/lang/String;)V
   L270
    LINENUMBER 978 L270
    ALOAD 0
    GETSTATIC aju.cJ : Lajt;
    LDC "sea_lantern"
    INVOKESPECIAL brw.a (Lajt;Ljava/lang/String;)V
   L271
    LINENUMBER 979 L271
    ALOAD 0
    GETSTATIC aju.cE : Lajt;
    LDC "slime"
    INVOKESPECIAL brw.a (Lajt;Ljava/lang/String;)V
   L272
    LINENUMBER 980 L272
    ALOAD 0
    GETSTATIC aju.aJ : Lajt;
    LDC "snow"
    INVOKESPECIAL brw.a (Lajt;Ljava/lang/String;)V
   L273
    LINENUMBER 981 L273
    ALOAD 0
    GETSTATIC aju.aH : Lajt;
    LDC "snow_layer"
    INVOKESPECIAL brw.a (Lajt;Ljava/lang/String;)V
   L274
    LINENUMBER 982 L274
    ALOAD 0
    GETSTATIC aju.aW : Lajt;
    LDC "soul_sand"
    INVOKESPECIAL brw.a (Lajt;Ljava/lang/String;)V
   L275
    LINENUMBER 983 L275
    ALOAD 0
    GETSTATIC aju.bU : Lajt;
    LDC "spruce_stairs"
    INVOKESPECIAL brw.a (Lajt;Ljava/lang/String;)V
   L276
    LINENUMBER 984 L276
    ALOAD 0
    GETSTATIC aju.F : Laqu;
    LDC "sticky_piston"
    INVOKESPECIAL brw.a (Lajt;Ljava/lang/String;)V
   L277
    LINENUMBER 985 L277
    ALOAD 0
    GETSTATIC aju.bv : Lajt;
    LDC "stone_brick_stairs"
    INVOKESPECIAL brw.a (Lajt;Ljava/lang/String;)V
   L278
    LINENUMBER 986 L278
    ALOAD 0
    GETSTATIC aju.aG : Lajt;
    LDC "stone_button"
    INVOKESPECIAL brw.a (Lajt;Ljava/lang/String;)V
   L279
    LINENUMBER 987 L279
    ALOAD 0
    GETSTATIC aju.az : Lajt;
    LDC "stone_pressure_plate"
    INVOKESPECIAL brw.a (Lajt;Ljava/lang/String;)V
   L280
    LINENUMBER 988 L280
    ALOAD 0
    GETSTATIC aju.aw : Lajt;
    LDC "stone_stairs"
    INVOKESPECIAL brw.a (Lajt;Ljava/lang/String;)V
   L281
    LINENUMBER 989 L281
    ALOAD 0
    GETSTATIC aju.W : Lajt;
    LDC "tnt"
    INVOKESPECIAL brw.a (Lajt;Ljava/lang/String;)V
   L282
    LINENUMBER 990 L282
    ALOAD 0
    GETSTATIC aju.aa : Lajt;
    LDC "torch"
    INVOKESPECIAL brw.a (Lajt;Ljava/lang/String;)V
   L283
    LINENUMBER 991 L283
    ALOAD 0
    GETSTATIC aju.bd : Lajt;
    LDC "trapdoor"
    INVOKESPECIAL brw.a (Lajt;Ljava/lang/String;)V
   L284
    LINENUMBER 992 L284
    ALOAD 0
    GETSTATIC aju.bR : Lapi;
    LDC "tripwire_hook"
    INVOKESPECIAL brw.a (Lajt;Ljava/lang/String;)V
   L285
    LINENUMBER 993 L285
    ALOAD 0
    GETSTATIC aju.bn : Lajt;
    LDC "vine"
    INVOKESPECIAL brw.a (Lajt;Ljava/lang/String;)V
   L286
    LINENUMBER 994 L286
    ALOAD 0
    GETSTATIC aju.bx : Lajt;
    LDC "waterlily"
    INVOKESPECIAL brw.a (Lajt;Ljava/lang/String;)V
   L287
    LINENUMBER 995 L287
    ALOAD 0
    GETSTATIC aju.G : Lajt;
    LDC "web"
    INVOKESPECIAL brw.a (Lajt;Ljava/lang/String;)V
   L288
    LINENUMBER 996 L288
    ALOAD 0
    GETSTATIC aju.cd : Lajt;
    LDC "wooden_button"
    INVOKESPECIAL brw.a (Lajt;Ljava/lang/String;)V
   L289
    LINENUMBER 997 L289
    ALOAD 0
    GETSTATIC aju.aB : Lajt;
    LDC "wooden_pressure_plate"
    INVOKESPECIAL brw.a (Lajt;Ljava/lang/String;)V
   L290
    LINENUMBER 998 L290
    ALOAD 0
    GETSTATIC aju.N : Lalm;
    GETSTATIC alm$a.a : Lalm$a;
    INVOKEVIRTUAL alm$a.b ()I
    LDC "dandelion"
    INVOKEVIRTUAL brw.a (Lajt;ILjava/lang/String;)V
   L291
    LINENUMBER 999 L291
    ALOAD 0
    GETSTATIC aju.cQ : Lajt;
    LDC "end_rod"
    INVOKESPECIAL brw.a (Lajt;Ljava/lang/String;)V
   L292
    LINENUMBER 1000 L292
    ALOAD 0
    GETSTATIC aju.cR : Lajt;
    LDC "chorus_plant"
    INVOKESPECIAL brw.a (Lajt;Ljava/lang/String;)V
   L293
    LINENUMBER 1001 L293
    ALOAD 0
    GETSTATIC aju.cS : Lajt;
    LDC "chorus_flower"
    INVOKESPECIAL brw.a (Lajt;Ljava/lang/String;)V
   L294
    LINENUMBER 1002 L294
    ALOAD 0
    GETSTATIC aju.cT : Lajt;
    LDC "purpur_block"
    INVOKESPECIAL brw.a (Lajt;Ljava/lang/String;)V
   L295
    LINENUMBER 1003 L295
    ALOAD 0
    GETSTATIC aju.cU : Lajt;
    LDC "purpur_pillar"
    INVOKESPECIAL brw.a (Lajt;Ljava/lang/String;)V
   L296
    LINENUMBER 1004 L296
    ALOAD 0
    GETSTATIC aju.cV : Lajt;
    LDC "purpur_stairs"
    INVOKESPECIAL brw.a (Lajt;Ljava/lang/String;)V
   L297
    LINENUMBER 1005 L297
    ALOAD 0
    GETSTATIC aju.cX : Lalz;
    LDC "purpur_slab"
    INVOKESPECIAL brw.a (Lajt;Ljava/lang/String;)V
   L298
    LINENUMBER 1006 L298
    ALOAD 0
    GETSTATIC aju.cW : Lalz;
    LDC "purpur_double_slab"
    INVOKESPECIAL brw.a (Lajt;Ljava/lang/String;)V
   L299
    LINENUMBER 1007 L299
    ALOAD 0
    GETSTATIC aju.cY : Lajt;
    LDC "end_bricks"
    INVOKESPECIAL brw.a (Lajt;Ljava/lang/String;)V
   L300
    LINENUMBER 1008 L300
    ALOAD 0
    GETSTATIC aju.ae : Lake;
    LDC "chest"
    INVOKESPECIAL brw.a (Lajt;Ljava/lang/String;)V
   L301
    LINENUMBER 1009 L301
    ALOAD 0
    GETSTATIC aju.cg : Lajt;
    LDC "trapped_chest"
    INVOKESPECIAL brw.a (Lajt;Ljava/lang/String;)V
   L302
    LINENUMBER 1010 L302
    ALOAD 0
    GETSTATIC aju.bQ : Lajt;
    LDC "ender_chest"
    INVOKESPECIAL brw.a (Lajt;Ljava/lang/String;)V
   L303
    LINENUMBER 1011 L303
    ALOAD 0
    GETSTATIC ads.a : Lado;
    LDC "iron_shovel"
    INVOKESPECIAL brw.a (Lado;Ljava/lang/String;)V
   L304
    LINENUMBER 1012 L304
    ALOAD 0
    GETSTATIC ads.b : Lado;
    LDC "iron_pickaxe"
    INVOKESPECIAL brw.a (Lado;Ljava/lang/String;)V
   L305
    LINENUMBER 1013 L305
    ALOAD 0
    GETSTATIC ads.c : Lado;
    LDC "iron_axe"
    INVOKESPECIAL brw.a (Lado;Ljava/lang/String;)V
   L306
    LINENUMBER 1014 L306
    ALOAD 0
    GETSTATIC ads.d : Lado;
    LDC "flint_and_steel"
    INVOKESPECIAL brw.a (Lado;Ljava/lang/String;)V
   L307
    LINENUMBER 1015 L307
    ALOAD 0
    GETSTATIC ads.e : Lado;
    LDC "apple"
    INVOKESPECIAL brw.a (Lado;Ljava/lang/String;)V
   L308
    LINENUMBER 1016 L308
    ALOAD 0
    GETSTATIC ads.f : Lach;
    LDC "bow"
    INVOKESPECIAL brw.a (Lado;Ljava/lang/String;)V
   L309
    LINENUMBER 1017 L309
    ALOAD 0
    GETSTATIC ads.g : Lado;
    LDC "arrow"
    INVOKESPECIAL brw.a (Lado;Ljava/lang/String;)V
   L310
    LINENUMBER 1018 L310
    ALOAD 0
    GETSTATIC ads.h : Lado;
    LDC "spectral_arrow"
    INVOKESPECIAL brw.a (Lado;Ljava/lang/String;)V
   L311
    LINENUMBER 1019 L311
    ALOAD 0
    GETSTATIC ads.i : Lado;
    LDC "tipped_arrow"
    INVOKESPECIAL brw.a (Lado;Ljava/lang/String;)V
   L312
    LINENUMBER 1020 L312
    ALOAD 0
    GETSTATIC ads.j : Lado;
    ICONST_0
    LDC "coal"
    INVOKEVIRTUAL brw.a (Lado;ILjava/lang/String;)V
   L313
    LINENUMBER 1021 L313
    ALOAD 0
    GETSTATIC ads.j : Lado;
    ICONST_1
    LDC "charcoal"
    INVOKEVIRTUAL brw.a (Lado;ILjava/lang/String;)V
   L314
    LINENUMBER 1022 L314
    ALOAD 0
    GETSTATIC ads.k : Lado;
    LDC "diamond"
    INVOKESPECIAL brw.a (Lado;Ljava/lang/String;)V
   L315
    LINENUMBER 1023 L315
    ALOAD 0
    GETSTATIC ads.l : Lado;
    LDC "iron_ingot"
    INVOKESPECIAL brw.a (Lado;Ljava/lang/String;)V
   L316
    LINENUMBER 1024 L316
    ALOAD 0
    GETSTATIC ads.m : Lado;
    LDC "gold_ingot"
    INVOKESPECIAL brw.a (Lado;Ljava/lang/String;)V
   L317
    LINENUMBER 1025 L317
    ALOAD 0
    GETSTATIC ads.n : Lado;
    LDC "iron_sword"
    INVOKESPECIAL brw.a (Lado;Ljava/lang/String;)V
   L318
    LINENUMBER 1026 L318
    ALOAD 0
    GETSTATIC ads.o : Lado;
    LDC "wooden_sword"
    INVOKESPECIAL brw.a (Lado;Ljava/lang/String;)V
   L319
    LINENUMBER 1027 L319
    ALOAD 0
    GETSTATIC ads.p : Lado;
    LDC "wooden_shovel"
    INVOKESPECIAL brw.a (Lado;Ljava/lang/String;)V
   L320
    LINENUMBER 1028 L320
    ALOAD 0
    GETSTATIC ads.q : Lado;
    LDC "wooden_pickaxe"
    INVOKESPECIAL brw.a (Lado;Ljava/lang/String;)V
   L321
    LINENUMBER 1029 L321
    ALOAD 0
    GETSTATIC ads.r : Lado;
    LDC "wooden_axe"
    INVOKESPECIAL brw.a (Lado;Ljava/lang/String;)V
   L322
    LINENUMBER 1030 L322
    ALOAD 0
    GETSTATIC ads.s : Lado;
    LDC "stone_sword"
    INVOKESPECIAL brw.a (Lado;Ljava/lang/String;)V
   L323
    LINENUMBER 1031 L323
    ALOAD 0
    GETSTATIC ads.t : Lado;
    LDC "stone_shovel"
    INVOKESPECIAL brw.a (Lado;Ljava/lang/String;)V
   L324
    LINENUMBER 1032 L324
    ALOAD 0
    GETSTATIC ads.u : Lado;
    LDC "stone_pickaxe"
    INVOKESPECIAL brw.a (Lado;Ljava/lang/String;)V
   L325
    LINENUMBER 1033 L325
    ALOAD 0
    GETSTATIC ads.v : Lado;
    LDC "stone_axe"
    INVOKESPECIAL brw.a (Lado;Ljava/lang/String;)V
   L326
    LINENUMBER 1034 L326
    ALOAD 0
    GETSTATIC ads.w : Lado;
    LDC "diamond_sword"
    INVOKESPECIAL brw.a (Lado;Ljava/lang/String;)V
   L327
    LINENUMBER 1035 L327
    ALOAD 0
    GETSTATIC ads.x : Lado;
    LDC "diamond_shovel"
    INVOKESPECIAL brw.a (Lado;Ljava/lang/String;)V
   L328
    LINENUMBER 1036 L328
    ALOAD 0
    GETSTATIC ads.y : Lado;
    LDC "diamond_pickaxe"
    INVOKESPECIAL brw.a (Lado;Ljava/lang/String;)V
   L329
    LINENUMBER 1037 L329
    ALOAD 0
    GETSTATIC ads.z : Lado;
    LDC "diamond_axe"
    INVOKESPECIAL brw.a (Lado;Ljava/lang/String;)V
   L330
    LINENUMBER 1038 L330
    ALOAD 0
    GETSTATIC ads.A : Lado;
    LDC "stick"
    INVOKESPECIAL brw.a (Lado;Ljava/lang/String;)V
   L331
    LINENUMBER 1039 L331
    ALOAD 0
    GETSTATIC ads.B : Lado;
    LDC "bowl"
    INVOKESPECIAL brw.a (Lado;Ljava/lang/String;)V
   L332
    LINENUMBER 1040 L332
    ALOAD 0
    GETSTATIC ads.C : Lado;
    LDC "mushroom_stew"
    INVOKESPECIAL brw.a (Lado;Ljava/lang/String;)V
   L333
    LINENUMBER 1041 L333
    ALOAD 0
    GETSTATIC ads.D : Lado;
    LDC "golden_sword"
    INVOKESPECIAL brw.a (Lado;Ljava/lang/String;)V
   L334
    LINENUMBER 1042 L334
    ALOAD 0
    GETSTATIC ads.E : Lado;
    LDC "golden_shovel"
    INVOKESPECIAL brw.a (Lado;Ljava/lang/String;)V
   L335
    LINENUMBER 1043 L335
    ALOAD 0
    GETSTATIC ads.F : Lado;
    LDC "golden_pickaxe"
    INVOKESPECIAL brw.a (Lado;Ljava/lang/String;)V
   L336
    LINENUMBER 1044 L336
    ALOAD 0
    GETSTATIC ads.G : Lado;
    LDC "golden_axe"
    INVOKESPECIAL brw.a (Lado;Ljava/lang/String;)V
   L337
    LINENUMBER 1045 L337
    ALOAD 0
    GETSTATIC ads.H : Lado;
    LDC "string"
    INVOKESPECIAL brw.a (Lado;Ljava/lang/String;)V
   L338
    LINENUMBER 1046 L338
    ALOAD 0
    GETSTATIC ads.I : Lado;
    LDC "feather"
    INVOKESPECIAL brw.a (Lado;Ljava/lang/String;)V
   L339
    LINENUMBER 1047 L339
    ALOAD 0
    GETSTATIC ads.J : Lado;
    LDC "gunpowder"
    INVOKESPECIAL brw.a (Lado;Ljava/lang/String;)V
   L340
    LINENUMBER 1048 L340
    ALOAD 0
    GETSTATIC ads.K : Lado;
    LDC "wooden_hoe"
    INVOKESPECIAL brw.a (Lado;Ljava/lang/String;)V
   L341
    LINENUMBER 1049 L341
    ALOAD 0
    GETSTATIC ads.L : Lado;
    LDC "stone_hoe"
    INVOKESPECIAL brw.a (Lado;Ljava/lang/String;)V
   L342
    LINENUMBER 1050 L342
    ALOAD 0
    GETSTATIC ads.M : Lado;
    LDC "iron_hoe"
    INVOKESPECIAL brw.a (Lado;Ljava/lang/String;)V
   L343
    LINENUMBER 1051 L343
    ALOAD 0
    GETSTATIC ads.N : Lado;
    LDC "diamond_hoe"
    INVOKESPECIAL brw.a (Lado;Ljava/lang/String;)V
   L344
    LINENUMBER 1052 L344
    ALOAD 0
    GETSTATIC ads.O : Lado;
    LDC "golden_hoe"
    INVOKESPECIAL brw.a (Lado;Ljava/lang/String;)V
   L345
    LINENUMBER 1053 L345
    ALOAD 0
    GETSTATIC ads.P : Lado;
    LDC "wheat_seeds"
    INVOKESPECIAL brw.a (Lado;Ljava/lang/String;)V
   L346
    LINENUMBER 1054 L346
    ALOAD 0
    GETSTATIC ads.Q : Lado;
    LDC "wheat"
    INVOKESPECIAL brw.a (Lado;Ljava/lang/String;)V
   L347
    LINENUMBER 1055 L347
    ALOAD 0
    GETSTATIC ads.R : Lado;
    LDC "bread"
    INVOKESPECIAL brw.a (Lado;Ljava/lang/String;)V
   L348
    LINENUMBER 1056 L348
    ALOAD 0
    GETSTATIC ads.S : Labw;
    LDC "leather_helmet"
    INVOKESPECIAL brw.a (Lado;Ljava/lang/String;)V
   L349
    LINENUMBER 1057 L349
    ALOAD 0
    GETSTATIC ads.T : Labw;
    LDC "leather_chestplate"
    INVOKESPECIAL brw.a (Lado;Ljava/lang/String;)V
   L350
    LINENUMBER 1058 L350
    ALOAD 0
    GETSTATIC ads.U : Labw;
    LDC "leather_leggings"
    INVOKESPECIAL brw.a (Lado;Ljava/lang/String;)V
   L351
    LINENUMBER 1059 L351
    ALOAD 0
    GETSTATIC ads.V : Labw;
    LDC "leather_boots"
    INVOKESPECIAL brw.a (Lado;Ljava/lang/String;)V
   L352
    LINENUMBER 1060 L352
    ALOAD 0
    GETSTATIC ads.W : Labw;
    LDC "chainmail_helmet"
    INVOKESPECIAL brw.a (Lado;Ljava/lang/String;)V
   L353
    LINENUMBER 1061 L353
    ALOAD 0
    GETSTATIC ads.X : Labw;
    LDC "chainmail_chestplate"
    INVOKESPECIAL brw.a (Lado;Ljava/lang/String;)V
   L354
    LINENUMBER 1062 L354
    ALOAD 0
    GETSTATIC ads.Y : Labw;
    LDC "chainmail_leggings"
    INVOKESPECIAL brw.a (Lado;Ljava/lang/String;)V
   L355
    LINENUMBER 1063 L355
    ALOAD 0
    GETSTATIC ads.Z : Labw;
    LDC "chainmail_boots"
    INVOKESPECIAL brw.a (Lado;Ljava/lang/String;)V
   L356
    LINENUMBER 1064 L356
    ALOAD 0
    GETSTATIC ads.aa : Labw;
    LDC "iron_helmet"
    INVOKESPECIAL brw.a (Lado;Ljava/lang/String;)V
   L357
    LINENUMBER 1065 L357
    ALOAD 0
    GETSTATIC ads.ab : Labw;
    LDC "iron_chestplate"
    INVOKESPECIAL brw.a (Lado;Ljava/lang/String;)V
   L358
    LINENUMBER 1066 L358
    ALOAD 0
    GETSTATIC ads.ac : Labw;
    LDC "iron_leggings"
    INVOKESPECIAL brw.a (Lado;Ljava/lang/String;)V
   L359
    LINENUMBER 1067 L359
    ALOAD 0
    GETSTATIC ads.ad : Labw;
    LDC "iron_boots"
    INVOKESPECIAL brw.a (Lado;Ljava/lang/String;)V
   L360
    LINENUMBER 1068 L360
    ALOAD 0
    GETSTATIC ads.ae : Labw;
    LDC "diamond_helmet"
    INVOKESPECIAL brw.a (Lado;Ljava/lang/String;)V
   L361
    LINENUMBER 1069 L361
    ALOAD 0
    GETSTATIC ads.af : Labw;
    LDC "diamond_chestplate"
    INVOKESPECIAL brw.a (Lado;Ljava/lang/String;)V
   L362
    LINENUMBER 1070 L362
    ALOAD 0
    GETSTATIC ads.ag : Labw;
    LDC "diamond_leggings"
    INVOKESPECIAL brw.a (Lado;Ljava/lang/String;)V
   L363
    LINENUMBER 1071 L363
    ALOAD 0
    GETSTATIC ads.ah : Labw;
    LDC "diamond_boots"
    INVOKESPECIAL brw.a (Lado;Ljava/lang/String;)V
   L364
    LINENUMBER 1072 L364
    ALOAD 0
    GETSTATIC ads.ai : Labw;
    LDC "golden_helmet"
    INVOKESPECIAL brw.a (Lado;Ljava/lang/String;)V
   L365
    LINENUMBER 1073 L365
    ALOAD 0
    GETSTATIC ads.aj : Labw;
    LDC "golden_chestplate"
    INVOKESPECIAL brw.a (Lado;Ljava/lang/String;)V
   L366
    LINENUMBER 1074 L366
    ALOAD 0
    GETSTATIC ads.ak : Labw;
    LDC "golden_leggings"
    INVOKESPECIAL brw.a (Lado;Ljava/lang/String;)V
   L367
    LINENUMBER 1075 L367
    ALOAD 0
    GETSTATIC ads.al : Labw;
    LDC "golden_boots"
    INVOKESPECIAL brw.a (Lado;Ljava/lang/String;)V
   L368
    LINENUMBER 1076 L368
    ALOAD 0
    GETSTATIC ads.am : Lado;
    LDC "flint"
    INVOKESPECIAL brw.a (Lado;Ljava/lang/String;)V
   L369
    LINENUMBER 1077 L369
    ALOAD 0
    GETSTATIC ads.an : Lado;
    LDC "porkchop"
    INVOKESPECIAL brw.a (Lado;Ljava/lang/String;)V
   L370
    LINENUMBER 1078 L370
    ALOAD 0
    GETSTATIC ads.ao : Lado;
    LDC "cooked_porkchop"
    INVOKESPECIAL brw.a (Lado;Ljava/lang/String;)V
   L371
    LINENUMBER 1079 L371
    ALOAD 0
    GETSTATIC ads.ap : Lado;
    LDC "painting"
    INVOKESPECIAL brw.a (Lado;Ljava/lang/String;)V
   L372
    LINENUMBER 1080 L372
    ALOAD 0
    GETSTATIC ads.aq : Lado;
    LDC "golden_apple"
    INVOKESPECIAL brw.a (Lado;Ljava/lang/String;)V
   L373
    LINENUMBER 1081 L373
    ALOAD 0
    GETSTATIC ads.aq : Lado;
    ICONST_1
    LDC "golden_apple"
    INVOKEVIRTUAL brw.a (Lado;ILjava/lang/String;)V
   L374
    LINENUMBER 1082 L374
    ALOAD 0
    GETSTATIC ads.ar : Lado;
    LDC "sign"
    INVOKESPECIAL brw.a (Lado;Ljava/lang/String;)V
   L375
    LINENUMBER 1083 L375
    ALOAD 0
    GETSTATIC ads.as : Lado;
    LDC "oak_door"
    INVOKESPECIAL brw.a (Lado;Ljava/lang/String;)V
   L376
    LINENUMBER 1084 L376
    ALOAD 0
    GETSTATIC ads.at : Lado;
    LDC "spruce_door"
    INVOKESPECIAL brw.a (Lado;Ljava/lang/String;)V
   L377
    LINENUMBER 1085 L377
    ALOAD 0
    GETSTATIC ads.au : Lado;
    LDC "birch_door"
    INVOKESPECIAL brw.a (Lado;Ljava/lang/String;)V
   L378
    LINENUMBER 1086 L378
    ALOAD 0
    GETSTATIC ads.av : Lado;
    LDC "jungle_door"
    INVOKESPECIAL brw.a (Lado;Ljava/lang/String;)V
   L379
    LINENUMBER 1087 L379
    ALOAD 0
    GETSTATIC ads.aw : Lado;
    LDC "acacia_door"
    INVOKESPECIAL brw.a (Lado;Ljava/lang/String;)V
   L380
    LINENUMBER 1088 L380
    ALOAD 0
    GETSTATIC ads.ax : Lado;
    LDC "dark_oak_door"
    INVOKESPECIAL brw.a (Lado;Ljava/lang/String;)V
   L381
    LINENUMBER 1089 L381
    ALOAD 0
    GETSTATIC ads.ay : Lado;
    LDC "bucket"
    INVOKESPECIAL brw.a (Lado;Ljava/lang/String;)V
   L382
    LINENUMBER 1090 L382
    ALOAD 0
    GETSTATIC ads.az : Lado;
    LDC "water_bucket"
    INVOKESPECIAL brw.a (Lado;Ljava/lang/String;)V
   L383
    LINENUMBER 1091 L383
    ALOAD 0
    GETSTATIC ads.aA : Lado;
    LDC "lava_bucket"
    INVOKESPECIAL brw.a (Lado;Ljava/lang/String;)V
   L384
    LINENUMBER 1092 L384
    ALOAD 0
    GETSTATIC ads.aB : Lado;
    LDC "minecart"
    INVOKESPECIAL brw.a (Lado;Ljava/lang/String;)V
   L385
    LINENUMBER 1093 L385
    ALOAD 0
    GETSTATIC ads.aC : Lado;
    LDC "saddle"
    INVOKESPECIAL brw.a (Lado;Ljava/lang/String;)V
   L386
    LINENUMBER 1094 L386
    ALOAD 0
    GETSTATIC ads.aD : Lado;
    LDC "iron_door"
    INVOKESPECIAL brw.a (Lado;Ljava/lang/String;)V
   L387
    LINENUMBER 1095 L387
    ALOAD 0
    GETSTATIC ads.aE : Lado;
    LDC "redstone"
    INVOKESPECIAL brw.a (Lado;Ljava/lang/String;)V
   L388
    LINENUMBER 1096 L388
    ALOAD 0
    GETSTATIC ads.aF : Lado;
    LDC "snowball"
    INVOKESPECIAL brw.a (Lado;Ljava/lang/String;)V
   L389
    LINENUMBER 1097 L389
    ALOAD 0
    GETSTATIC ads.aG : Lado;
    LDC "oak_boat"
    INVOKESPECIAL brw.a (Lado;Ljava/lang/String;)V
   L390
    LINENUMBER 1098 L390
    ALOAD 0
    GETSTATIC ads.aH : Lado;
    LDC "spruce_boat"
    INVOKESPECIAL brw.a (Lado;Ljava/lang/String;)V
   L391
    LINENUMBER 1099 L391
    ALOAD 0
    GETSTATIC ads.aI : Lado;
    LDC "birch_boat"
    INVOKESPECIAL brw.a (Lado;Ljava/lang/String;)V
   L392
    LINENUMBER 1100 L392
    ALOAD 0
    GETSTATIC ads.aJ : Lado;
    LDC "jungle_boat"
    INVOKESPECIAL brw.a (Lado;Ljava/lang/String;)V
   L393
    LINENUMBER 1101 L393
    ALOAD 0
    GETSTATIC ads.aK : Lado;
    LDC "acacia_boat"
    INVOKESPECIAL brw.a (Lado;Ljava/lang/String;)V
   L394
    LINENUMBER 1102 L394
    ALOAD 0
    GETSTATIC ads.aL : Lado;
    LDC "dark_oak_boat"
    INVOKESPECIAL brw.a (Lado;Ljava/lang/String;)V
   L395
    LINENUMBER 1103 L395
    ALOAD 0
    GETSTATIC ads.aM : Lado;
    LDC "leather"
    INVOKESPECIAL brw.a (Lado;Ljava/lang/String;)V
   L396
    LINENUMBER 1104 L396
    ALOAD 0
    GETSTATIC ads.aN : Lado;
    LDC "milk_bucket"
    INVOKESPECIAL brw.a (Lado;Ljava/lang/String;)V
   L397
    LINENUMBER 1105 L397
    ALOAD 0
    GETSTATIC ads.aO : Lado;
    LDC "brick"
    INVOKESPECIAL brw.a (Lado;Ljava/lang/String;)V
   L398
    LINENUMBER 1106 L398
    ALOAD 0
    GETSTATIC ads.aP : Lado;
    LDC "clay_ball"
    INVOKESPECIAL brw.a (Lado;Ljava/lang/String;)V
   L399
    LINENUMBER 1107 L399
    ALOAD 0
    GETSTATIC ads.aQ : Lado;
    LDC "reeds"
    INVOKESPECIAL brw.a (Lado;Ljava/lang/String;)V
   L400
    LINENUMBER 1108 L400
    ALOAD 0
    GETSTATIC ads.aR : Lado;
    LDC "paper"
    INVOKESPECIAL brw.a (Lado;Ljava/lang/String;)V
   L401
    LINENUMBER 1109 L401
    ALOAD 0
    GETSTATIC ads.aS : Lado;
    LDC "book"
    INVOKESPECIAL brw.a (Lado;Ljava/lang/String;)V
   L402
    LINENUMBER 1110 L402
    ALOAD 0
    GETSTATIC ads.aT : Lado;
    LDC "slime_ball"
    INVOKESPECIAL brw.a (Lado;Ljava/lang/String;)V
   L403
    LINENUMBER 1111 L403
    ALOAD 0
    GETSTATIC ads.aU : Lado;
    LDC "chest_minecart"
    INVOKESPECIAL brw.a (Lado;Ljava/lang/String;)V
   L404
    LINENUMBER 1112 L404
    ALOAD 0
    GETSTATIC ads.aV : Lado;
    LDC "furnace_minecart"
    INVOKESPECIAL brw.a (Lado;Ljava/lang/String;)V
   L405
    LINENUMBER 1113 L405
    ALOAD 0
    GETSTATIC ads.aW : Lado;
    LDC "egg"
    INVOKESPECIAL brw.a (Lado;Ljava/lang/String;)V
   L406
    LINENUMBER 1114 L406
    ALOAD 0
    GETSTATIC ads.aX : Lado;
    LDC "compass"
    INVOKESPECIAL brw.a (Lado;Ljava/lang/String;)V
   L407
    LINENUMBER 1115 L407
    ALOAD 0
    GETSTATIC ads.aY : Ladi;
    LDC "fishing_rod"
    INVOKESPECIAL brw.a (Lado;Ljava/lang/String;)V
   L408
    LINENUMBER 1116 L408
    ALOAD 0
    GETSTATIC ads.aZ : Lado;
    LDC "clock"
    INVOKESPECIAL brw.a (Lado;Ljava/lang/String;)V
   L409
    LINENUMBER 1117 L409
    ALOAD 0
    GETSTATIC ads.ba : Lado;
    LDC "glowstone_dust"
    INVOKESPECIAL brw.a (Lado;Ljava/lang/String;)V
   L410
    LINENUMBER 1118 L410
    ALOAD 0
    GETSTATIC ads.bb : Lado;
    GETSTATIC adh$a.a : Ladh$a;
    INVOKEVIRTUAL adh$a.a ()I
    LDC "cod"
    INVOKEVIRTUAL brw.a (Lado;ILjava/lang/String;)V
   L411
    LINENUMBER 1119 L411
    ALOAD 0
    GETSTATIC ads.bb : Lado;
    GETSTATIC adh$a.b : Ladh$a;
    INVOKEVIRTUAL adh$a.a ()I
    LDC "salmon"
    INVOKEVIRTUAL brw.a (Lado;ILjava/lang/String;)V
   L412
    LINENUMBER 1120 L412
    ALOAD 0
    GETSTATIC ads.bb : Lado;
    GETSTATIC adh$a.c : Ladh$a;
    INVOKEVIRTUAL adh$a.a ()I
    LDC "clownfish"
    INVOKEVIRTUAL brw.a (Lado;ILjava/lang/String;)V
   L413
    LINENUMBER 1121 L413
    ALOAD 0
    GETSTATIC ads.bb : Lado;
    GETSTATIC adh$a.d : Ladh$a;
    INVOKEVIRTUAL adh$a.a ()I
    LDC "pufferfish"
    INVOKEVIRTUAL brw.a (Lado;ILjava/lang/String;)V
   L414
    LINENUMBER 1122 L414
    ALOAD 0
    GETSTATIC ads.bc : Lado;
    GETSTATIC adh$a.a : Ladh$a;
    INVOKEVIRTUAL adh$a.a ()I
    LDC "cooked_cod"
    INVOKEVIRTUAL brw.a (Lado;ILjava/lang/String;)V
   L415
    LINENUMBER 1123 L415
    ALOAD 0
    GETSTATIC ads.bc : Lado;
    GETSTATIC adh$a.b : Ladh$a;
    INVOKEVIRTUAL adh$a.a ()I
    LDC "cooked_salmon"
    INVOKEVIRTUAL brw.a (Lado;ILjava/lang/String;)V
   L416
    LINENUMBER 1124 L416
    ALOAD 0
    GETSTATIC ads.bd : Lado;
    GETSTATIC act.p : Lact;
    INVOKEVIRTUAL act.b ()I
    LDC "dye_black"
    INVOKEVIRTUAL brw.a (Lado;ILjava/lang/String;)V
   L417
    LINENUMBER 1125 L417
    ALOAD 0
    GETSTATIC ads.bd : Lado;
    GETSTATIC act.o : Lact;
    INVOKEVIRTUAL act.b ()I
    LDC "dye_red"
    INVOKEVIRTUAL brw.a (Lado;ILjava/lang/String;)V
   L418
    LINENUMBER 1126 L418
    ALOAD 0
    GETSTATIC ads.bd : Lado;
    GETSTATIC act.n : Lact;
    INVOKEVIRTUAL act.b ()I
    LDC "dye_green"
    INVOKEVIRTUAL brw.a (Lado;ILjava/lang/String;)V
   L419
    LINENUMBER 1127 L419
    ALOAD 0
    GETSTATIC ads.bd : Lado;
    GETSTATIC act.m : Lact;
    INVOKEVIRTUAL act.b ()I
    LDC "dye_brown"
    INVOKEVIRTUAL brw.a (Lado;ILjava/lang/String;)V
   L420
    LINENUMBER 1128 L420
    ALOAD 0
    GETSTATIC ads.bd : Lado;
    GETSTATIC act.l : Lact;
    INVOKEVIRTUAL act.b ()I
    LDC "dye_blue"
    INVOKEVIRTUAL brw.a (Lado;ILjava/lang/String;)V
   L421
    LINENUMBER 1129 L421
    ALOAD 0
    GETSTATIC ads.bd : Lado;
    GETSTATIC act.k : Lact;
    INVOKEVIRTUAL act.b ()I
    LDC "dye_purple"
    INVOKEVIRTUAL brw.a (Lado;ILjava/lang/String;)V
   L422
    LINENUMBER 1130 L422
    ALOAD 0
    GETSTATIC ads.bd : Lado;
    GETSTATIC act.j : Lact;
    INVOKEVIRTUAL act.b ()I
    LDC "dye_cyan"
    INVOKEVIRTUAL brw.a (Lado;ILjava/lang/String;)V
   L423
    LINENUMBER 1131 L423
    ALOAD 0
    GETSTATIC ads.bd : Lado;
    GETSTATIC act.i : Lact;
    INVOKEVIRTUAL act.b ()I
    LDC "dye_silver"
    INVOKEVIRTUAL brw.a (Lado;ILjava/lang/String;)V
   L424
    LINENUMBER 1132 L424
    ALOAD 0
    GETSTATIC ads.bd : Lado;
    GETSTATIC act.h : Lact;
    INVOKEVIRTUAL act.b ()I
    LDC "dye_gray"
    INVOKEVIRTUAL brw.a (Lado;ILjava/lang/String;)V
   L425
    LINENUMBER 1133 L425
    ALOAD 0
    GETSTATIC ads.bd : Lado;
    GETSTATIC act.g : Lact;
    INVOKEVIRTUAL act.b ()I
    LDC "dye_pink"
    INVOKEVIRTUAL brw.a (Lado;ILjava/lang/String;)V
   L426
    LINENUMBER 1134 L426
    ALOAD 0
    GETSTATIC ads.bd : Lado;
    GETSTATIC act.f : Lact;
    INVOKEVIRTUAL act.b ()I
    LDC "dye_lime"
    INVOKEVIRTUAL brw.a (Lado;ILjava/lang/String;)V
   L427
    LINENUMBER 1135 L427
    ALOAD 0
    GETSTATIC ads.bd : Lado;
    GETSTATIC act.e : Lact;
    INVOKEVIRTUAL act.b ()I
    LDC "dye_yellow"
    INVOKEVIRTUAL brw.a (Lado;ILjava/lang/String;)V
   L428
    LINENUMBER 1136 L428
    ALOAD 0
    GETSTATIC ads.bd : Lado;
    GETSTATIC act.d : Lact;
    INVOKEVIRTUAL act.b ()I
    LDC "dye_light_blue"
    INVOKEVIRTUAL brw.a (Lado;ILjava/lang/String;)V
   L429
    LINENUMBER 1137 L429
    ALOAD 0
    GETSTATIC ads.bd : Lado;
    GETSTATIC act.c : Lact;
    INVOKEVIRTUAL act.b ()I
    LDC "dye_magenta"
    INVOKEVIRTUAL brw.a (Lado;ILjava/lang/String;)V
   L430
    LINENUMBER 1138 L430
    ALOAD 0
    GETSTATIC ads.bd : Lado;
    GETSTATIC act.b : Lact;
    INVOKEVIRTUAL act.b ()I
    LDC "dye_orange"
    INVOKEVIRTUAL brw.a (Lado;ILjava/lang/String;)V
   L431
    LINENUMBER 1139 L431
    ALOAD 0
    GETSTATIC ads.bd : Lado;
    GETSTATIC act.a : Lact;
    INVOKEVIRTUAL act.b ()I
    LDC "dye_white"
    INVOKEVIRTUAL brw.a (Lado;ILjava/lang/String;)V
   L432
    LINENUMBER 1140 L432
    ALOAD 0
    GETSTATIC ads.be : Lado;
    LDC "bone"
    INVOKESPECIAL brw.a (Lado;Ljava/lang/String;)V
   L433
    LINENUMBER 1141 L433
    ALOAD 0
    GETSTATIC ads.bf : Lado;
    LDC "sugar"
    INVOKESPECIAL brw.a (Lado;Ljava/lang/String;)V
   L434
    LINENUMBER 1142 L434
    ALOAD 0
    GETSTATIC ads.bg : Lado;
    LDC "cake"
    INVOKESPECIAL brw.a (Lado;Ljava/lang/String;)V
   L435
    LINENUMBER 1143 L435
    ALOAD 0
    GETSTATIC ads.bh : Lado;
    LDC "bed"
    INVOKESPECIAL brw.a (Lado;Ljava/lang/String;)V
   L436
    LINENUMBER 1144 L436
    ALOAD 0
    GETSTATIC ads.bi : Lado;
    LDC "repeater"
    INVOKESPECIAL brw.a (Lado;Ljava/lang/String;)V
   L437
    LINENUMBER 1145 L437
    ALOAD 0
    GETSTATIC ads.bj : Lado;
    LDC "cookie"
    INVOKESPECIAL brw.a (Lado;Ljava/lang/String;)V
   L438
    LINENUMBER 1146 L438
    ALOAD 0
    GETSTATIC ads.bl : Lael;
    LDC "shears"
    INVOKESPECIAL brw.a (Lado;Ljava/lang/String;)V
   L439
    LINENUMBER 1147 L439
    ALOAD 0
    GETSTATIC ads.bm : Lado;
    LDC "melon"
    INVOKESPECIAL brw.a (Lado;Ljava/lang/String;)V
   L440
    LINENUMBER 1148 L440
    ALOAD 0
    GETSTATIC ads.bn : Lado;
    LDC "pumpkin_seeds"
    INVOKESPECIAL brw.a (Lado;Ljava/lang/String;)V
   L441
    LINENUMBER 1149 L441
    ALOAD 0
    GETSTATIC ads.bo : Lado;
    LDC "melon_seeds"
    INVOKESPECIAL brw.a (Lado;Ljava/lang/String;)V
   L442
    LINENUMBER 1150 L442
    ALOAD 0
    GETSTATIC ads.bp : Lado;
    LDC "beef"
    INVOKESPECIAL brw.a (Lado;Ljava/lang/String;)V
   L443
    LINENUMBER 1151 L443
    ALOAD 0
    GETSTATIC ads.bq : Lado;
    LDC "cooked_beef"
    INVOKESPECIAL brw.a (Lado;Ljava/lang/String;)V
   L444
    LINENUMBER 1152 L444
    ALOAD 0
    GETSTATIC ads.br : Lado;
    LDC "chicken"
    INVOKESPECIAL brw.a (Lado;Ljava/lang/String;)V
   L445
    LINENUMBER 1153 L445
    ALOAD 0
    GETSTATIC ads.bs : Lado;
    LDC "cooked_chicken"
    INVOKESPECIAL brw.a (Lado;Ljava/lang/String;)V
   L446
    LINENUMBER 1154 L446
    ALOAD 0
    GETSTATIC ads.bv : Lado;
    LDC "rabbit"
    INVOKESPECIAL brw.a (Lado;Ljava/lang/String;)V
   L447
    LINENUMBER 1155 L447
    ALOAD 0
    GETSTATIC ads.bw : Lado;
    LDC "cooked_rabbit"
    INVOKESPECIAL brw.a (Lado;Ljava/lang/String;)V
   L448
    LINENUMBER 1156 L448
    ALOAD 0
    GETSTATIC ads.bt : Lado;
    LDC "mutton"
    INVOKESPECIAL brw.a (Lado;Ljava/lang/String;)V
   L449
    LINENUMBER 1157 L449
    ALOAD 0
    GETSTATIC ads.bu : Lado;
    LDC "cooked_mutton"
    INVOKESPECIAL brw.a (Lado;Ljava/lang/String;)V
   L450
    LINENUMBER 1158 L450
    ALOAD 0
    GETSTATIC ads.by : Lado;
    LDC "rabbit_foot"
    INVOKESPECIAL brw.a (Lado;Ljava/lang/String;)V
   L451
    LINENUMBER 1159 L451
    ALOAD 0
    GETSTATIC ads.bz : Lado;
    LDC "rabbit_hide"
    INVOKESPECIAL brw.a (Lado;Ljava/lang/String;)V
   L452
    LINENUMBER 1160 L452
    ALOAD 0
    GETSTATIC ads.bx : Lado;
    LDC "rabbit_stew"
    INVOKESPECIAL brw.a (Lado;Ljava/lang/String;)V
   L453
    LINENUMBER 1161 L453
    ALOAD 0
    GETSTATIC ads.bA : Lado;
    LDC "rotten_flesh"
    INVOKESPECIAL brw.a (Lado;Ljava/lang/String;)V
   L454
    LINENUMBER 1162 L454
    ALOAD 0
    GETSTATIC ads.bB : Lado;
    LDC "ender_pearl"
    INVOKESPECIAL brw.a (Lado;Ljava/lang/String;)V
   L455
    LINENUMBER 1163 L455
    ALOAD 0
    GETSTATIC ads.bC : Lado;
    LDC "blaze_rod"
    INVOKESPECIAL brw.a (Lado;Ljava/lang/String;)V
   L456
    LINENUMBER 1164 L456
    ALOAD 0
    GETSTATIC ads.bD : Lado;
    LDC "ghast_tear"
    INVOKESPECIAL brw.a (Lado;Ljava/lang/String;)V
   L457
    LINENUMBER 1165 L457
    ALOAD 0
    GETSTATIC ads.bE : Lado;
    LDC "gold_nugget"
    INVOKESPECIAL brw.a (Lado;Ljava/lang/String;)V
   L458
    LINENUMBER 1166 L458
    ALOAD 0
    GETSTATIC ads.bF : Lado;
    LDC "nether_wart"
    INVOKESPECIAL brw.a (Lado;Ljava/lang/String;)V
   L459
    LINENUMBER 1167 L459
    ALOAD 0
    GETSTATIC ads.cV : Lado;
    LDC "beetroot"
    INVOKESPECIAL brw.a (Lado;Ljava/lang/String;)V
   L460
    LINENUMBER 1168 L460
    ALOAD 0
    GETSTATIC ads.cU : Lado;
    LDC "beetroot_seeds"
    INVOKESPECIAL brw.a (Lado;Ljava/lang/String;)V
   L461
    LINENUMBER 1169 L461
    ALOAD 0
    GETSTATIC ads.cW : Lado;
    LDC "beetroot_soup"
    INVOKESPECIAL brw.a (Lado;Ljava/lang/String;)V
   L462
    LINENUMBER 1170 L462
    ALOAD 0
    GETSTATIC ads.bG : Laed;
    LDC "bottle_drinkable"
    INVOKESPECIAL brw.a (Lado;Ljava/lang/String;)V
   L463
    LINENUMBER 1171 L463
    ALOAD 0
    GETSTATIC ads.bH : Laed;
    LDC "bottle_splash"
    INVOKESPECIAL brw.a (Lado;Ljava/lang/String;)V
   L464
    LINENUMBER 1172 L464
    ALOAD 0
    GETSTATIC ads.bI : Laed;
    LDC "bottle_lingering"
    INVOKESPECIAL brw.a (Lado;Ljava/lang/String;)V
   L465
    LINENUMBER 1173 L465
    ALOAD 0
    GETSTATIC ads.bJ : Lado;
    LDC "glass_bottle"
    INVOKESPECIAL brw.a (Lado;Ljava/lang/String;)V
   L466
    LINENUMBER 1174 L466
    ALOAD 0
    GETSTATIC ads.bK : Lado;
    LDC "dragon_breath"
    INVOKESPECIAL brw.a (Lado;Ljava/lang/String;)V
   L467
    LINENUMBER 1175 L467
    ALOAD 0
    GETSTATIC ads.bL : Lado;
    LDC "spider_eye"
    INVOKESPECIAL brw.a (Lado;Ljava/lang/String;)V
   L468
    LINENUMBER 1176 L468
    ALOAD 0
    GETSTATIC ads.bM : Lado;
    LDC "fermented_spider_eye"
    INVOKESPECIAL brw.a (Lado;Ljava/lang/String;)V
   L469
    LINENUMBER 1177 L469
    ALOAD 0
    GETSTATIC ads.bN : Lado;
    LDC "blaze_powder"
    INVOKESPECIAL brw.a (Lado;Ljava/lang/String;)V
   L470
    LINENUMBER 1178 L470
    ALOAD 0
    GETSTATIC ads.bO : Lado;
    LDC "magma_cream"
    INVOKESPECIAL brw.a (Lado;Ljava/lang/String;)V
   L471
    LINENUMBER 1179 L471
    ALOAD 0
    GETSTATIC ads.bP : Lado;
    LDC "brewing_stand"
    INVOKESPECIAL brw.a (Lado;Ljava/lang/String;)V
   L472
    LINENUMBER 1180 L472
    ALOAD 0
    GETSTATIC ads.bQ : Lado;
    LDC "cauldron"
    INVOKESPECIAL brw.a (Lado;Ljava/lang/String;)V
   L473
    LINENUMBER 1181 L473
    ALOAD 0
    GETSTATIC ads.bR : Lado;
    LDC "ender_eye"
    INVOKESPECIAL brw.a (Lado;Ljava/lang/String;)V
   L474
    LINENUMBER 1182 L474
    ALOAD 0
    GETSTATIC ads.bS : Lado;
    LDC "speckled_melon"
    INVOKESPECIAL brw.a (Lado;Ljava/lang/String;)V
   L475
    LINENUMBER 1183 L475
    ALOAD 0
    GETFIELD brw.d : Lbni;
    GETSTATIC ads.bT : Lado;
    NEW brw$5
    DUP
    ALOAD 0
    INVOKESPECIAL brw$5.<init> (Lbrw;)V
    INVOKEVIRTUAL bni.a (Lado;Lbnj;)V
   L476
    LINENUMBER 1190 L476
    ALOAD 0
    GETSTATIC ads.bU : Lado;
    LDC "experience_bottle"
    INVOKESPECIAL brw.a (Lado;Ljava/lang/String;)V
   L477
    LINENUMBER 1191 L477
    ALOAD 0
    GETSTATIC ads.bV : Lado;
    LDC "fire_charge"
    INVOKESPECIAL brw.a (Lado;Ljava/lang/String;)V
   L478
    LINENUMBER 1192 L478
    ALOAD 0
    GETSTATIC ads.bW : Lado;
    LDC "writable_book"
    INVOKESPECIAL brw.a (Lado;Ljava/lang/String;)V
   L479
    LINENUMBER 1193 L479
    ALOAD 0
    GETSTATIC ads.bY : Lado;
    LDC "emerald"
    INVOKESPECIAL brw.a (Lado;Ljava/lang/String;)V
   L480
    LINENUMBER 1194 L480
    ALOAD 0
    GETSTATIC ads.bZ : Lado;
    LDC "item_frame"
    INVOKESPECIAL brw.a (Lado;Ljava/lang/String;)V
   L481
    LINENUMBER 1195 L481
    ALOAD 0
    GETSTATIC ads.ca : Lado;
    LDC "flower_pot"
    INVOKESPECIAL brw.a (Lado;Ljava/lang/String;)V
   L482
    LINENUMBER 1196 L482
    ALOAD 0
    GETSTATIC ads.cb : Lado;
    LDC "carrot"
    INVOKESPECIAL brw.a (Lado;Ljava/lang/String;)V
   L483
    LINENUMBER 1197 L483
    ALOAD 0
    GETSTATIC ads.cc : Lado;
    LDC "potato"
    INVOKESPECIAL brw.a (Lado;Ljava/lang/String;)V
   L484
    LINENUMBER 1198 L484
    ALOAD 0
    GETSTATIC ads.cd : Lado;
    LDC "baked_potato"
    INVOKESPECIAL brw.a (Lado;Ljava/lang/String;)V
   L485
    LINENUMBER 1199 L485
    ALOAD 0
    GETSTATIC ads.ce : Lado;
    LDC "poisonous_potato"
    INVOKESPECIAL brw.a (Lado;Ljava/lang/String;)V
   L486
    LINENUMBER 1200 L486
    ALOAD 0
    GETSTATIC ads.cf : Lacy;
    LDC "map"
    INVOKESPECIAL brw.a (Lado;Ljava/lang/String;)V
   L487
    LINENUMBER 1201 L487
    ALOAD 0
    GETSTATIC ads.cg : Lado;
    LDC "golden_carrot"
    INVOKESPECIAL brw.a (Lado;Ljava/lang/String;)V
   L488
    LINENUMBER 1202 L488
    ALOAD 0
    GETSTATIC ads.ch : Lado;
    ICONST_0
    LDC "skull_skeleton"
    INVOKEVIRTUAL brw.a (Lado;ILjava/lang/String;)V
   L489
    LINENUMBER 1203 L489
    ALOAD 0
    GETSTATIC ads.ch : Lado;
    ICONST_1
    LDC "skull_wither"
    INVOKEVIRTUAL brw.a (Lado;ILjava/lang/String;)V
   L490
    LINENUMBER 1204 L490
    ALOAD 0
    GETSTATIC ads.ch : Lado;
    ICONST_2
    LDC "skull_zombie"
    INVOKEVIRTUAL brw.a (Lado;ILjava/lang/String;)V
   L491
    LINENUMBER 1205 L491
    ALOAD 0
    GETSTATIC ads.ch : Lado;
    ICONST_3
    LDC "skull_char"
    INVOKEVIRTUAL brw.a (Lado;ILjava/lang/String;)V
   L492
    LINENUMBER 1206 L492
    ALOAD 0
    GETSTATIC ads.ch : Lado;
    ICONST_4
    LDC "skull_creeper"
    INVOKEVIRTUAL brw.a (Lado;ILjava/lang/String;)V
   L493
    LINENUMBER 1207 L493
    ALOAD 0
    GETSTATIC ads.ch : Lado;
    ICONST_5
    LDC "skull_dragon"
    INVOKEVIRTUAL brw.a (Lado;ILjava/lang/String;)V
   L494
    LINENUMBER 1208 L494
    ALOAD 0
    GETSTATIC ads.ci : Lado;
    LDC "carrot_on_a_stick"
    INVOKESPECIAL brw.a (Lado;Ljava/lang/String;)V
   L495
    LINENUMBER 1209 L495
    ALOAD 0
    GETSTATIC ads.cj : Lado;
    LDC "nether_star"
    INVOKESPECIAL brw.a (Lado;Ljava/lang/String;)V
   L496
    LINENUMBER 1210 L496
    ALOAD 0
    GETSTATIC ads.cP : Lado;
    LDC "end_crystal"
    INVOKESPECIAL brw.a (Lado;Ljava/lang/String;)V
   L497
    LINENUMBER 1211 L497
    ALOAD 0
    GETSTATIC ads.ck : Lado;
    LDC "pumpkin_pie"
    INVOKESPECIAL brw.a (Lado;Ljava/lang/String;)V
   L498
    LINENUMBER 1212 L498
    ALOAD 0
    GETSTATIC ads.cm : Lado;
    LDC "firework_charge"
    INVOKESPECIAL brw.a (Lado;Ljava/lang/String;)V
   L499
    LINENUMBER 1213 L499
    ALOAD 0
    GETSTATIC ads.co : Lado;
    LDC "comparator"
    INVOKESPECIAL brw.a (Lado;Ljava/lang/String;)V
   L500
    LINENUMBER 1214 L500
    ALOAD 0
    GETSTATIC ads.cp : Lado;
    LDC "netherbrick"
    INVOKESPECIAL brw.a (Lado;Ljava/lang/String;)V
   L501
    LINENUMBER 1215 L501
    ALOAD 0
    GETSTATIC ads.cq : Lado;
    LDC "quartz"
    INVOKESPECIAL brw.a (Lado;Ljava/lang/String;)V
   L502
    LINENUMBER 1216 L502
    ALOAD 0
    GETSTATIC ads.cr : Lado;
    LDC "tnt_minecart"
    INVOKESPECIAL brw.a (Lado;Ljava/lang/String;)V
   L503
    LINENUMBER 1217 L503
    ALOAD 0
    GETSTATIC ads.cs : Lado;
    LDC "hopper_minecart"
    INVOKESPECIAL brw.a (Lado;Ljava/lang/String;)V
   L504
    LINENUMBER 1218 L504
    ALOAD 0
    GETSTATIC ads.ct : Labx;
    LDC "armor_stand"
    INVOKESPECIAL brw.a (Lado;Ljava/lang/String;)V
   L505
    LINENUMBER 1219 L505
    ALOAD 0
    GETSTATIC ads.cu : Lado;
    LDC "iron_horse_armor"
    INVOKESPECIAL brw.a (Lado;Ljava/lang/String;)V
   L506
    LINENUMBER 1220 L506
    ALOAD 0
    GETSTATIC ads.cv : Lado;
    LDC "golden_horse_armor"
    INVOKESPECIAL brw.a (Lado;Ljava/lang/String;)V
   L507
    LINENUMBER 1221 L507
    ALOAD 0
    GETSTATIC ads.cw : Lado;
    LDC "diamond_horse_armor"
    INVOKESPECIAL brw.a (Lado;Ljava/lang/String;)V
   L508
    LINENUMBER 1222 L508
    ALOAD 0
    GETSTATIC ads.cx : Lado;
    LDC "lead"
    INVOKESPECIAL brw.a (Lado;Ljava/lang/String;)V
   L509
    LINENUMBER 1223 L509
    ALOAD 0
    GETSTATIC ads.cy : Lado;
    LDC "name_tag"
    INVOKESPECIAL brw.a (Lado;Ljava/lang/String;)V
   L510
    LINENUMBER 1224 L510
    ALOAD 0
    GETFIELD brw.d : Lbni;
    GETSTATIC ads.cO : Lado;
    NEW brw$6
    DUP
    ALOAD 0
    INVOKESPECIAL brw$6.<init> (Lbrw;)V
    INVOKEVIRTUAL bni.a (Lado;Lbnj;)V
   L511
    LINENUMBER 1231 L511
    ALOAD 0
    GETFIELD brw.d : Lbni;
    GETSTATIC ads.cQ : Lado;
    NEW brw$7
    DUP
    ALOAD 0
    INVOKESPECIAL brw$7.<init> (Lbrw;)V
    INVOKEVIRTUAL bni.a (Lado;Lbnj;)V
   L512
    LINENUMBER 1238 L512
    ALOAD 0
    GETSTATIC ads.cR : Lado;
    LDC "elytra"
    INVOKESPECIAL brw.a (Lado;Ljava/lang/String;)V
   L513
    LINENUMBER 1239 L513
    ALOAD 0
    GETSTATIC ads.cS : Lado;
    LDC "chorus_fruit"
    INVOKESPECIAL brw.a (Lado;Ljava/lang/String;)V
   L514
    LINENUMBER 1240 L514
    ALOAD 0
    GETSTATIC ads.cT : Lado;
    LDC "chorus_fruit_popped"
    INVOKESPECIAL brw.a (Lado;Ljava/lang/String;)V
   L515
    LINENUMBER 1241 L515
    ALOAD 0
    GETSTATIC ads.cA : Lado;
    LDC "record_13"
    INVOKESPECIAL brw.a (Lado;Ljava/lang/String;)V
   L516
    LINENUMBER 1242 L516
    ALOAD 0
    GETSTATIC ads.cB : Lado;
    LDC "record_cat"
    INVOKESPECIAL brw.a (Lado;Ljava/lang/String;)V
   L517
    LINENUMBER 1243 L517
    ALOAD 0
    GETSTATIC ads.cC : Lado;
    LDC "record_blocks"
    INVOKESPECIAL brw.a (Lado;Ljava/lang/String;)V
   L518
    LINENUMBER 1244 L518
    ALOAD 0
    GETSTATIC ads.cD : Lado;
    LDC "record_chirp"
    INVOKESPECIAL brw.a (Lado;Ljava/lang/String;)V
   L519
    LINENUMBER 1245 L519
    ALOAD 0
    GETSTATIC ads.cE : Lado;
    LDC "record_far"
    INVOKESPECIAL brw.a (Lado;Ljava/lang/String;)V
   L520
    LINENUMBER 1246 L520
    ALOAD 0
    GETSTATIC ads.cF : Lado;
    LDC "record_mall"
    INVOKESPECIAL brw.a (Lado;Ljava/lang/String;)V
   L521
    LINENUMBER 1247 L521
    ALOAD 0
    GETSTATIC ads.cG : Lado;
    LDC "record_mellohi"
    INVOKESPECIAL brw.a (Lado;Ljava/lang/String;)V
   L522
    LINENUMBER 1248 L522
    ALOAD 0
    GETSTATIC ads.cH : Lado;
    LDC "record_stal"
    INVOKESPECIAL brw.a (Lado;Ljava/lang/String;)V
   L523
    LINENUMBER 1249 L523
    ALOAD 0
    GETSTATIC ads.cI : Lado;
    LDC "record_strad"
    INVOKESPECIAL brw.a (Lado;Ljava/lang/String;)V
   L524
    LINENUMBER 1250 L524
    ALOAD 0
    GETSTATIC ads.cJ : Lado;
    LDC "record_ward"
    INVOKESPECIAL brw.a (Lado;Ljava/lang/String;)V
   L525
    LINENUMBER 1251 L525
    ALOAD 0
    GETSTATIC ads.cK : Lado;
    LDC "record_11"
    INVOKESPECIAL brw.a (Lado;Ljava/lang/String;)V
   L526
    LINENUMBER 1252 L526
    ALOAD 0
    GETSTATIC ads.cL : Lado;
    LDC "record_wait"
    INVOKESPECIAL brw.a (Lado;Ljava/lang/String;)V
   L527
    LINENUMBER 1253 L527
    ALOAD 0
    GETSTATIC ads.cM : Lado;
    LDC "prismarine_shard"
    INVOKESPECIAL brw.a (Lado;Ljava/lang/String;)V
   L528
    LINENUMBER 1254 L528
    ALOAD 0
    GETSTATIC ads.cN : Lado;
    LDC "prismarine_crystals"
    INVOKESPECIAL brw.a (Lado;Ljava/lang/String;)V
   L529
    LINENUMBER 1255 L529
    ALOAD 0
    GETFIELD brw.d : Lbni;
    GETSTATIC ads.cn : Lacz;
    NEW brw$8
    DUP
    ALOAD 0
    INVOKESPECIAL brw$8.<init> (Lbrw;)V
    INVOKEVIRTUAL bni.a (Lado;Lbnj;)V
   L530
    LINENUMBER 1262 L530
    ALOAD 0
    GETFIELD brw.d : Lbni;
    GETSTATIC ads.bk : Ladw;
    NEW brw$9
    DUP
    ALOAD 0
    INVOKESPECIAL brw$9.<init> (Lbrw;)V
    INVOKEVIRTUAL bni.a (Lado;Lbnj;)V
   L531
    LINENUMBER 1269 L531
    ALOAD 0
    GETSTATIC aju.bX : Lajt;
    LDC "command_block"
    INVOKESPECIAL brw.a (Lajt;Ljava/lang/String;)V
   L532
    LINENUMBER 1270 L532
    ALOAD 0
    GETSTATIC ads.cl : Lado;
    LDC "fireworks"
    INVOKESPECIAL brw.a (Lado;Ljava/lang/String;)V
   L533
    LINENUMBER 1271 L533
    ALOAD 0
    GETSTATIC ads.cz : Lado;
    LDC "command_block_minecart"
    INVOKESPECIAL brw.a (Lado;Ljava/lang/String;)V
   L534
    LINENUMBER 1272 L534
    ALOAD 0
    GETSTATIC aju.cv : Lajt;
    LDC "barrier"
    INVOKESPECIAL brw.a (Lajt;Ljava/lang/String;)V
   L535
    LINENUMBER 1273 L535
    ALOAD 0
    GETSTATIC aju.ac : Lajt;
    LDC "mob_spawner"
    INVOKESPECIAL brw.a (Lajt;Ljava/lang/String;)V
   L536
    LINENUMBER 1274 L536
    ALOAD 0
    GETSTATIC ads.bX : Lado;
    LDC "written_book"
    INVOKESPECIAL brw.a (Lado;Ljava/lang/String;)V
   L537
    LINENUMBER 1275 L537
    ALOAD 0
    GETSTATIC aju.bg : Lajt;
    GETSTATIC amh$a.k : Lamh$a;
    INVOKEVIRTUAL amh$a.a ()I
    LDC "brown_mushroom_block"
    INVOKEVIRTUAL brw.a (Lajt;ILjava/lang/String;)V
   L538
    LINENUMBER 1276 L538
    ALOAD 0
    GETSTATIC aju.bh : Lajt;
    GETSTATIC amh$a.k : Lamh$a;
    INVOKEVIRTUAL amh$a.a ()I
    LDC "red_mushroom_block"
    INVOKEVIRTUAL brw.a (Lajt;ILjava/lang/String;)V
   L539
    LINENUMBER 1277 L539
    ALOAD 0
    GETSTATIC aju.bI : Lajt;
    LDC "dragon_egg"
    INVOKESPECIAL brw.a (Lajt;Ljava/lang/String;)V
   L540
    LINENUMBER 1278 L540
    ALOAD 0
    GETSTATIC aju.dc : Lajt;
    LDC "repeating_command_block"
    INVOKESPECIAL brw.a (Lajt;Ljava/lang/String;)V
   L541
    LINENUMBER 1279 L541
    ALOAD 0
    GETSTATIC aju.dd : Lajt;
    LDC "chain_command_block"
    INVOKESPECIAL brw.a (Lajt;Ljava/lang/String;)V
   L542
    LINENUMBER 1280 L542
    ALOAD 0
    GETSTATIC aju.df : Lajt;
    GETSTATIC aqp$a.a : Laqp$a;
    INVOKEVIRTUAL aqp$a.a ()I
    LDC "structure_block"
    INVOKEVIRTUAL brw.a (Lajt;ILjava/lang/String;)V
   L543
    LINENUMBER 1281 L543
    ALOAD 0
    GETSTATIC aju.df : Lajt;
    GETSTATIC aqp$a.b : Laqp$a;
    INVOKEVIRTUAL aqp$a.a ()I
    LDC "structure_block"
    INVOKEVIRTUAL brw.a (Lajt;ILjava/lang/String;)V
   L544
    LINENUMBER 1282 L544
    ALOAD 0
    GETSTATIC aju.df : Lajt;
    GETSTATIC aqp$a.c : Laqp$a;
    INVOKEVIRTUAL aqp$a.a ()I
    LDC "structure_block"
    INVOKEVIRTUAL brw.a (Lajt;ILjava/lang/String;)V
   L545
    LINENUMBER 1283 L545
    ALOAD 0
    GETSTATIC aju.df : Lajt;
    GETSTATIC aqp$a.d : Laqp$a;
    INVOKEVIRTUAL aqp$a.a ()I
    LDC "structure_block"
    INVOKEVIRTUAL brw.a (Lajt;ILjava/lang/String;)V
   L546
    LINENUMBER 1285 L546
    GETSTATIC net/optifine/reflect/Reflector.ModelLoader_onRegisterItems : Lnet/optifine/reflect/ReflectorMethod;
    INVOKEVIRTUAL net/optifine/reflect/ReflectorMethod.exists ()Z
    IFEQ L547
   L548
    LINENUMBER 1286 L548
    GETSTATIC net/optifine/reflect/Reflector.ModelLoader_onRegisterItems : Lnet/optifine/reflect/ReflectorMethod;
    ICONST_1
    ANEWARRAY java/lang/Object
    DUP
    ICONST_0
    ALOAD 0
    GETFIELD brw.d : Lbni;
    AASTORE
    INVOKESTATIC net/optifine/reflect/Reflector.call (Lnet/optifine/reflect/ReflectorMethod;[Ljava/lang/Object;)Ljava/lang/Object;
    POP
   L547
    LINENUMBER 1288 L547
   FRAME FULL [brw] []
    RETURN
   L549
    LOCALVARIABLE this Lbrw; L0 L549 0
    MAXSTACK = 5
    MAXLOCALS = 1

  // access flags 0x1
  public a(Lbwd;)V
   L0
    LINENUMBER 1292 L0
    ALOAD 0
    GETFIELD brw.d : Lbni;
    INVOKEVIRTUAL bni.b ()V
   L1
    LINENUMBER 1293 L1
    RETURN
   L2
    LOCALVARIABLE this Lbrw; L0 L2 0
    LOCALVARIABLE resourceManager Lbwd; L0 L2 1
    MAXSTACK = 1
    MAXLOCALS = 2

  // access flags 0x8
  static <clinit>()V
   L0
    LINENUMBER 69 L0
    NEW kl
    DUP
    LDC "textures/misc/enchanted_item_glint.png"
    INVOKESPECIAL kl.<init> (Ljava/lang/String;)V
    PUTSTATIC brw.b : Lkl;
    RETURN
    MAXSTACK = 3
    MAXLOCALS = 0
}
